Workbook

Sheet Summary
B1: USME Customer Contract Register - Summary
B3: As-of date (edit to roll forward) | C3: 46305
B4: Documents reviewed | C4: =COUNTA(Register[File Name]) -> 275
B6: Documents by status
B7: Active | C7: =COUNTIF(Register[Status],B7) -> 134
B8: Likely Active - verify | C8: =COUNTIF(Register[Status],B8) -> 18
B9: Unclear - verify | C9: =COUNTIF(Register[Status],B9) -> 12
B10: Expired | C10: =COUNTIF(Register[Status],B10) -> 85
B11: Reference/Superseded | C11: =COUNTIF(Register[Status],B11) -> 26
B13: Active / likely-active documents expiring
B14: Past stated expiry, no auto-renew projection (holdover / verify) | C14: =COUNTIFS(Register[Status],"<>Expired",Register[Status],"<>Reference/Superseded",Register[Days to Expiry],">="&-100000,Register[Days to Expiry],"<="&-1) -> 35
B15: Within 90 days | C15: =COUNTIFS(Register[Status],"<>Expired",Register[Status],"<>Reference/Superseded",Register[Days to Expiry],">="&0,Register[Days to Expiry],"<="&90) -> 10
B16: 91-180 days | C16: =COUNTIFS(Register[Status],"<>Expired",Register[Status],"<>Reference/Superseded",Register[Days to Expiry],">="&91,Register[Days to Expiry],"<="&180) -> 10
B17: 181-365 days | C17: =COUNTIFS(Register[Status],"<>Expired",Register[Status],"<>Reference/Superseded",Register[Days to Expiry],">="&181,Register[Days to Expiry],"<="&365) -> 30
B18: Beyond 12 months | C18: =COUNTIFS(Register[Status],"<>Expired",Register[Status],"<>Reference/Superseded",Register[Days to Expiry],">="&366,Register[Days to Expiry],"<="&100000) -> 74
B19: No determinable expiry date | C19: =COUNTIFS(Register[Status],"<>Expired",Register[Status],"<>Reference/Superseded",Register[Expiration Date],"") -> 5
B21: Documents by type (all)
B22: Amendment | C22: =COUNTIF(Register[Doc Type],B22) -> 45
B23: Extension | C23: =COUNTIF(Register[Doc Type],B23) -> 23
B24: GPO Agreement | C24: =COUNTIF(Register[Doc Type],B24) -> 34
B25: GPO Letter of Participation/SIP | C25: =COUNTIF(Register[Doc Type],B25) -> 34
B26: Master/Rental Agreement | C26: =COUNTIF(Register[Doc Type],B26) -> 100
B27: Notice/Other | C27: =COUNTIF(Register[Doc Type],B27) -> 1
B28: Pricing Exhibit | C28: =COUNTIF(Register[Doc Type],B28) -> 5
B29: Purchase/Sale Agreement | C29: =COUNTIF(Register[Doc Type],B29) -> 7
B30: Rebate Agreement | C30: =COUNTIF(Register[Doc Type],B30) -> 10
B31: Service Agreement/SOW | C31: =COUNTIF(Register[Doc Type],B31) -> 16
B33: Data quality
B34: Confidence: High | C34: =COUNTIF(Register[Confidence],"High") -> 172
B35: Confidence: Medium | C35: =COUNTIF(Register[Confidence],"Medium") -> 101
B36: Confidence: Low | C36: =COUNTIF(Register[Confidence],"Low") -> 2
B37: Read via OCR (scanned PDFs) | C37: =COUNTIF(Register[Text Source],"OCR") -> 98

Sheet Contract Register
A1: Customer Group | B1: Counterparty (as written) | C1: Folder | D1: File Name | E1: Doc Type | F1: Service Lines | G1: GPO / Contract # | H1: USME Entity | I1: Effective Date | J1: Expiration (as stated) | K1: Expiration Date | L1: Exp. Date Source | M1: Projected Term End (auto-renew roll-fwd) | N1: Days to Expiry | O1: Status | P1: Initial Term | Q1: Renewal | R1: Termination | S1: Pricing Basis | T1: Price Increase / Escalator | U1: Rebate / Admin Fee | V1: Commitment / Exclusivity | W1: Payment Terms | X1: Liability / Risk Terms | Y1: Key Notes | Z1: Confidence | AA1: Text Source
A2: Advantus Health Partners (Bon Secours Mercy) | B2: Advantage Health Partners LLC d/b/a Advantus Health Partners (on behalf of AHP and its Buyers) | C2: Advantus | D2: Advantus HP MME_BTS Exp 6.30.28_auto.pdf | E2: GPO Agreement | F2: MME Rental, BTS Rental | G2: Advantus AHP-MM-0034 | H2: US Med-Equip, LLC | I2: 2025-04-14 | J2: 2028-04-13 | K2: 46856 | L2: Contract text | N2: =IF(M2<>"",M2-Summary!$C$3,IF(K2="","",K2-Summary!$C$3)) -> 551 | O2: Active | P2: 3 years | Q2: Auto-renews 1-yr terms until terminated | R2: Either party (Vendor or AHP), 90 days written notice, without penalty; every LOP must allow mutual 90-day no-cause termination; vendor must give 90-day transition | S2: Exhibit B (MME) and B-1 (BTS) daily rates; two tiers: Tier 1 Access (no commitment) and Tier 2 Provider 90% | T2: Fixed for initial 3 years; thereafter vendor may modify B-1 pricing not more than once annually with documentation via written amendment | U2: AHP administrative fee 3% of aggregate purchases; any rebates paid directly to Buyers; Value Add per Exhibit D | V2: Tier 2 requires 90% rental spend commitment, USME primary vendor, business line reviews; 60-day notice/cure before tier reduction | W2: Net 30 from receipt of uncontested invoice, electronic; Buyers pay no late penalties or interest | X2: AHP Exhibit A terms control; Buyers are third-party beneficiaries; mutual consequential damages exclusion; assignment needs consent; audit (vendor pays if >5% under/overcharge); auto liability $1M | Y2: AHP is BSMH-affiliated GPO; covers MME and BTS for participating facilities via LOP. Filename says Exp 6/30/28 but text gives 3-year term from 4/14/2025 (~4/13/2028) with auto-renewal. | Z2: High | AA2: Text
A3: AdventHealth | B3: Adventist Health System Sunbelt Healthcare Corporation d/b/a AdventHealth | C3: AdventHealth | D3: PP-NS-1565 US Med-Equip A1.docx.pdf | E3: Amendment | F3: BTS Rental, Other | G3: Premier PP-NS-1565 | H3: US Med-Equip, LLC | I3: 2025-10-01 | J3: Not stated (follows underlying PP-NS-1565 supplement agreement) | L3: Unknown | N3: =IF(M3<>"",M3-Summary!$C$3,IF(K3="","",K3-Summary!$C$3)) | O3: Active | P3: Not stated | Q3: Not stated | R3: Not stated | S3: Adds one item to Schedule 1: Stryker Medical Extender Kit (item 59739) at $13.11/EA | T3: Not stated | U3: Not stated | V3: Not stated | W3: Not stated | X3: Not stated | Y3: Amendment 1 to AdventHealth GPO supplement agreement under Premier PP-NS-1565 adding a Stryker extender kit; signed 10/24/2025 by Doug Pytlinski (AdventHealth) and Tim Heck (USME). Term and other terms governed by the underlying supplement. | Z3: High | AA3: Text
A4: AdventHealth | B4: Adventist Health System Sunbelt Healthcare Corporation d/b/a AdventHealth | C4: AdventHealth | D4: AdventHealth BTS_Exp_03_01_31.pdf | E4: GPO Letter of Participation/SIP | F4: BTS Rental, MME Rental | G4: Premier PP-NS-1565 (supplement) | H4: US Med-Equip, LLC | I4: 2025-10-01 | J4: 2031-03-01 | K4: 47908 | L4: Contract text | N4: =IF(M4<>"",M4-Summary!$C$3,IF(K4="","",K4-Summary!$C$3)) -> 1603 | O4: Active | P4: ~5.4 years (Oct 1, 2025 to Mar 1, 2031) | Q4: None stated; continues if new Premier GPO award, else Premier terms survive as individual agreement | R4: Either party, 30 days prior written notice; AdventHealth may terminate immediately if Supplier fails credentialing | S4: Schedule B fixed daily rates per model (Premier-based supplement pricing) | T4: Not stated; no pass-through of taxes/tariffs permitted | U4: 2% rebate on aggregate sales + additional 2% multi-service line rebate (BTS + MME primary, 90% first call each, DSO <=30); paid annually 45 days after anniversary | V4: 90% first-call annual purchase commitment for beds/mattresses/therapeutic surfaces rental | W4: Per Premier GPO Agreement; DSO must not exceed 30 days for rebate | X4: KPIs: 98% fill rate, delivery within 2 hrs + drive time, pickup 24 hrs (billing stops on notice), 24-hr replacement; TLS1.2/AES-256 data security, third-party risk review | Y4: Supplement to Premier PP-NS-1565 covering AdventHealth facilities (Schedule A); includes rental equity discount (25%) and lost-equipment buyout policy. Agreement outlasts Premier agreement term. | Z4: High | AA4: Text
A5: AdventHealth | B5: Adventist Health System Sunbelt Healthcare Corporation d/b/a AdventHealth | C5: AdventHealth | D5: AdventHealth_Amendment_Verticles_Exp_03_01_31.pdf | E5: Rebate Agreement | F5: BTS Rental, MME Rental | G5: Premier PP-NS-1565 (Patient Beds-Rental), SP-NS-2139 (Peak Use Rental) | H5: US Med-Equip, LLC | I5: 2026-04-01 | J5: 2031-03-01 | K5: 47908 | L5: Contract text | N5: =IF(M5<>"",M5-Summary!$C$3,IF(K5="","",K5-Summary!$C$3)) -> 1603 | O5: Active | P5: ~5 years (2026-04-01 to 2031-03-01) | Q5: None stated | R5: Either party, without cause, 30 days written notice (all or part / by product); immediate if credentialing fails | S5: Per GPO contracts listed in Exhibit A (Premier PP-NS-1565, SP-NS-2139); 'Master Product Incentive Agreement' AH-CI-6370 | T5: Not stated | U5: 2% rebate on aggregate net sales + additional 2% multi-service-line rebate if USME primary for beds and MME (90% first call), DSO <=30 days; paid 45 days after anniversary | V5: 90% first-call commitment for Patient Beds and Peak Use Rental; no penalty for facility reductions; clinical-issue product removal without liability | W5: Not stated in agreement (rebate conditioned on DSO <=30 days; disputes within 15 days of invoice) | X5: Supplier liability cap = 12 months' fees, carve-outs for injury, indemnity, confidentiality, HIPAA, negligence; broad supplier indemnity; insurance $5M/$10M CGL, $5M auto, $5M EL | Y5: Health-system incentive agreement layering rebates over Premier contracts for all AdventHealth facilities (auto-adds new facilities). Filename says 'Amendment' but document is a new Master Product Incentive Agreement; rebate section cites Exhibit C but rebate is Exhibit B. | Z5: High | AA5: Text
A6: Adventist Health (West) | B6: Adventist Health System/West | C6: Adventist West | D6: AdventistHealth West_MME BTS_Exp 03.31.2029_auto renew.pdf | E6: Amendment | F6: MME Rental, BTS Rental | G6: Direct | H6: US Med-Equip, LLC | I6: 2026-04-01 | J6: Not stated in amendment (filename: 2029-03-31, auto renew) | K6: 47208 | L6: Contract text | N6: =IF(M6<>"",M6-Summary!$C$3,IF(K6="","",K6-Summary!$C$3)) -> 903 | O6: Active | P6: Not stated | Q6: Not stated in amendment (filename indicates auto-renew) | R6: Not stated | S6: Per underlying Equipment Rental Agreement; Non-Owned Facilities load pricing via Exhibit 1.1 Letter of Participation | T6: Not stated | U6: Not stated | V6: Not stated | W6: Not stated | X6: Adventist Health disclaims liability for Non-Owned (affiliate acute) facilities' obligations | Y6: First Amendment replacing Attachment B Covered Facilities (~25 acute facilities in CA/OR/HI plus non-acute entities) and adding a LOP for non-owned affiliates. Base agreement (eff. 4/1/2026) not in this file; expiry taken from filename only. | Z6: Medium | AA6: Text
A7: Adventist Health (West) | B7: Adventist Health System/West | C7: Adventist Health - CA | D7: Adventist Health BTS Exp 3.31.29.pdf | E7: Master/Rental Agreement | F7: MME Rental, BTS Rental, Respiratory, Restraints/Posey | G7: Vizient CE9205, CE7782 (incorporated by reference) | H7: US Med-Equip, LLC | I7: 2026-04-01 | J7: 2029-03-31 | K7: 47208 | L7: Contract text | N7: =IF(M7<>"",M7-Summary!$C$3,IF(K7="","",K7-Summary!$C$3)) -> 903 | O7: Active | P7: 3 years | Q7: Auto-renews successive 1-yr terms | R7: After Initial Term, either party without cause on 60 days written notice; breach with 60-day cure | S7: Daily rates per Attachment A (MME and BTS); Primary Vendor pricing; April 2026 MME rent waived as conversion incentive (skip billing) | T7: Fixed for Initial Term; thereafter up to 3% once per contract year with 30 days notice | U7: USME pays Vizient GPO admin fees and sales reports per Vizient agreements | V7: Primary Vendor: 90%+ of annual rental spend for covered facilities; 120-day cure, then list pricing until cured | W7: Net 30 via ACH/wire; 1.5%/month interest on undisputed past due; credit hold/repossession rights | X7: Customer responsible for loss/damage and must insure at replacement cost; mutual indemnity; no consequential damages; USME GL $1M/$3M; assignment requires USME consent; Delaware law | Y7: Conversion from incumbent across ~30 Adventist Health West acute facilities in CA/OR (Attachment B); 2-hour plus drive time delivery commitment. Filename says BTS but agreement covers both MME and BTS. | Z7: High | AA7: Text
A8: Adventist HealthCare (MD) | B8: Adventist Healthcare (Maryland) | C8: Adventist MD | D8: Adventist_Healthcare_MD_Rental_Agreement_Exp_8_31_2030.pdf | E8: Master/Rental Agreement | F8: BTS Rental | G8: Direct | H8: US Med-Equip, LLC | I8: 2025-09-01 | J8: 2030-08-31 | K8: 47726 | L8: Contract text | N8: =IF(M8<>"",M8-Summary!$C$3,IF(K8="","",K8-Summary!$C$3)) -> 1421 | O8: Active | P8: 5 years | Q8: Auto-renews successive 1-yr terms | R8: Either party, 60 days written notice without cause, only after Initial Term; 60-day cure for breach | S8: Daily rates per Attachment A (Primary Vendor pricing); contract # AD08262025JS | T8: Fixed until 2nd anniversary; then max 1x/yr by greater of 5% or prior-yr Medical Care CPI-U, 30 days notice (email OK) | U8: Not stated | V8: Primary Vendor: 90%+ of annual rental spend; 60-day cure, else list pricing for remaining term | W8: Net 30 via ACH/wire; interest at max legal rate on past due; repossession/credit hold/list pricing on non-payment | X8: Customer liable for loss/damage and must insure equipment at replacement cost; mutual indemnity; no consequential damages; USME CGL $1M/$3M; customer may not assign w/o consent; TX law, Harris County | Y8: Covers Fort Washington MC and White Oak MC (Attachment B). Strong USME-favorable terms incl. escalator and list-price fallback for commitment breach. | Z8: High | AA8: Text
A9: Allegheny Health Network (Highmark Health) | B9: Allegheny Health Network | C9: Allegheny Health - MME | D9: Allegheny MME _Exp_2_28_30.pdf | E9: Master/Rental Agreement | F9: MME Rental, Respiratory | G9: Direct | H9: US Med-Equip, LLC | I9: 2025-03-01 | J9: 2030-02-28 | K9: 47542 | L9: Contract text | N9: =IF(M9<>"",M9-Summary!$C$3,IF(K9="","",K9-Summary!$C$3)) -> 1237 | O9: Active | P9: 5 years | Q9: Auto-renews successive 1-yr terms | R9: Either party without cause on 30 days written notice; 60-day cure for breach | S9: Daily/monthly rental rates per Attachment A (Preferred Vendor pricing; list price shown for safe harbor reporting); Contract #09202024JS | T9: Not stated | U9: Not stated | V9: Preferred vendor: customer to place 90%+ of annual rental spend for Attachment A equipment with USME at Covered Facilities (Att. B); 60-day cure, else then-applicable pricing | W9: Net 30; USME may repossess or put customer on credit hold for non-payment | X9: Customer liable for loss/damage and must insure equipment at replacement cost; full new-equipment cost if not surrendered; broad USME indemnity; no assignment without consent; CGL $1M/$3M | Y9: 5-year preferred-vendor MME deal with 90% spend commitment, but either party can exit on 30 days notice, which weakens the commitment. AHN exhibits C-G (AI, data security, BAA) add obligations. | Z9: High | AA9: Text
A10: Allegheny Health Network (Vizient) | B10: Vizient Supply, LLC for the benefit of Allegheny Health Network (AHN) | C10: Allegheny Health - Beds | D10: AHN US Med-Equip Bariatric Bed Rentals Addendum Exp 2_29_2028.pdf | E10: Amendment | F10: BTS Rental | G10: Vizient CE9205AB (formerly CE3363AB) | H10: US Med-Equip, LLC | I10: 2025-03-01 | J10: 2028-02-29 | K10: 46812 | L10: Contract text | N10: =IF(M10<>"",M10-Summary!$C$3,IF(K10="","",K10-Summary!$C$3)) -> 507 | O10: Active | P10: Not stated (addendum expires 2/29/2028) | Q10: None stated | R10: Vizient may terminate without cause on 90 days written notice; auto-terminates if base agreement CE9205 terminates | S10: Not stated in amendment (per underlying addendum) | T10: Not stated | U10: Not stated | V10: Not stated | W10: Not stated | X10: Not stated | Y10: Amends AHN bariatric & therapeutic beds addendum: extends to 2/29/2028 and re-points base agreement from CE3363 to Vizient CE9205 (dated 3/1/2025); sales to be reported under CE9205. | Z10: High | AA10: Text
A11: Amber Well Health | B11: Amber Well Health Hiawatha | C11: Amber Well | D11: Amber Well Health Hiawatha_Rental_Agreement_Exp_02_28_26.pdf | E11: Master/Rental Agreement | F11: BTS Rental, MME Rental | G11: Direct | H11: US Med-Equip, LLC | I11: 2025-03-01 | J11: 2027-02-28 (current auto-renewal term; initial term ended 2026-02-28) | K11: 46446 | L11: Contract text | N11: =IF(M11<>"",M11-Summary!$C$3,IF(K11="","",K11-Summary!$C$3)) -> 141 | O11: Active | P11: 1 year | Q11: Auto-renews successive 1-yr terms | R11: Either party, 30 days written notice without cause after Initial Term; 60-day cure for breach | S11: Daily/monthly rates per Attachment A; Primary Vendor pricing (BTS + MME cribs) | T11: Fixed until 2nd anniversary (2027-03-01); then max once/yr, greater of 5% or prior-yr Medical Care CPI-U, 30 days notice (email OK) | U11: Not stated | V11: Primary Vendor: 90%+ of annual rental spend; 60-day cure, else list pricing for remainder of term | W11: Net 30; late interest lesser of 1.5%/mo or legal max; credit-hold and list pricing on non-payment | X11: Customer liable for loss/damage and must insure equipment at replacement cost; mutual indemnity; no consequential damages; USME CGL $1M/$3M; full new-unit cost if not surrendered | Y11: Single Kansas critical-access hospital (Hiawatha, KS), contract KS02072025HCH. Mostly BTS (Freedom Wave, Nuvay surfaces) plus cribs. Filename expiry 2/28/26 is end of initial term; auto-renewed. | Z11: High | AA11: OCR
A12: AMG Integrated Healthcare | B12: Houston-AMG Specialty Hospital, Inc. | C12: AMG/Houston | D12: AMG Houston Biomed Service_Exp_06_30_29.pdf | E12: Service Agreement/SOW | F12: Biomed/Repair Service | G12: Direct | H12: US Med-Equip, LLC | I12: 2026-07-01 | J12: 2029-06-30 | K12: 47299 | L12: Contract text | N12: =IF(M12<>"",M12-Summary!$C$3,IF(K12="","",K12-Summary!$C$3)) -> 994 | O12: Active | P12: 3 years | Q12: Auto-renews successive 1-yr terms | R12: Customer may terminate without cause on 60 days written notice at any time; after Initial Term either party 60 days; customer termination for unsatisfactory PM after 30-day cure | S12: Fixed PM fee for customer-owned equipment (Exhibit A): $2,980/month, $35,760/year; parts excluded | T12: Annual CPI-U adjustment, lesser of 3% or CPI-U increase | U12: Not stated | V12: Non-exclusive; no minimum/maximum volume guarantees | W12: Net 30 from receipt of undisputed invoice; 1.5%/month late fee; USME may suspend services for late payment | X12: USME liability capped at total agreement price; no consequential damages; mutual indemnity; insurance $1M/$3M GL & professional; exclusions for misuse, acts of God, customer modifications | Y12: Annual on-site preventive maintenance (inspection, testing, calibration, documentation) on hospital-owned equipment per Exhibit A (e.g., Zoll defibrillators); repairs, parts and software excluded. Contract ID 05052601HP. Customer's anytime 60-day convenience termination undercuts the 3-year term. | Z12: High | AA12: Text
A13: AMG Specialty Hospital | B13: Clear Lake-AMG Specialty Hospital, Inc. | C13: AMG/Clear Lake | D13: AMG Clear Lake Biomed Service_Exp_06_30_29.pdf | E13: Service Agreement/SOW | F13: Biomed/Repair Service | G13: Direct | H13: US Med-Equip, LLC | I13: 2026-07-01 | J13: 2029-06-30 | K13: 47299 | L13: Contract text | N13: =IF(M13<>"",M13-Summary!$C$3,IF(K13="","",K13-Summary!$C$3)) -> 994 | O13: Active | P13: 3 years | Q13: Auto-renews successive 1-yr terms | R13: Customer may terminate without cause on 60 days written notice anytime; after Initial Term either party on 60 days notice; customer may terminate for unsatisfactory PM after 30-day cure | S13: Annual PM (excl. parts) on hospital-owned equipment in Exhibit A: $3,705.63/month, $44,467.50/year (Contract ID 05052601HP) | T13: Annual CPI-U adjustment, capped at lesser of 3% or CPI | U13: None | V13: Non-exclusive; no volume minimums or guarantees | W13: Net 30 from receipt of undisputed invoice; 1.5%/month late fee; USME may suspend services for late payment | X13: USME liability capped at total contract price; no consequential damages; mutual indemnity; CGL/professional $1M/$3M; parts, repairs, software excluded | Y13: Biomed PM-only contract on customer-owned equipment (defibrillators, ECGs, etc.); parts and corrective repairs excluded. Customer has 60-day termination for convenience from day one. | Z13: High | AA13: Text
A14: Ascension (The Resource Group) | B14: Ascension Health Resource and Supply Management Group, LLC (The Resource Group) | C14: GPO/The Resource Group | D14: Resource Group_MME_3_31_2029.pdf | E14: Amendment | F14: MME Rental | G14: The Resource Group USMED-0170211 | H14: US Med-Equip LLC | I14: 2026-04-01 (Amendment 003; agreement dated 2023-02-15) | J14: 2029-03-31 | K14: 47208 | L14: Contract text | N14: =IF(M14<>"",M14-Summary!$C$3,IF(K14="","",K14-Summary!$C$3)) -> 903 | O14: Active | P14: Not stated | Q14: Not stated | R14: Not stated in amendment | S14: Exhibit 1 (Appendix A-2) daily/monthly rates vs list price | T14: Supplier may request price change once annually for material cost changes; 30-day good-faith negotiation, else may remove part number | U14: Contract admin fee 5%; 3% conversion rebate on first 12 months (requires 90% compliance, DSO <=30, non-stackable) | V14: Primary vendor: >=90% of annual MME rental spend (aggregate); up to 25% premium on non-compliant participants after 30-day notice + 60-day cure; 90-day transition | W14: Net 30 via ACH/wire; interest 1.5% on undisputed sums >45 days past due; credit-hold, list pricing, repossession rights | X14: No MFN/pricing parity (special promotions need not be extended); rebate reporting late interest | Y14: Amendment 003 extends Ascension TRG MME agreement to 3/31/2029, raises admin fee to 5%, adds Appendix O primary provider terms. Document contains bank remittance details. | Z14: High | AA14: Text
A15: Atlantic Health System | B15: Atlantic Health System, Inc. | C15: Atlantic Health System | D15: Atlantic Health_BTS_Exp_11_14_30.pdf | E15: Master/Rental Agreement | F15: BTS Rental | G15: Premier PP-NS-1565 (GPO fees traced) | H15: US Med-Equip, LLC | I15: 2025-05-01 (signed 2025-11-12) | J15: 2030-04-30 (5 yrs from effective date; filename says 11/14/30) | K15: 47603 | L15: Contract text | N15: =IF(M15<>"",M15-Summary!$C$3,IF(K15="","",K15-Summary!$C$3)) -> 1298 | O15: Active | P15: 5 years | Q15: Successive 1-yr renewals by mutual written consent | R15: After Initial Term, either party without cause on 30 days written notice; breach with 60-day cure | S15: Attachment A daily/monthly rates; primary vendor pricing (list pricing if 80% commitment not cured in 60 days) | T15: Fixed until 2nd anniversary; then max once/yr, greater of 5% or Medical Care CPI-U, 30 days notice | U15: Quarterly rebate: Yr1 8%, Yrs 2-5+ 3%; requires 80% BTS commitment, DSO <=30, ACH payment; no stacking with other rebates | V15: Primary vendor: 80%+ of annual BTS rental spend; 60-day cure else list pricing | W15: Net 30 via ACH/wire; interest on past due at max legal rate; USME may suspend service | X15: Customer liable for loss/damage of equipment and must insure at replacement cost; mutual indemnity; CGL $1M/$3M; delivery 4 hrs avg, pickup 24 hrs avg; assignment needs consent (customer merger exempt) | Y15: Covers 9 Atlantic facilities in NJ incl. CentraState and Morristown. Filename expiry 11/14/30 conflicts with 5-yr term from 5/1/2025 effective date (text implies 4/30/2030). | Z15: High | AA15: Text
... A21: Centra Health | B21: Centra Health | C21: Centra Health | D21: Centra Health BTS Exp 12_21_2028.pdf | E21: Master/Rental Agreement | F21: BTS Rental, MME Rental, Asset Mgmt/On-site | G21: Direct (Contract # CH010324JS) | H21: US Med-Equip, LLC | I21: 2023-12-22 | J21: 2028-12-21 | K21: 47108 | L21: Contract text | N21: =IF(M21<>"",M21-Summary!$C$3,IF(K21="","",K21-Summary!$C$3)) -> 803 | O21: Active | P21: 5 years | Q21: Auto-renews successive 1-yr terms | R21: Either party without cause on 60 days notice, only after Initial Term | S21: Primary Vendor daily rates per Attachment A (Freedom 1000 $55.00, Freedom 500 $27.55, Pronova-O2 $1,400); 25% Rental Equity Discount option | T21: Fixed 2 yrs; then once per contract year up to greater of 5% or Medical Care CPI-U, 30 days notice | U21: Not stated | V21: Primary vendor: 80%+ of annual rental spend for Attachment A equipment types; after 60-day cure, market rates apply | W21: Net 30; late interest 1.5%/month (18%/yr); credit hold/repossession rights | X21: Customer liable for loss/damage repair/replacement and must insure at replacement cost; mutual indemnity; no consequential damages; USME CGL $1M/$3M | Y21: Covers Lynchburg General, Virginia Baptist, Centra Specialty Hospital (Lynchburg, VA). EMR integration at no charge. Virginia law. | Z21: High | AA21: Text
A22: CHOMP (Montage Health) | B22: Community Hospital of the Monterey Peninsula | C22: Community Hospital of the Monterey Peninsula (CHOMP) | D22: CHOMP_BTS_Exp_1_31_2026.docx | E22: Master/Rental Agreement | F22: BTS Rental, MME Rental | G22: Direct (Vizient Tier 4 pricing referenced) | H22: US Med-Equip, LLC | I22: 2022-10-11 | J22: 2025-10-11 initial; auto-renewed to 2026-10-11 | K22: 45941 | L22: Contract text | M22: 46306 | N22: =IF(M22<>"",M22-Summary!$C$3,IF(K22="","",K22-Summary!$C$3)) -> 1 | O22: Active | P22: 3 years | Q22: Auto-renews successive 1-yr terms | R22: Either party without cause, 30 days written notice | S22: Vizient Tier 4 daily rates per Attachment A (bariatric beds, low beds, Posey/Freedom Safe beds, transfer devices); consignment, no charge until used | T22: Not stated | U22: None stated; value-adds include 25% rental equity credit toward buyout and 50% lost-equipment buyout credit | V22: Primary vendor: 90%+ of annual rental spend for Attachment B facilities | W22: Net 30; USME may repossess on non-payment; customer pays collection/attorney fees | X22: Customer liable for loss/damage and abuse repairs; full new-unit cost if not returned in good condition; mutual indemnity; USME CGL $1M/$3M; Texas law, Harris County venue | Y22: Consigned peak-use BTS/bariatric equipment at CHOMP. Filename says Exp 1/31/2026 but text gives 3-yr term from 10/11/2022 with auto-renewal; primary vendor clause text says MME although equipment is BTS. CHOMP BTS amendment exp 9/30/2027 also on file. | Z22: Medium | AA22: Text
A23: CHOMP (Montage Health) | B23: Community Hospital of the Monterey Peninsula | C23: Community Hospital of the Monterey Peninsula (CHOMP) | D23: CHOMP amedment BTS_Exp_09_30_2027.pdf | E23: Amendment | F23: BTS Rental | G23: Direct | H23: US Med-Equip, LLC | I23: 2025-09-01 | J23: 2027-09-30 | K23: 46660 | L23: Contract text | N23: =IF(M23<>"",M23-Summary!$C$3,IF(K23="","",K23-Summary!$C$3)) -> 355 | O23: Active | P23: Not stated (extension of agreement dated 2025-08-13) | Q23: Not stated; further changes by mutual written amendment | R23: Per underlying agreement (not stated here) | S23: Daily rates per Attachment A: VersaTech 1100 ULB Drive $82.22; VersaTech 600 2.0 / 600 ULB $29.00; Rotec VersaTech 1100 bariatric low bed $57.00 | T23: Not stated | U23: Not stated | V23: Not stated | W23: Not stated | X23: Not stated | Y23: Extends Equipment Rental Agreement (contract UCIMC1012022TH, dated 2025-08-13) to 9/30/2027 and adds bariatric bed items. Contract number appears reused from a UCI template; verify. Amendment section 1 text truncated. | Z23: Medium | AA23: OCR
A24: CHRISTUS Health | B24: CHRISTUS Health | C24: Christus Health | D24: CHRISTUS Refurb Purchase Agreement exp_12_31_2021_auto renew.pdf | E24: Purchase/Sale Agreement | F24: Refurb Equipment Sales, Biomed/Repair Service | G24: Direct | H24: US Med-Equip, Inc. | I24: 2017-01-01; Amendment 2018-07-24 | J24: 2021-12-31 initial; auto-renews 1-yr terms (current term to 2026-12-31 if not terminated) | K24: 44561 | L24: Contract text | M24: 46387 | N24: =IF(M24<>"",M24-Summary!$C$3,IF(K24="","",K24-Summary!$C$3)) -> 82 | O24: Active | P24: 5 years | Q24: Auto-renews successive 1-yr terms | R24: Either party without cause on 30 days written notice; breach w/15-day cure; Facility immediate for cause | S24: Fixed purchase prices per Exhibit A/Attachment 1 (refurb/new Philips, Physio, Zoll defibs; flat repair after warranty); $125/hr bench rate non-warranty | T24: Supplier provides then-current published list price each Jan 1; discounts per table | U24: Not stated | V24: None stated | W24: Monthly invoicing to CHRISTUS AP; terms not legible in excerpt | X24: Broad supplier indemnity; insurance GL $1M/$2M, auto $1M, E&O $1M, cyber $10M, umbrella $1M; no assignment w/o consent; 5-yr/12-mo bench warranties | Y24: Refurbished defibrillator sales and repair agreement; 2018 amendment added products, pricing and participating facilities. Evergreen renewal per text. | Z24: Medium | AA24: OCR
A25: CHRISTUS Health | B25: CHRISTUS Health | C25: Christus Health | D25: CHRISTUS-US Med Equip-Respiratory Subordinate Agreement_Exp01_04_29.pdf | E25: Purchase/Sale Agreement | F25: Respiratory, Biomed/Repair Service | G25: Direct | H25: US Med-Equip LLC | I25: 2026-01-05 | J25: 2029-01-04 | K25: 47122 | L25: Contract text | N25: =IF(M25<>"",M25-Summary!$C$3,IF(K25="","",K25-Summary!$C$3)) -> 817 | O25: Active | P25: 3 years | Q25: None stated (governed by Master Purchasing Agreement eff. 2026-01-05) | R25: Not stated in subordinate agreement (Master Agreement controls); auto-terminates for facilities that cease to qualify | S25: Fixed purchase prices per Attachment 1 (e.g., Airon pNeuton Model A ventilator start-up kit $9,841.40); trade-in allowances at USME discretion | T25: Not stated | U25: Not stated | V25: Not stated; quotation-compliance warranty with refund of overcharges | W25: Not stated (Applicable Rate for late = lesser of 1.5%/mo or legal max) | X25: SLA: phone support within 30 min (10% monthly service credit if missed); Urban FSE onsite 2 hrs (service extension penalty); pass-through OEM uptime/warranty; 12-mo parts warranty; perpetual software license; IT access controls | Y25: Subordinate purchasing agreement under CHRISTUS Master Purchasing Agreement for respiratory/ventilator products (Airon pNeuton transport ventilators) at CHRISTUS St. Michael (Texarkana/Atlanta TX) facilities. Service/PM obligations attach if service purchased. | Z25: Medium | AA25: OCR
A26: CHRISTUS Health | B26: CHRISTUS Health | C26: Christus Health | D26: CHRISTUS-US Med Equip-Master Agreement_Exp01_04_29.pdf | E26: Master/Rental Agreement | F26: MME Rental, Biomed/Repair Service, Refurb Equipment Sales | G26: Direct | H26: US Med-Equip LLC | I26: 2026-01-05 | J26: 2036-01-04 per text (10-yr term); filename says 01/04/29 | K26: 49678 | L26: Contract text | N26: =IF(M26<>"",M26-Summary!$C$3,IF(K26="","",K26-Summary!$C$3)) -> 3373 | O26: Active | P26: 10 years; survives while any Subordinate Agreement remains in effect | Q26: None stated | R26: No convenience termination stated; either party for material breach (30-day cure); CHRISTUS immediate for cause (safety, reputation, exclusion, false reps) or regulatory issues | S26: Master Purchasing Agreement; pricing set in separate Subordinate Agreements per Facility | T26: Firm pricing: no increases during Subordinate Agreement Term unless stated therein; decreases must be offered to all Facilities | U26: Not stated | V26: None stated; Facilities not obligated to buy across Subordinate Agreements; failure to supply -> USME pays price difference for Competing Product | W26: Facility pays within 30 days of receipt of compliant invoice; equipment purchases 80% on delivery / 20% on acceptance; no handling fees | X26: MFN: prices/terms must equal or beat any other customer, with refunds of difference; insurance: GL $1M/$2M, auto $1M, E&O $1M, cyber $1M, umbrella $5M; assignment needs consent (affiliate/M&A allowed with notice) | Y26: Umbrella MSA signed 1/6/2026 governing all CHRISTUS Subordinate Agreements; Catholic ERDs, HIPAA, MDS2 forms due within 30 days of each Subordinate Agreement. Filename expiry (1/4/2029) conflicts with 10-yr term in text; may reflect a Subordinate Agreement term. | Z26: High | AA26: OCR
A27: ClearSky Health | B27: ClearSky Health | C27: ClearSky Health | D27: ClearSky Health MME BTS Exp_5_31_26_LR.pdf | E27: Master/Rental Agreement | F27: MME Rental | G27: Direct | H27: US Med-Equip, LLC | I27: 2023-06-01 | J27: 2027-05-31 (current auto-renewal term; initial term ended 2026-05-31) | K27: 46538 | L27: Contract text | N27: =IF(M27<>"",M27-Summary!$C$3,IF(K27="","",K27-Summary!$C$3)) -> 233 | O27: Active | P27: 3 years | Q27: Auto-renews successive 1-yr terms | R27: Either party, 30 days written notice without cause (any time) | S27: Monthly rental rates per Attachment A; Primary Vendor pricing | T27: Not stated | U27: Not stated | V27: Primary Vendor: 90%+ of annual MME rental spend for Attachment B facilities | W27: Net 30 | X27: Customer liable for loss/damage and abuse repairs plus USME enforcement/collection costs; full new-unit cost if not surrendered; USME CGL $1M/$3M; customer may not assign without consent | Y27: Contract 06082023LR with New Mexico rehab operator. Only MME monthly pricing visible in OCR (no BTS pricing found despite 'MME BTS' filename). Attachment B facility list not captured. | Z27: Medium | AA27: OCR
A28: ClearSky Health | B28: ClearSky Health | C28: ClearSky Health | D28: ClearSky_Agreement_Exp_9_30_27_2_29_28.pdf | E28: Master/Rental Agreement | F28: MME Rental, BTS Rental | G28: Vizient CE7782 (MME Tier 3) and Vizient CE9205 (BTS Tier 3) | H28: US Med-Equip, LLC | I28: 2025-05-06 | J28: 2028-05-05 (initial term; auto-renews) | K28: 46878 | L28: Contract text | N28: =IF(M28<>"",M28-Summary!$C$3,IF(K28="","",K28-Summary!$C$3)) -> 573 | O28: Active | P28: 3 years | Q28: Auto-renews successive 1-yr terms | R28: After Initial Term only: either party, without cause, 60 days written notice | S28: Vizient CE7782 Tier 3 (90% commitment) for MME; Vizient CE9205 Tier 3 (80% commitment) for beds/surfaces; fixed for term | T28: Fixed for term (pricing effective for term of contract) | U28: Not stated | V28: Primary vendor: 90% of MME rental spend, 80% of BTS rental spend; 60-day cure then list pricing for remaining term | W28: Net 30 via ACH/wire; late interest 1.5%/month (18%/yr); credit hold and list pricing on non-payment | X28: Customer liable for loss/damage and must insure equipment at replacement cost; mutual indemnity; consequential damages exclusion; CGL $1M/$3M; customer may not assign | Y28: Filename dates (9/30/27, 2/29/28) do not match text: 3-yr term from 5/6/2025 implies initial term ending 5/5/2028. No convenience exit during first 3 years. | Z28: High | AA28: Text
A29: Cleveland Clinic | B29: The Cleveland Clinic Foundation d.b.a. Cleveland Clinic | C29: Cleveland Clinic | D29: Cleveland Clinic_Exp_7_31_28.pdf | E29: Master/Rental Agreement | F29: BTS Rental | G29: Direct (CCF Contract ID 4330960) | H29: US Med-Equip, LLC | I29: 2025-08 (signed 8/8-8/11/2025; term starts on installation) | J29: 2028-07-31 (per filename; 3 years from installation) | K29: 46965 | L29: Contract text | N29: =IF(M29<>"",M29-Summary!$C$3,IF(K29="","",K29-Summary!$C$3)) -> 660 | O29: Active | P29: 3 years from installation | Q29: Extension by written agreement of parties | R29: Customer-only: Lessee with or without cause on 30 days notice; either party for uncured breach (30 days) or insolvency | S29: Exhibit A fixed rates: Advanced Wave Mattress $32.00, Advanced Wave Mattress XMS $42.00 (Rotec VersaTech beds also in scope) | T29: Not stated | U29: Not stated | V29: None stated | W29: Not stated | X29: Lessee pays FMV replacement for loss/theft after acceptance; Lessor liable for its negligence; mutual indemnity; consequential damages excluded; no assignment w/o consent; recall notice 24 hrs | Y29: Rental of Advanced Wave mattresses and Rotec VersaTech beds to Cleveland Clinic and 10 eligible facilities (incl. Weston, FL). Customer can exit on 30 days. | Z29: High | AA29: OCR
A30: CommonSpirit Health | B30: CommonSpirit Health (FKA CHI, Dignity Health) and Affiliates | C30: CommonSpirit | D30: CSH-MM-156_CommonSpirit_Exp_3_31_28.pdf | E30: Master/Rental Agreement | F30: MME Rental, Respiratory | G30: Direct (CSH-MM-156) | H30: US Med Equip, LLC | I30: 2025-04-01 | J30: 2028-03-31 | K30: 46843 | L30: Contract text | N30: =IF(M30<>"",M30-Summary!$C$3,IF(K30="","",K30-Summary!$C$3)) -> 538 | O30: Active | P30: 3 years | Q30: None unless mutually agreed in writing | R30: Either party without cause, 60 days written notice; CSH may terminate immediately on Vendor change of control or repeated SLA failures | S30: CSH-specific Tier 1 daily/monthly rates per Section 2 (model-level list), 28-day monthly cap; patient beds excluded | T30: Fixed first 12 months; then max once per calendar year with documentation and written amendment, capped at lesser of 3% or CPI-U | U30: 3% rebate to CSH entities, paid quarterly within 30 days of quarter end | V30: Not stated (no volume commitment found) | W30: Net 30 from receipt of undisputed invoice via EFT; invoices >180 days late not payable; no late fees on rejected invoices | X30: IDN MFN price warranty (breach = termination right); FMV damage process; delivery 2 hrs + drive time; insurance up to $5M; change-of-control termination; transition assistance | Y30: National peak-use rental agreement (infusion, monitoring, respiratory, infant care) covering all CommonSpirit facilities. Expressly supersedes and voids Premier PP-NS-1662 and related pricing for CSH. | Z30: High | AA30: Text
A31: CommonSpirit Health | B31: CommonSpirit Health (on behalf of itself and affiliates) | C31: CommonSpirit | D31: CSH-MM-158_CommonSpirit_BTS_Exp_3_31_28.pdf | E31: Master/Rental Agreement | F31: BTS Rental, Restraints/Posey | G31: Direct (CSH-MM-158) | H31: US Med-Equip, LLC | I31: 2025-04-01 | J31: 2028-03-31 | K31: 46843 | L31: Contract text | N31: =IF(M31<>"",M31-Summary!$C$3,IF(K31="","",K31-Summary!$C$3)) -> 538 | O31: Active | P31: 3 years | Q31: None stated | R31: Either party, 60 days written notice without cause; immediate for material breach | S31: National daily rental rates per Section 2 fee schedule | T31: Conflict: Sec 2 fixed 12 months then 1x/yr capped at lesser of 3% or CPI-U via written amendment; Std T&C 2.2 says fixed for initial term | U31: 3% rebate on service fees paid quarterly within 30 days (Schedule C); no GPO admin fee paid | V31: None stated | W31: Net 30 from invoice receipt via EFT; no late fees on good-faith rejected invoices | X31: Vendor liable for damage it causes; mutual consequential damages waiver w/ carve-outs; audit reimbursement if overcharge >=5%; assignment requires consent; extensive personnel screening; insurance incl. $3M/occurrence line | Y31: National BTS agreement for CommonSpirit facilities; replaces prior arrangements. Requires corporate account manager and heavy vendor-credentialing compliance. | Z31: High | AA31: Text
A32: Cook Children's | B32: Cook Children's Medical Center | C32: Cook Children's | D32: Cook Children MSA BTS Repair_Exp_10_19_23_Auto_2026.pdf | E32: Master/Rental Agreement | F32: BTS Rental, Biomed/Repair Service | G32: Direct | H32: US Med-Equip, LLC | I32: 2023-10-19 | J32: 2026-10-19 (or later expiration of any open SOW) | K32: 46314 | L32: Contract text | N32: =IF(M32<>"",M32-Summary!$C$3,IF(K32="","",K32-Summary!$C$3)) -> 9 | O32: Active | P32: 3 years (or until all SOWs end, if later) | Q32: No auto-renewal stated; MSA survives until all SOWs expire | R32: No convenience termination; breach with 60-day cure, insolvency, force majeure >30 days (10 days notice), mutual agreement; USME may terminate on customer change of control | S32: Per SOW Program Budget (no SOW attached) | T32: Not stated (Program Budget changes require mutual written consent) | U32: Not stated | V32: Expressly non-exclusive | W32: Net 30 from invoice receipt (undisputed); late interest lesser of 1.5%/mo or TX max, compounded; collection costs | X32: USME liability capped at 12 months of fees for applicable SOW; no consequential damages; USME indemnifies for equipment damage in its custody; 12-mo non-solicit; USME CGL $1M/$3M | Y32: Framework MSA for BTS rental and repair services; commercial terms live in SOWs not included in file. Filename 'Exp_10_19_23' is effective date; text gives 3-year term to 10/19/2026, expiring in 9 days absent active SOW. | Z32: High | AA32: OCR
A33: County of Los Angeles | B33: County of Los Angeles (Department of Health Services) | C33: County of Los Angeles | D33: LA County RT Biomed Exp 6.30.2028.pdf | E33: Service Agreement/SOW | F33: Biomed/Repair Service, Respiratory | G33: Direct | H33: US Med-Equip, LLC | I33: 2024-10-17 | J33: 2028-06-30 | K33: 46934 | L33: Contract text | N33: =IF(M33<>"",M33-Summary!$C$3,IF(K33="","",K33-Summary!$C$3)) -> 629 | O33: Active | P33: ~3.7 years (2024-10-17 to 2028-06-30) | Q33: County Director may extend at sole discretion on written notice | R33: County only, for convenience, at least 10 days notice; also non-appropriation of funds | S33: Maintenance fees per Exhibit B Rate Schedule (per-model PM/overhaul rates for respiratory equipment); hourly rate for additional services via Work Orders | T33: Rates effective through 2028-06-30; changes only by County-prepared amendment | U33: Not stated | V33: Non-exclusive master agreement | W33: Invoice in arrears; no payment for services after expiration | X33: 95% uptime guarantee with tiered credits (to $500); <80% uptime 5+ days = default; 4-hr service response; liquidated damages; broad indemnity; County approval for assignment/merger/change of control | Y33: Master Agreement H-711223 for Respiratory Equipment Maintenance and Repair Services at DHS facilities. Must notify DHS 6 months before expiration. Heavy county compliance requirements (background checks, jury service, etc.). | Z33: High | AA33: Text
A34: County of Los Angeles (DHS) | B34: County of Los Angeles, Department of Health Services | C34: County of Los Angeles | D34: County of Los Angeles_Service agreement_Exp_6_30_2028.pdf | E34: Service Agreement/SOW | F34: Biomed/Repair Service, Respiratory | G34: Direct (Master Agreement H-711223, via RFR) | H34: US Med-Equip, LLC | I34: 2024-10-17 | J34: 2028-06-30 | K34: 46934 | L34: Contract text | N34: =IF(M34<>"",M34-Summary!$C$3,IF(K34="","",K34-Summary!$C$3)) -> 629 | O34: Active | P34: ~3.7 years (through June 30, 2028) | Q34: Director may extend term at sole discretion with prior written notice | R34: County-only, for convenience at sole discretion, effective >=10 days after notice; also for default, non-appropriation, insolvency | S34: Exhibit B Rate Schedule: per-model PM/inspection fees by service category (e.g., Servo i PM $1,313) plus hourly rate for Additional Services; Work Orders capped at Maximum Fixed Price | T34: Rates effective through 2028-06-30; no escalator stated | U34: Not stated | V34: Non-exclusive; payment only for County-approved work | W34: Invoice monthly in arrears within 30 days of month-end; County approval required; no pay for post-expiration services | X34: Broad County indemnity (incl. confidentiality and IP); liquidated damages; 4-hr service call response; County approval for assignment/merger/change of control; background checks; CGL insurance required | Y34: Respiratory equipment maintenance and repair at DHS facilities (e.g., Harbor-UCLA). Heavy public-agency compliance burden; USME must notify DHS 6 months before expiry. | Z34: High | AA34: Text
A35: County of San Mateo | B35: County of San Mateo on behalf of San Mateo Medical Center | C35: San Mateo Medical Center | D35: San Mateo_Equip Rental Agmt_MME BTS_Exp 11_30_27.pdf | E35: Master/Rental Agreement | F35: MME Rental, BTS Rental | G35: Direct | H35: US Med-Equip, LLC | I35: 2024-12-01 | J35: 2027-11-30 | K35: 46721 | L35: Contract text | N35: =IF(M35<>"",M35-Summary!$C$3,IF(K35="","",K35-Summary!$C$3)) -> 416 | O35: Active | P35: 3 years | Q35: May be extended by amendment | R35: Customer may terminate at any time (notice text garbled); customer may terminate immediately for lack of funding; 60-day breach cure | S35: Daily/monthly rates per pricing attachment; contract # KS08052025SMMC | T35: Fixed until 2nd anniversary; then max 1x/yr by greater of 5% or CPI-U | U35: Not stated | V35: Primary Vendor section blank | W35: Net 30 | X35: Total payments capped at $200,000; customer liable for loss/damage; mutual indemnity; additional-insured and primary insurance requirements; county ordinance compliance (living wage, jury service, $2,500 LDs); CA law | Y35: County contract with $200K not-to-exceed cap that could limit billing. Text partially garbled. | Z35: Medium | AA35: Text
A36: Craig Hospital | B36: Craig Hospital | C36: Craig Hospital | D36: Craig Hospital Posey agreement Exp_08_02_29.pdf | E36: Master/Rental Agreement | F36: Restraints/Posey | G36: Direct | H36: US Med-Equip, LLC | I36: 2026-08-03 | J36: 2029-08-02 | K36: 47332 | L36: Contract text | N36: =IF(M36<>"",M36-Summary!$C$3,IF(K36="","",K36-Summary!$C$3)) -> 1027 | O36: Active | P36: 3 years | Q36: Auto-renews successive 1-yr terms | R36: Customer may terminate without cause on 60 days notice during Initial Term; either party on 60 days after Initial Term | S36: Monthly rates per Attachment A: Posey 8060 Enclosure $700/month (qty 10); Primary Vendor pricing | T36: Not stated | U36: Not stated | V36: Primary Vendor: 90%+ of annual rental spend; 60-day cure, then list pricing for remainder of term | W36: Net 30 via ACH/wire; interest at max legal rate on past due; credit hold and list pricing on nonpayment | X36: Customer liable for loss/damage only from its negligence/misuse; mutual indemnity; no consequential damages; USME CGL $1M/$3M; customer insures replacement cost; customer may not assign | Y36: New 2026 Posey enclosure rental agreement (10 units). Customer has a one-sided termination-for-convenience right during the initial term, which undercuts the 3-year term. | Z36: High | AA36: OCR
A37: CuraHealth | B37: Curahealth, LLC | C37: CuraHealth | D37: CuraHealth_MME_Exp12_3_2023_auto_renew.pdf | E37: Master/Rental Agreement | F37: MME Rental, Respiratory | G37: Vizient (Preferred Partnership 90% LOC Tier 3 pricing; no contract # stated) | H37: US Med-Equip, LLC | I37: 2020-12-04 | J37: 2023-12-03 initial; auto-renewed, current term likely through 2026-12-03 | K37: 45263 | L37: Contract text | M37: 46359 | N37: =IF(M37<>"",M37-Summary!$C$3,IF(K37="","",K37-Summary!$C$3)) -> 54 | O37: Active | P37: 3 years | Q37: Auto-renews successive 1-yr terms unless either party cancels in writing 30 days before term end | R37: No termination for convenience; for uncured breach (60-day cure) or insolvency; non-renewal with 30 days notice | S37: Monthly rental rates per Attachment A at Vizient Preferred Partnership 90% LOC Tier 3 pricing; Contract # CH 10122020JD | T37: Not stated | U37: Not stated; equity option: 25% of monthly rental paid (up to 12 months) credited toward purchase | V37: Customer names USME primary first-call vendor for MME rental in exchange for Vizient Preferred Partnership pricing | W37: Monthly rent due on the 1st of each month; customer pays collection/attorney fees on default | X37: Customer responsible for safekeeping, loss/damage and abuse repairs; full replacement cost if not returned in good condition; GL $1M/$3M; mutual indemnity; customer may not assign | Y37: Monthly MME/respiratory rental (ventilators, pumps, monitors, CPMs) to Curahealth. Auto-renewal keeps it in force absent a non-renewal notice; next renewal date ~12/3/2026, cancel notice by ~11/3/2026. | Z37: Medium | AA37: OCR
A38: DaVita | B38: DaVita Inc. | C38: Davita | D38: Davita _Exp_5_31_28.pdf | E38: Amendment | F38: Refurb Equipment Sales, MME Rental, Biomed/Repair Service | G38: Direct | H38: US Med-Equip LLC (written 'US Medi-Equip LLC') | I38: 2025-07-08 (Second Amendment; base Product Purchase Agreement eff. 2021-09-01) | J38: 2028-05-31 | K38: 46904 | L38: Contract text | N38: =IF(M38<>"",M38-Summary!$C$3,IF(K38="","",K38-Summary!$C$3)) -> 599 | O38: Active | P38: Not stated (term extended through 2028-05-31) | Q38: Not stated | R38: Not stated in amendment (per base agreement) | S38: Restated Exhibit A: refurb pump sales (Spectrum $1,035.71, Medfusion 3500 $1,821.43), IV sets, rentals $49-$132.44/month, service $125/hr, PM $100 | T38: Not stated | U38: Not stated; early payment discount removed | V38: Not stated | W38: Net 30 from AP receipt; monthly invoicing; customer may withhold disputed amounts; early-pay discount removed | X38: Title passes on delivery; DaVita pays shipping; orders ship ground within 24 hrs; free training and manuals required | Y38: Second Amendment extends DaVita product purchase agreement to 5/31/2028 and replaces pricing; covers refurbished infusion pump sales, disposables, pump rentals and repair service. Entity name misspelled in the preamble. | Z38: High | AA38: Text
A39: Department of Veterans Affairs | B39: Department of Veterans Affairs, Network Contract Office 17 (Amarillo VA Medical Center) | C39: Veteran Affairs Amarillo Medical Center | D39: Amendmen for VA Agreement_06.16.2026.pdf | E39: Amendment | F39: Not stated | G39: Direct (VA contract/order 36C25726R0023 per OCR; Mod P0002) | H39: US Med-Equip, LLC | I39: 2026-06-16 (contractor signature date; effective date block references 16c) | J39: Not stated | L39: Unknown | N39: =IF(M39<>"",M39-Summary!$C$3,IF(K39="","",K39-Summary!$C$3)) | O39: Active | P39: Not stated | Q39: Not stated | R39: Noncompliance with FAR 52.222-90 may result in cancellation, termination or suspension | S39: Not stated | T39: Not stated | U39: Not stated | V39: Not stated | W39: Not stated | X39: Adds FAR 52.222-90 (no racially discriminatory DEI activities); compliance material to payment under False Claims Act; flow-down to subcontractors required | Y39: SF-30 Modification P0002 solely incorporating FAR 52.222-90 per EO 14398; no other changes. Signed by Clay Rose 6/16/2026; underlying VA contract terms not included. | Z39: Medium | AA39: OCR
A40: DispatchHealth | B40: Dispatch Health Management, LLC | C40: Dispatch Health | D40: Dispatch_Health_Amendment_exp 06_30_29.pdf | E40: Extension | F40: MME Rental, BTS Rental, Respiratory | G40: Direct | H40: US Med-Equip, LLC | I40: 2026-06-03 (amendment); extension term starts 2026-07-01 | J40: 2029-06-30 | K40: 47299 | L40: Contract text | N40: =IF(M40<>"",M40-Summary!$C$3,IF(K40="","",K40-Summary!$C$3)) -> 994 | O40: Active | P40: 3-year extension (base agreement dated 2025-07-02) | Q40: Not stated | R40: Per underlying agreement (not stated in amendment) | S40: Exhibit A replaced: MME (oxygen concentrators, Kangaroo pump, Philips M10) and BTS (Freedom 500 bed, bariatric wheelchairs) daily/monthly rates | T40: Not stated | U40: Not stated | V40: Not stated | W40: Not stated | X40: Not stated | Y40: Extends Dispatch Health rental agreement 7/1/2026-6/30/2029, replaces pricing, and adds 16 locations across OH, GA, TX, CO, NV, FL, AZ, VA, WA (Exhibit B). Signed 7/31/2026 by James Duvall (USME). | Z40: High | AA40: Text
A41: Encompass Health | B41: Encompass Health Corporation | C41: Encompass Health | D41: Encompass_Exp_11_12_2023_auto_renewal.pdf | E41: Master/Rental Agreement | F41: MME Rental, Respiratory | G41: Vizient CE7073 | H41: US Med-Equip, LLC | I41: 2020-11-12 | J41: 2023-11-12 initial; auto-renews 1-yr (current term to ~2026-11-12) | K41: 45242 | L41: Contract text | M41: 46338 | N41: =IF(M41<>"",M41-Summary!$C$3,IF(K41="","",K41-Summary!$C$3)) -> 33 | O41: Active | P41: 3 years | Q41: Auto-renews 1-yr terms unless cancelled 30 days before term end | R41: Either party, 60 days written notice without cause | S41: Monthly rates per Attachment A at Vizient Tier 3 Preferred Partnership (90% LOC) pricing | T41: Fixed for term (reductions only) | U41: Vizient admin fees apply; 25% equity discount on rental dollars (up to 12 months) toward purchase | V41: Dual-source MME vendor designation; credit standing required, DSO <= 60 days | W41: Due 1st of each month; repossession right on non-payment | X41: Customer bears loss/damage and abuse repairs; USME indemnifies for customer use of equipment; CGL $1M/$3M; assignment requires consent; Delaware law | Y41: Contract # EH 09152020JD. Vizient terms apply where more favorable to customer. Next renewal ~2026-11-12; cancellation window closes ~mid-Oct 2026. | Z41: Medium | AA41: OCR
A42: Encompass Health | B42: Encompass Health Rehabilitation Hospital of Northwest Tucson, L.P. | C42: Encompass Tucson | D42: Encompass Tucson_MME_BTS_Exp_3_31_2024_LR.pdf | E42: Master/Rental Agreement | F42: MME Rental, BTS Rental, Respiratory, Restraints/Posey | G42: Direct | H42: Freedom Medical, Inc. | I42: 2019-06-14 | J42: 2024-03-31 (now rolling 30-day renewals) | K42: 45382 | L42: Contract text | N42: =IF(M42<>"",M42-Summary!$C$3,IF(K42="","",K42-Summary!$C$3)) -> -923 | O42: Active | P42: Through 2024-03-31 (~4.8 years) | Q42: Auto-renews 30-day periods unless 30 days notice | R42: Either party on 30 days written notice after initial term; customer may terminate immediately for quality issues, rep breach, or hospital sale/closure | S42: Fixed daily/monthly rates per Exhibit A; beds at Tier 5 pricing schedule | T42: Not stated | U42: Not stated | V42: Not stated | W42: Net 30; invoices due by 10th of following month; invoices received 1+ year after service deemed paid | X42: Customer bears loss/damage at replacement cost; mutual negligence indemnity; no assignment without consent (FMI-to-USME assignment risk); insurance CGL $1M/$2M, auto $1M, umbrella $5M | Y42: Legacy Freedom Medical contract for single Tucson rehab hospital; initial term ended 3/31/2024 and it has been running month-to-month. Filename '_LR' consistent; agreement names FMI, not USME. | Z42: Medium | AA42: Text
A43: Englewood Post Acute | B43: Cherry Hills Healthcare, Inc. dba Englewood Post Acute and Rehabilitation | C43: Englewood | D43: Englewood Post Acute_Exp_04_18_2025_auto_2027.pdf | E43: Master/Rental Agreement | F43: BTS Rental | G43: Direct | H43: Freedom Medical, Inc. | I43: 2022-04-19 | J43: 2025-04-18 initial; renewals to 2027-04-18 | K43: 45765 | L43: Contract text | N43: =IF(M43<>"",M43-Summary!$C$3,IF(K43="","",K43-Summary!$C$3)) -> -540 | O43: Active | P43: 3 years | Q43: Two consecutive 12-month renewals unless either party gives 60 days notice of non-renewal | R43: Either party without cause, 30 days written notice | S43: Daily rental rates per Exhibit A (Freedom Comfort/Advanced Wave mattresses, $8.25-$55.00/day) | T43: Firm for 36 months; thereafter not stated | U43: None | V43: Customer to use FMI as primary medical equipment rental provider (no % stated) | W43: Net 30 from invoice; 1.5%/month on invoices 60+ days past due; no offset; billing disputes within 90 days | X43: Customer liable for loss/damage from receipt to return at current market value; FMI liability limited to repair/replace/refund, no consequential damages; mutual indemnity; arbitration | Y43: Legacy Freedom Medical therapeutic surface rental agreement for a post-acute facility. Assumed in second renewal period through 4/18/2027 absent non-renewal notice. | Z43: High | AA43: Text
A44: Erlanger Health | B44: Chattanooga-Hamilton County Hospital Authority d/b/a Erlanger Health System | C44: Erlanger Health | D44: Erlanger_MME_Exp_10_7_2021_Auto renew.pdf | E44: Master/Rental Agreement | F44: MME Rental, Respiratory | G44: Vizient (Access / LOC Tier 2 / LOC Tier 3 pricing; contract no. not stated) | H44: US Med-Equip, Inc. | I44: 2018-10-08 (OCR date partial) | J44: 2021-10-07 initial; auto-renews 1-yr (current term to ~2027-10-07) | K44: 44476 | L44: Contract text | M44: 46667 | N44: =IF(M44<>"",M44-Summary!$C$3,IF(K44="","",K44-Summary!$C$3)) -> 362 | O44: Active | P44: 3 years | Q44: Auto-renews 1-yr terms unless cancelled 30 days before term end | R44: No termination for convenience; breach (60-day cure) or insolvency only | S44: Daily/monthly rates per Attachment A by Vizient Access, LOC Tier 2 and LOC Tier 3 columns | T44: Not stated | U44: 25% equity discount on rental dollars (up to 12 months) toward purchase | V44: Not stated | W44: Net 30 (text also references net 60 - conflicting); PO required per delivery | X44: Customer bears loss/damage; delivery included F.O.B. destination; USME pays medical device tax; full new-unit replacement charge if not returned in good condition; CGL $1M/$3M | Y44: Contract # 070118THCHCHA covering Hamilton County TN facilities. Remains in effect via 1-yr auto-renewals absent cancellation. | Z44: Medium | AA44: OCR
A45: Grandview Medical Center (CHS / CHSPSC) | B45: Affinity Hospital LLC d/b/a Grandview Medical Center | C45: Grandview Medical Center | D45: Grandview Asset Mgt_rental_Exp_3_31_2028_LR.pdf | E45: Service Agreement/SOW | F45: Asset Mgmt/On-site, MME Rental, Biomed/Repair Service, Respiratory | G45: HPG-7093 (rental pricing) with CHSPSC Group SIP | H45: US Med-Equip (US Med-Equip LLC) | I45: 2023-04-01 | J45: Not explicitly stated; 5-year commitment implies 2028-03-31 | K45: 46843 | L45: Contract text | N45: =IF(M45<>"",M45-Summary!$C$3,IF(K45="","",K45-Summary!$C$3)) -> 538 | O45: Active | P45: 5 years | Q45: Not stated | R45: Either party without cause, 90 days written notice; $60,000 termination fee if Grandview terminates without cause in first 12 months | S45: Asset management fixed fee $37,397/month plus $10,000 one-time startup; rental at HPG-7093/CHSPSC SIP pricing; respiratory PM price list at HPG price (discount to list) | T45: Rental pricing held firm through term; more favorable renewed HPG/SIP pricing prevails | U45: Not stated | V45: 5-year commitment; 4 on-site USME staff (team lead + 3) covering 1,910 hospital-owned devices | W45: Not stated | X45: USME indemnifies Grandview; insurance CGL $1M/$2M, professional $1M/$3M, cyber $5M/$10M, product $1M/$3M; loss/damage on party at fault; Grandview may terminate if force majeure >30 days | Y45: Proposal-form agreement (dated 2023-02-28) for on-site asset management with STAR Trax RFID at Grandview. Filename _LR; expiration inferred from 5-yr term. | Z45: Medium | AA45: Text
A46: Hackensack Meridian Health | B46: Hackensack Meridian Health Network | C46: Hackensack Meridian | D46: Hackensack_Meridian_Health_MME_agreement_Exp_12_31_2030.pdf | E46: Master/Rental Agreement | F46: MME Rental, Respiratory | G46: Direct | H46: US Med-Equip, LLC | I46: 2025-01-01 | J46: 2029-12-31 per 5-yr term (filename says 2030-12-31) | K46: 47483 | L46: Contract text | N46: =IF(M46<>"",M46-Summary!$C$3,IF(K46="","",K46-Summary!$C$3)) -> 1178 | O46: Active | P46: 5 years | Q46: Auto-renews successive 1-yr terms | R46: After Initial Term, either party without cause on 30 days written notice; 60-day cure for breach | S46: Daily/monthly rates per Attachment A (Primary Vendor pricing); list pricing if commitment breached | T46: Fixed for first 2 years; then once per contract year, up to greater of 5% or prior-year Medical Care CPI-U, 30 days notice | U46: Rebate template (Att. C): 2% for 1 vertical, 4% for 2, 6% for 3 (MME, BTS, ASAP); requires net 30 DSO, ACH, EMR integration, QBRs | V46: Primary vendor: 90%+ of annual rental spend at Covered Facilities (Att. B); 60-day cure or list pricing for remaining term | W46: Net 30; 1.5%/month late interest; credit hold and repossession rights | X46: Customer bears loss/damage and insures at replacement cost; full new-equipment cost if not returned; mutual indemnity; no consequential damages; Texas law, Harris County venue | Y46: Favorable USME paper: Texas law, 90% commitment, price escalator after year 2, no early convenience termination. 5-year term from 1/1/2025 ends 12/31/2029, conflicting with filename's 2030. | Z46: High | AA46: Text
A47: HCA Healthcare / HealthTrust (HPG) | B47: HealthTrust Purchasing Group, L.P. (HealthTrust and HCA) | C47: GPO/HealthTrust | D47: HPG MME S2_7093_Amendment_extension_exp 6_30_2027.pdf | E47: Extension | F47: MME Rental | G47: HPG agreement no. 143302 (filed under HPG-7093) | H47: US Med-Equip, LLC | I47: 2026-07-01 | J47: 2027-06-30 | K47: 46568 | L47: Contract text | N47: =IF(M47<>"",M47-Summary!$C$3,IF(K47="","",K47-Summary!$C$3)) -> 263 | O47: Active | P47: Original agreement dated 2020-08-01 | Q47: Extension to 2027-06-30 | R47: Not stated (per underlying agreement) | S47: Not stated (unchanged per underlying agreement) | T47: Not stated | U47: Not stated | V47: Not stated | W47: Not stated | X47: Not stated | Y47: One-page amendment extending the Aug 1, 2020 HCA/HealthTrust MME pricing agreement (No. 143302) to 6/30/2027; signed by Doug Murray (CRO) June 2026. Text references both 'Pricing Agreement' and 'Purchasing Agreement'. | Z47: High | AA47: Text
A48: Healthbridge Children's Hospital | B48: Healthbridge Children's Hospital | C48: Healthbridge Children's Hospital | D48: Healthbridge Children's Hospital_MME_BTS_Exp 04_15_2029_auto.pdf | E48: Master/Rental Agreement | F48: MME Rental, BTS Rental | G48: Direct | H48: US Med-Equip, LLC | I48: 2026-04-16 | J48: 2029-04-15 | K48: 47223 | L48: Contract text | N48: =IF(M48<>"",M48-Summary!$C$3,IF(K48="","",K48-Summary!$C$3)) -> 918 | O48: Active | P48: 3 years | Q48: Auto-renews successive 1-yr terms | R48: Either party without cause, 60 days notice, only after Initial Term | S48: Daily/monthly rates per Attachment A; Primary Vendor pricing | T48: Firm until 2nd anniversary; then 1 increase per contract year up to greater of 5% or Medical Care CPI-U, 30 days notice | U48: Not stated | V48: Primary Vendor: 90%+ of annual rental spend; 60-day cure then list pricing for remainder of term | W48: Net 30 via ACH/wire; interest at max legal rate; credit hold and list pricing on additional equipment for late pay | X48: Customer bears loss/damage; must insure equipment at replacement cost; mutual indemnity; no consequential damages; USME GL $1M/$3M; Texas law, Harris County | Y48: Current USME template with stronger protections: escalator, list-price fallback, credit-hold remedies. Covered Facilities in Attachment B. | Z48: High | AA48: OCR
A49: HealthTrust (HPG) | B49: Genesis Health Inc. dba Brooks Rehabilitation | C49: Brooks Rehab | D49: Brooks Rehab SIP BTS Exp 9_30_2027.pdf | E49: GPO Letter of Participation/SIP | F49: BTS Rental | G49: HPG-77980 | H49: US Med-Equip, LLC | I49: 2024-08-01 (signed 2025-03-26) | J49: Not stated (tied to HPG-77980; filename 2027-09-30) | K49: 46660 | L49: Contract text | N49: =IF(M49<>"",M49-Summary!$C$3,IF(K49="","",K49-Summary!$C$3)) -> 355 | O49: Active | P49: Not stated | Q49: None stated | R49: Facility, 30 days notice; HealthTrust, 30 days notice; Vendor may terminate SIP only for missed commitment after 60-day cure | S49: Per HPG-77980 pricing | T49: Not stated | U49: 3% rebate on Covered Product purchases, paid annually to HealthTrust within 60 days of calendar year end | V49: Facility/Group commits to 80% of requirements for rental beds, surfaces and equipment | W49: Not stated | X49: Rebate obligation continues through date of facility termination | Y49: HPG SIP facility and group acknowledgement for Brooks Rehab, Jacksonville FL. Expiry follows HPG-77980 (extended to 9/30/2027). | Z49: High | AA49: Text
A50: HealthTrust (HPG) | B50: HealthTrust Purchasing Group, L.P. | C50: GPO/HealthTrust | D50: HealthTrust_HCA-Beds_incl amendment_HPG-77980_exp 09.30.2027.pdf | E50: GPO Agreement | F50: BTS Rental, Restraints/Posey | G50: HPG-77980 | H50: US Med-Equip, LLC (amendment); Freedom Medical, Inc. (original agreement) | I50: 2022-10-01 (amendment 2025-03-17) | J50: 2027-09-30 | K50: 46660 | L50: Contract text | N50: =IF(M50<>"",M50-Summary!$C$3,IF(K50="","",K50-Summary!$C$3)) -> 355 | O50: Active | P50: 3 years (orig. exp. 2025-09-30) | Q50: HealthTrust option for two 1-yr extensions by amendment; extended to 2027-09-30 | R50: HealthTrust only, 60 days written notice without cause | S50: Fixed daily/monthly rates per Exhibit A/AA; multi-source award; direct purchase | T50: Firm/fixed from Effective Date through Expiration Date | U50: 3% GPO fee monthly; rebates per Exhibit C, paid monthly; SIP forms: 8% growth rebate template | V50: Multi-source; no minimums; members may exit existing contracts to use HPG pricing | W50: Net 60; 2% discount if paid in 10 days; 1%/month late fee provisions; must accept e-payment programs | X50: 95% fill rate; 2 hr + drive time delivery; vendor replaces items damaged in transit; change of control provisions; must add new category products at comparable pricing or HealthTrust may terminate | Y50: HCA/HealthTrust national beds/surfaces agreement originally with Freedom Medical; 2025 amendment names USME, refreshes Exhibit A pricing and extends term. Amendment recites agreement date inconsistently (Oct 2022 vs Feb 2025). | Z50: High | AA50: Text
A51: HealthTrust (HPG) | B51: HealthTrust Purchasing Group, L.P. | C51: GPO/HealthTrust | D51: HealthTrust_HCA_Amendment extension_exp 7_31_2029.pdf | E51: Extension | F51: MME Rental | G51: HPG-7093 | H51: US Med-Equip, LLC | I51: 2025-08-01 | J51: 2029-07-31 | K51: 47330 | L51: Contract text | N51: =IF(M51<>"",M51-Summary!$C$3,IF(K51="","",K51-Summary!$C$3)) -> 1025 | O51: Active | P51: Extension of agreement dated 2021-08-01 | Q51: None stated | R51: Not stated | S51: Unchanged; per underlying HPG-7093 Rental - Moveable Medical Equipment agreement | T51: Not stated | U51: Not stated | V51: Not stated | W51: Not stated | X51: Not stated | Y51: One-page amendment extending HPG-7093 (Rental - MME) expiration to 7/31/2029; all other terms unchanged. Filename references HCA but document names HealthTrust only. | Z51: High | AA51: Text
A52: HealthTrust (HPG) | B52: Summa Health System | C52: Summa Health | D52: Summa Health SIP agreement.pdf | E52: GPO Letter of Participation/SIP | F52: MME Rental | G52: HPG-7093 | H52: US Med-Equip, LLC | I52: 2026-02-17 (signed; HPG-7093 effective 2021-08-01) | J52: Not stated (tied to HPG-7093, extended to 2029-07-31) | K52: 47330 | L52: Contract text | N52: =IF(M52<>"",M52-Summary!$C$3,IF(K52="","",K52-Summary!$C$3)) -> 1025 | O52: Active | P52: Not stated | Q52: Not stated | R52: Group may exit SIP on 30 days notice; HealthTrust 30 days; vendor only for non-compliance after 60-day cure | S52: SIP Committed Price per HPG-7093 Exhibit A | T52: Not stated | U52: Not stated | V52: 80% of requirements for Products | W52: Not stated | X52: Not stated | Y52: Recently signed HPG SIP for Summa Health; facility list left blank (spreadsheet may be attached). | Z52: Medium | AA52: Text
A53: HealthTrust (HPG) | B53: HealthTrust Purchasing Group, L.P. | C53: GPO/HealthTrust | D53: HPG MME HPG7093 Extension Exp 7.31.29.pdf | E53: Extension | F53: MME Rental | G53: HPG-7093 | H53: US Med-Equip, LLC | I53: 2025-08-01 | J53: 2029-07-31 | K53: 47330 | L53: Contract text | N53: =IF(M53<>"",M53-Summary!$C$3,IF(K53="","",K53-Summary!$C$3)) -> 1025 | O53: Active | P53: Not stated (Agreement dated 2021-08-01) | Q53: None stated | R53: Not stated; parties warrant they will not seek to rescind the amendment | S53: Per existing HPG-7093 Agreement (unchanged) | T53: Not stated | U53: Not stated | V53: Not stated | W53: Not stated | X53: Not stated | Y53: Current controlling extension of the HPG-7093 national MME rental agreement, through 7/31/2029. All other terms unchanged. | Z53: High | AA53: Text
A54: Henry Mayo Newhall Hospital | B54: Henry Mayo Newhall Memorial Hospital | C54: Henry Mayo | D54: Henry Mayo Newhall Memorial Hospital_MME_BTS_Exp_9_20_2025_Auto_2026_LR.pdf | E54: Master/Rental Agreement | F54: MME Rental, BTS Rental | G54: Direct | H54: US Med-Equip, LLC | I54: 2022-09-21 | J54: 2025-09-20 initial; auto-renewed, current term through 2026-09-20 then 2027-09-20 | K54: 45920 | L54: Contract text | M54: 46650 | N54: =IF(M54<>"",M54-Summary!$C$3,IF(K54="","",K54-Summary!$C$3)) -> 345 | O54: Active | P54: 3 years | Q54: Auto-renews successive 1-yr terms | R54: Either party without cause, 30 days written notice | S54: Monthly rental fee per Attachment A; Primary Vendor pricing | T54: Not stated | U54: Not stated; 25% equity discount on MME rental dollars (up to 12 months) toward buyout; 50% lost-equipment buyout credit | V54: Primary Vendor: 90%+ of annual rental spend for MME and beds/therapeutic surfaces | W54: Net 30; repossession after notifying CFO with 5-day cure | X54: Customer bears loss/damage and abuse repairs; full new-unit cost if not returned in good condition; mutual indemnity; USME GL $1M/$3M; California law | Y54: Contract # HM092022TH. Easy 30-day convenience exit despite primary vendor commitment. | Z54: High | AA54: OCR
A55: Hurley Medical Center | B55: Hurley Medical Center | C55: Hurley Medical | D55: Hurley Medical Center Agreement BTS_Exp_06_5_2030_auto_renewal.pdf | E55: Master/Rental Agreement | F55: BTS Rental | G55: Direct (Vizient pricing parity clause) | H55: US Med-Equip, LLC | I55: 2025-06-06 | J55: 2030-06-05 (initial term; then auto-renews) | K55: 47639 | L55: Contract text | N55: =IF(M55<>"",M55-Summary!$C$3,IF(K55="","",K55-Summary!$C$3)) -> 1334 | O55: Active | P55: 5 years | Q55: Auto-renews for successive 1-yr terms | R55: Either party with or without cause, 60 days prior notice (Sec. 8.1); Sec. 2 also allows 60-day termination after Initial Term | S55: Attachment A daily/monthly primary vendor pricing; list pricing if 80% commitment breached and uncured | T55: Not stated; must extend any lower Vizient GPO pricing for same products prospectively | U55: Not stated | V55: Primary vendor: 80%+ of annual rental spend for Attachment B facilities; 60-day cure else list pricing | W55: Net 30 via ACH/wire; interest at max legal rate; credit hold / repossession rights | X55: Customer liable for loss/damage and must insure at replacement cost; replacement cost charged if not returned; mutual indemnity; CGL $1M/$3M; Vizient price-parity (MFN-like) clause; Harris County TX venue | Y55: Bariatric/therapeutic beds and surfaces rental for Hurley (Michigan). Section 8.1 termination for convenience at any time on 60 days notice undercuts 5-yr term. | Z55: High | AA55: Text
A56: iMedical / Bon Secours Mercy Health | B56: iMedical (managing rentals for Bon Secours Mercy Health VA and OH locations) | C56: iMedical | D56: iMedical_BTS_Exp_4_30_2025_ext 2027.pdf | E56: Master/Rental Agreement | F56: BTS Rental | G56: Direct | H56: Freedom Medical, Inc. | I56: 2021-09-01 | J56: 2025-04-30 initial; two 12-month renewals run to 2027-04-30 | K56: 45777 | L56: Contract text | N56: =IF(M56<>"",M56-Summary!$C$3,IF(K56="","",K56-Summary!$C$3)) -> -528 | O56: Active | P56: Through 2025-04-30 (or earlier end of iMedical-BSM agreement) | Q56: Renews for two consecutive 12-month periods unless either party gives 60 days non-renewal notice | R56: For cause only (30-day cure); early cancellation without cause triggers default invoicing (difference to standard pricing) | S56: Rental rates per Exhibit B Rental Pricing Schedule (exhibit blank in scan) | T56: Firm through 2025-04-30 (term of iMedical's BSM agreement); renewal pricing not stated | U56: Not stated | V56: FMI exclusive rental supplier of therapeutic support surfaces and bariatric bed frames for BSM VA/OH locations; breach triggers repricing to standard rates | W56: Net 30; 1.5%/month on invoices 60+ days past due; may suspend on 5 days notice; no offset | X56: Customer liable for loss/damage from receipt to return at replacement cost; FMI liability limited to repair/replace/refund, no consequential damages; mutual indemnity; PA law | Y56: Sub-rental arrangement via iMedical for Bon Secours Mercy Health hospitals; includes QBRs, annual utilization reports, in-servicing. Filename 'ext 2027' consistent with two 12-month renewals; Exhibits A/B blank in scan. | Z56: Medium | AA56: OCR
A57: Infirmary Health | B57: Infirmary Health Hospitals, Inc. d/b/a Infirmary LTAC Hospital | C57: Infirmary LTAC Hospital | D57: Infirmary Health_Vizient_Tier 1_Exp_2_11_2011_Auto renew.pdf | E57: Master/Rental Agreement | F57: MME Rental, Respiratory | G57: Not stated in text (filename says Vizient Tier 1) | H57: US Med-Equip, Inc. | I57: 2018-02-12 | J57: 2021-02-11 initial term; auto-renewing | K57: 44238 | L57: Contract text | M57: 46429 | N57: =IF(M57<>"",M57-Summary!$C$3,IF(K57="","",K57-Summary!$C$3)) -> 124 | O57: Active | P57: 3 years | Q57: Auto-renews successive 1-yr terms unless cancelled 30 days before term end | R57: Non-renewal by either party 30 days before term end; Company may terminate for customer breach (30-day cure) | S57: Primary Vendor pricing per Attachment A (e.g. PB 980 vent $71.14/day, $1,992/mo); 25% equity discount up to 12 months | T57: Not stated | U57: Not stated | V57: Primary vendor: 90%+ of annual MME rental spend | W57: Due on 1st of each month | X57: Customer responsible for loss/damage and abuse repairs; full new-unit cost if not returned; USME CGL $1M/$3M; Alabama law, Mobile County venue | Y57: Contract 02072018, ventilator-focused pricing. Filename 'Exp_2_11_2011' is a typo for 2021. Auto-renews annually, so likely still in effect unless cancelled. | Z57: Medium | AA57: OCR
A58: Kaiser Permanente | B58: Kaiser Vacaville Hospital Foundation | C58: Kaiser Vacaville | D58: Kaiser Vacaville Hospital_Posey_Exp_03_4_25_auto_renew.pdf | E58: Master/Rental Agreement | F58: Restraints/Posey | G58: Direct | H58: US Med-Equip, LLC | I58: 2024-09-05 | J58: 2025-03-04 initial; auto-renewing 6-month terms (current term to 2027-03-04) | K58: 45720 | L58: Contract text | N58: =IF(M58<>"",M58-Summary!$C$3,IF(K58="","",K58-Summary!$C$3)) -> -585 | O58: Active | P58: 6 months | Q58: Auto-renews successive 6-month terms unless cancelled 30 days before term end | R58: Non-renewal by either party 30 days before term end; no convenience termination; early equipment return requires paying remainder of rental term | S58: Posey Enclosure Bed billed $45/unit monthly; 1 unit | T58: Not stated | U58: Not stated | V58: Not stated | W58: Due 30 days from monthly invoice; collection costs | X58: Customer pays full new replacement cost for lost/damaged equipment; customer-only indemnity of USME; Texas law, Harris County venue | Y58: Single Posey enclosure bed rental stored on-site. Customer signature block blank in text; agreement date lacks year in body (USME signed 9/5/2024). | Z58: Medium | AA58: Text
A59: Lehigh Valley Health Network (LVHN) | B59: Lehigh Valley Health Network, Inc. (for its wholly owned non-profit subsidiaries) | C59: Lehigh Valley Health Network (LVHN) | D59: LVHN Equipment and Service Agreement_Exp_3_4_2026_incl amend.pdf | E59: Master/Rental Agreement | F59: MME Rental, BTS Rental, Biomed/Repair Service, Asset Mgmt/On-site | G59: Direct | H59: US Med-Equip, LLC | I59: 2024-03-01 | J59: 2026-02-28 initial; auto-renewed to 2027-02-28 | K59: 46081 | L59: Contract text | M59: 46446 | N59: =IF(M59<>"",M59-Summary!$C$3,IF(K59="","",K59-Summary!$C$3)) -> 141 | O59: Active | P59: 2 years | Q59: Auto-renews 1-yr terms unless 60 days notice | R59: After initial term, either party without cause on 60 days written notice | S59: MME daily/monthly Primary Vendor rates per Attachment A; SOW #1 on-site BMET services $12,395/month (3-yr SOW to 2027-02-28) | T59: Not stated | U59: Not stated | V59: Primary vendor: 90%+ of annual rental spend for Attachment A equipment; 60-day cure, else market rates | W59: Net 30 from invoice; late interest 1.5%/month | X59: 95% monthly fill rate guarantee (USME pays cost difference); customer liable for loss/damage from negligence; mutual indemnity; no consequential damages; CGL $1M/$2M, products $8M, cyber $10M | Y59: Includes Amendment No. 1 (beds at HPG-77980 pricing) and SOW #1 for on-site biomed technician services. Filename exp 3/4/2026 vs text initial term ending ~2/28/2026, now auto-renewed. | Z59: High | AA59: Text
A60: Lehigh Valley Health Network (LVHN) | B60: Lehigh Valley Health Network Inc. (for its wholly owned subsidiaries) | C60: Lehigh Valley Health Network (LVHN) | D60: LVHN Equipment and Service agreement_Exp_2_28_2026.pdf | E60: Master/Rental Agreement | F60: MME Rental, Biomed/Repair Service, Asset Mgmt/On-site | G60: Direct | H60: US Med-Equip, LLC | I60: 2024-03-01 | J60: 2026-02-28 initial; auto-renewed through 2027-02-28 absent notice | K60: 46081 | L60: Contract text | M60: 46446 | N60: =IF(M60<>"",M60-Summary!$C$3,IF(K60="","",K60-Summary!$C$3)) -> 141 | O60: Active | P60: 2 years | Q60: Auto-renews successive 1-yr terms unless 60 days notice before renewal | R60: Either party, 60 days written notice without cause after Initial Term; 60-day cure for breach | S60: Monthly rental fees per Attachment A; Primary Vendor pricing; on-site BMET service fees per SOW Annex 3 | T60: Not stated | U60: Rental equity discount: 25% of monthly rental credit toward buyout (up to 12 months) | V60: Primary Vendor: 90%+ of annual rental spend; 60-day cure, else market rates | W60: Net 30; late interest lesser of 1.5%/month or legal max; 15-day late notice before remedies | X60: 95% monthly fill rate guarantee, USME pays cost difference for substitute products; customer liable for loss/damage only if negligent; insurance: products $8M, E&O $5M, cyber $10M; mutual indemnity | Y60: Combined MME rental and on-site BMET/biomed SOW (RFID tracking, PM/repair of hospital-owned equipment, M-F 8-5). Initial term ended 2/28/2026; auto-renewal likely in effect. | Z60: Medium | AA60: Text
A61: Lehigh Valley Health Network (LVHN) | B61: Lehigh Valley Health Network, Inc. | C61: Lehigh Valley Health Network (LVHN) | D61: LVHN Amendment_Exp_2_28_2026.pdf | E61: Amendment | F61: MME Rental, BTS Rental | G61: HPG-77980 (bed pricing basis) | H61: US Med-Equip, LLC | I61: 2024-03-05 | J61: Not stated (base agreement auto-renews; current term to 2027-02-28) | K61: 46446 | L61: Contract text | N61: =IF(M61<>"",M61-Summary!$C$3,IF(K61="","",K61-Summary!$C$3)) -> 141 | O61: Active | P61: Base: 2 years from 2024-03-01 | Q61: Base auto-renews 1-yr terms | R61: Per base agreement | S61: Adds hospital/specialty bed rentals (bariatric, wound care) for LVH-Macungie and LVH-Gilbertsville at HealthTrust HPG-77980 published pricing | T61: Not stated | U61: Not stated | V61: Not stated | W61: Not stated | X61: Not stated | Y61: Amendment No. 1 clarifies customer as LVHN and its affiliates and adds as-needed bed rentals at two affiliates. Filename exp 2/28/2026 reflects base initial term, which auto-renews. | Z61: High | AA61: Text
A62: Lehigh Valley Health Network (LVHN) | B62: Lehigh Valley Health Network | C62: Lehigh Valley Health Network (LVHN) | D62: SOW_Lehigh_Valley_Bed_Tech_Services_Exp_6_30_27.pdf | E62: Service Agreement/SOW | F62: Biomed/Repair Service, Asset Mgmt/On-site, BTS Rental | G62: Direct | H62: US Med-Equip, LLC | I62: 2025-07-01 | J62: 2027-06-30 | K62: 46568 | L62: Contract text | N62: =IF(M62<>"",M62-Summary!$C$3,IF(K62="","",K62-Summary!$C$3)) -> 263 | O62: Active | P62: 2 years (body also references 36 working months) | Q62: Only by written agreement of both parties | R62: Per Section 8 of MSA (breach/insolvency) | S62: $52,500/month for 5 on-site bed technicians; Nuvay Arctic mattress replacements $895-$1,595 each | T62: Not stated | U62: Not stated | V62: Not stated | W62: Per MSA (net 30) | X62: LVHN supplies PM kits/parts; exclusions for abuse, misuse, water/fire damage; 12-month non-solicit of USME staff | Y62: SOW #2: five full-time on-site bed technicians (Cedar Crest, Hecktown Oaks, Muhlenberg) for PM/repair of hospital-owned beds, RFID tracking, foam mattress audits. Term text conflict: 2 years vs 36 months. | Z62: High | AA62: Text
A63: LHC Group | B63: LHC Group, Inc. | C63: LHC | D63: LHC _EXP_5_14_2020_Auto_2024.pdf | E63: Master/Rental Agreement | F63: MME Rental | G63: Direct | H63: US Med-Equip, Inc. | I63: 2019-05-15 | J63: 2027-05-14 (current auto-renewal term, if never cancelled) | K63: 46521 | L63: Contract text | N63: =IF(M63<>"",M63-Summary!$C$3,IF(K63="","",K63-Summary!$C$3)) -> 216 | O63: Active | P63: 1 year | Q63: Auto-renews successive 1-yr terms unless either party cancels 30 days before term end | R63: Customer only: any time on 60 days written notice; breach with 60-day cure | S63: Daily/monthly rates per Attachment A (Sole Source Vendor pricing); 25% equity discount toward buyout up to 12 months | T63: Not stated | U63: Not stated | V63: Sole source: 90%+ of annual MME rental spend | W63: Due 30 days from receipt of invoice | X63: Customer liable for loss/damage from negligence and abuse plus USME enforcement costs; full new-unit cost if not surrendered; USME CGL $1M/$3M; lost-equipment 50% buyout credit | Y63: Contract LHC040819TH. Filename 'Auto_2024' implies renewals tracked only through 2024; text auto-renews indefinitely, so confirm whether still billing. | Z63: Medium | AA63: OCR
A64: Mayo Clinic | B64: Mayo Foundation for Medical Education and Research (on behalf of affiliates) | C64: Mayo LaCrosse | D64: Mayo La Crosse Services Amendment Exp_07_28.pdf | E64: Amendment | F64: Asset Mgmt/On-site | G64: Direct | H64: US Med-Equip, LLC | I64: 2025-07 (day blank; amendment to agreement dated 2023-06-06) | J64: Not stated (filename: 2028-07) | L64: Unknown | N64: =IF(M64<>"",M64-Summary!$C$3,IF(K64="","",K64-Summary!$C$3)) | O64: Active | P64: Not stated | Q64: Not stated | R64: Not stated (per Existing Agreement) | S64: Monthly service fee increased from $31,674 to $40,031 | T64: Not stated | U64: Not stated | V64: Not stated | W64: Not stated | X64: Not stated | Y64: Amendment No. 1 to Non-Medical Services Agreement expanding on-site coverage (M-F 7am-11pm, Sat-Sun 7am-7pm CT) and adding 1 FTE + 1 PTE. Expiration not in text; filename indicates July 2028. | Z64: Medium | AA64: Text
A65: Mayo Clinic | B65: Mayo Foundation for Medical Education and Research (on behalf of affiliates) | C65: Mayo LaCrosse | D65: Mayo La Crosse Master Services Agreement Captis_Exp_7_4_28_LR.pdf | E65: Service Agreement/SOW | F65: Asset Mgmt/On-site | G65: Direct | H65: US Med-Equip, LLC | I65: 2023-07-05 | J65: 2028-07-04 | K65: 46938 | L65: Contract text | N65: =IF(M65<>"",M65-Summary!$C$3,IF(K65="","",K65-Summary!$C$3)) -> 633 | O65: Active | P65: 5 years | Q65: Auto-renews successive 1-yr terms | R65: No termination for convenience: mutual agreement, for cause (30-day cure), breach, insolvency, regulatory change (90 days), force majeure >90 days (10 days) | S65: Per Statement of Work (not included) | T65: Not stated | U65: Not stated | V65: Non-exclusive | W65: Net 30 from receipt of invoice; EFT; EDI setup within 60 days on request | X65: CGL $3M/$5M, property $500K, auto $1M, umbrella $1M, WC; Mayo additional insured; contractor indemnifies Mayo; staff replacement within 7 days on request; no subcontracting without consent | Y65: Non-Medical Services Agreement USM-315455 for on-site equipment management at Mayo (La Crosse). Filename references Captis but text has no GPO terms; SOW pricing not in file. | Z65: Medium | AA65: Text
A66: Methodist Health System (Dallas) | B66: Methodist Hospitals of Dallas d/b/a Methodist Health System | C66: Methodist Hospitals of Dallas | D66: Methodist_DFW_Master_Service_Agreement_Exp_04_30_2028.pdf | E66: Master/Rental Agreement | F66: MME Rental, BTS Rental, Respiratory | G66: Direct (GPO price-parity clause) | H66: US Med-Equip, LLC | I66: 2025-05-01 | J66: 2028-04-30 (initial term; then auto-renews) | K66: 46873 | L66: Contract text | N66: =IF(M66<>"",M66-Summary!$C$3,IF(K66="","",K66-Summary!$C$3)) -> 568 | O66: Active | P66: 3 years | Q66: Auto-renews for successive 1-yr terms | R66: Either party without cause, 30 days written notice; customer may also terminate for service shortfall (30-day cure), better pricing to other GPOs/competitors, or unavailable new technology | S66: Exhibit A primary vendor daily/monthly rates; list pricing if 90% commitment breached and uncured in 60 days | T66: Firm for Initial Term; must match more favorable pricing given to customer's GPO | U66: Quarterly rebate: 2% for one vertical (MME or BTS) as primary, 4% each if both; paid within 45 days of quarter; requires ACH, DSO 30, EMR integration effort | V66: Primary vendor: 90%+ of annual rental spend (MME and BTS); Sec. 15 states no minimum service requirements | W66: Net 30; FOB Destination; ACH required for rebate | X66: USME responsible for damage it causes (customer may offset repair costs); broad USME indemnity; CGL and professional $1M/$3M; customer termination for insurance lapse; GPO price-parity (MFN) | Y66: Replaces prior agreements with Methodist Health System (Dallas). Customer holds multiple broad termination/renegotiation rights despite 3-yr term. | Z66: High | AA66: Text
A67: Methodist Le Bonheur Healthcare | B67: Methodist Le Bonheur Healthcare | C67: Methodist LeBonheur | D67: Methodist_LeBonheur_MME_BTS_Exp_10_10_2028_LR.pdf | E67: Master/Rental Agreement | F67: MME Rental, BTS Rental | G67: Direct | H67: US Med-Equip, LLC | I67: 2023-10-11 | J67: 2028-10-10 | K67: 47036 | L67: Contract text | N67: =IF(M67<>"",M67-Summary!$C$3,IF(K67="","",K67-Summary!$C$3)) -> 731 | O67: Active | P67: 60 months | Q67: Auto-renews successive 1-yr terms | R67: Either party, without cause, 30 days written notice | S67: Primary Vendor pricing per Attachment A (monthly rental rates) | T67: Fixed 2 years; then once per contract year up to greater of 5% or prior-year Medical Care CPI-U, 30 days notice | U67: 3% annual rebate on bed and therapeutic surface rentals, paid 45 days after calendar year; 25% equity credit and lost-equipment policy | V67: Primary vendor: 90% of annual rental spend for Attachment A equipment; >5% shortfall, 60-day cure then market rates | W67: Net 30 from receipt; late interest 1.5%/month (18%/yr) | X67: Customer liable for loss/damage in custody and must insure at replacement cost; USME bears recall costs; mutual indemnity; CGL $1M/$3M; mutual assignment consent | Y67: Contract #MLH09192023MS covering Methodist Le Bonheur entities (Attachment B). Either party can exit on 30 days, so commitment is soft despite 5-yr term. | Z67: High | AA67: Text
A68: Montage Health (CHOMP) | B68: Community Hospital of the Monterey Peninsula | C68: Community Hospital of the Monterey Peninsula (CHOMP) | D68: CHOMP_BTS_Exp_1_31_26.pdf | E68: Master/Rental Agreement | F68: BTS Rental, MME Rental | G68: Vizient (Tier 4 pricing referenced) | H68: US Med-Equip, LLC | I68: 2023-02-01 | J68: 2026-01-31 initial; auto-renewed, current term through 2027-01-31 | K68: 46053 | L68: Contract text | M68: 46418 | N68: =IF(M68<>"",M68-Summary!$C$3,IF(K68="","",K68-Summary!$C$3)) -> 113 | O68: Active | P68: 3 years | Q68: Auto-renews successive 1-yr terms | R68: Either party without cause, 90 days written notice | S68: Monthly rental fee per Attachment A; Primary Vendor pricing; Vizient Tier 4 daily rates (e.g., Freedom 1000 $67.50/day) | T68: Not stated | U68: Not stated; value adds include 25% rental equity credit (up to 12 months) and 50% lost-equipment buyout credit | V68: Primary Vendor: 90%+ of annual rental spend for Covered Facilities (Attachment B); consignment equipment on site at no charge until used | W68: Net 30; USME may repossess on non-payment | X68: Customer liable for loss/damage and abuse repairs; full new-unit cost if not surrendered in good condition; mutual indemnity; USME GL $1M/$3M; California law | Y68: Consignment model for peak need with customer usage reporting. Contract # UCIMC10112022TH appears carried over from another template. Filename BTS; text covers MME primary vendor and BTS surfaces. | Z68: Medium | AA68: OCR
A69: Mount Sinai Health System | B69: The Mount Sinai Hospital, Icahn School of Medicine, St. Luke's-Roosevelt, NY Eye and Ear Infirmary, South Nassau Communities Hospital, 5 East 98th Street LLC | C69: Mount Sinai | D69: Mount_Sinai_ agreement MME_Exp_07_31_2030.pdf | E69: Master/Rental Agreement | F69: MME Rental | G69: Premier PP-NS-1662 | H69: US Med-Equip, LLC | I69: 2025-08-01 | J69: 2030-07-31 | K69: 47695 | L69: Contract text | N69: =IF(M69<>"",M69-Summary!$C$3,IF(K69="","",K69-Summary!$C$3)) -> 1390 | O69: Active | P69: 5 years | Q69: None stated | R69: Mount Sinai and USME each may terminate on 30 days written notice | S69: Primary Vendor daily/monthly rates per Attachment A | T69: Firm 2 years; then max once per contract year by greater of 2% or prior-year Medical Care CPI-U, 30 days notice | U69: Rebate: 2% for primary supplier in two verticals, 4% for three (MME, BTS, ASAP); paid annually within 30 days | V69: Primary vendor: 90%+ of annual rental spend; rebate requires 90% MME/BTS and 100% ASAP, ACH, EMR integration | W69: Net 45; written late notice with 30-day cure before credit hold; interest at max lawful rate | X69: Customer liable for loss/damage; FOB destination with USME freight risk; mutual indemnity; CGL $10M/$20M; mutual assignment consent; each entity pays separately | Y69: Established as an amendment to Premier PP-NS-1662 and bound by its terms, but PP-NS-1662 expired 11/30/2025, so the governing master needs confirming. Contract # JS03192025MS. | Z69: High | AA69: Text
A70: Mountain View Regional | B70: Las Cruces Medical Center LLC d/b/a Mountain View Regional Medical Center | C70: Mountain View Regional | D70: Mountain View Sept 2017_AR_TH_exp_9_14_2020_auto renewal.pdf | E70: Master/Rental Agreement | F70: MME Rental | G70: Direct | H70: US Med-Equip, Inc. | I70: 2017-09-15 | J70: 2020-09-14 initial; auto-renews 1-yr (current term to 2027-09-14 if not cancelled) | K70: 44088 | L70: Contract text | M70: 46644 | N70: =IF(M70<>"",M70-Summary!$C$3,IF(K70="","",K70-Summary!$C$3)) -> 339 | O70: Active | P70: 3 years | Q70: Auto-renews successive 1-yr terms unless 30 days written notice | R70: No termination for convenience in text (only non-renewal on 30 days notice; breach by Company w/30-day cure) | S70: Primary Vendor pricing per Attachment A (monthly rates); 25% equity discount toward purchase for up to 12 months | T70: Not stated | U70: Not stated | V70: Primary vendor: 95%+ of annual MME rental spend | W70: Rent due 1st of month | X70: Customer liable for loss/damage/abuse; monthly RFID verification audit by USME; mutual indemnity; USME GL $1M/$3M | Y70: Evergreen MME rental with monthly physical asset audit and RFID tagging obligation; 2017 grace period for competitive switch-out. Verify still active. | Z70: Medium | AA70: OCR
A71: Nash UNC Health Care | B71: Nash Hospital, Inc. | C71: Nash | D71: Nash_Hospital_Exp_7_31_28.pdf | E71: Master/Rental Agreement | F71: BTS Rental | G71: Direct | H71: US Med-Equip, LLC | I71: 2025-08-01 | J71: 2028-07-31 | K71: 46965 | L71: Contract text | N71: =IF(M71<>"",M71-Summary!$C$3,IF(K71="","",K71-Summary!$C$3)) -> 660 | O71: Active | P71: 3 years | Q71: Not stated | R71: No convenience termination; termination only on Event of Default | S71: Exhibit A committed schedule: 11 standard ($1,120/mo) + 5 bariatric ($1,400/mo) Advanced Wave mattress systems = $19,320/mo for 12 months; Exhibit B daily bed/surface rates | T71: Not stated | U71: Not stated | V71: Primary provider for Exhibit B equipment; 12-month committed rental of 16 units; USME exclusive service provider | W71: Due 30 days after invoice date | X71: One-way customer indemnity to USME; USME may repossess on default; defaulting party pays fees; TX law, Houston venue | Y71: Contract Nash06242025DA. Committed mattress schedule is 12 months (from 8/1/2025) within a 3-year agreement. | Z71: High | AA71: Text
A72: Natividad Medical Center (County of Monterey) | B72: County of Monterey on behalf of Natividad Medical Center | C72: Natividad Medical Ctr | D72: Natividad Medical Center_Exp_10_17_2026_Auto Renewal.pdf | E72: Master/Rental Agreement | F72: MME Rental, BTS Rental | G72: Direct | H72: US Med-Equip, LLC | I72: 2023-10-18 | J72: 2026-10-17 initial; auto-renews | K72: 46312 | L72: Contract text | N72: =IF(M72<>"",M72-Summary!$C$3,IF(K72="","",K72-Summary!$C$3)) -> 7 | O72: Active | P72: 3 years | Q72: Auto-renews successive 1-yr terms | R72: After Initial Term, either party without cause on 30 days written notice | S72: Monthly rates per Attachment A Primary Vendor pricing | T72: Fixed until 2nd anniversary; then max once per contract year by greater of 5% or Medical Care CPI-U, 30 days notice | U72: Not stated | V72: Primary vendor 80%+ of annual rental spend (MME and BTS); commitment void unless USME fills 100% of requests | W72: Net 30 from receipt by Monterey County Auditor-Controller; credit hold/market rates on nonpayment | X72: Customer liable for loss/damage and unreported damage; broad USME indemnity of County; CGL $1M/$3M, auto $500K, EL $1M; County additional insured; CA law, Monterey venue | Y72: Initial term ends 10/17/2026 and rolls to 1-yr renewal; price increase right available now. Fill-rate carve-out weakens the 80% commitment. | Z72: High | AA72: OCR
A73: Nebraska Methodist Health System | B73: Nebraska Methodist Health System, Inc. (and affiliates) | C73: Nebraska Methodist | D73: Nebraska Methodist_BTS_Exp_04_14_28.pdf | E73: Master/Rental Agreement | F73: BTS Rental | G73: Direct (Vizient/MSS reporting) | H73: US Med Equip, LLC | I73: 2025-04-15 (date of last signature) | J73: 2028-04-14 | K73: 46857 | L73: Contract text | N73: =IF(M73<>"",M73-Summary!$C$3,IF(K73="","",K73-Summary!$C$3)) -> 552 | O73: Active | P73: 3 years | Q73: None stated | R73: MHS only, 90 days written notice without cause; either party 30-day cure for breach | S73: Pricing per Exhibit B.1 (primary vendor, market-share) and B.2 (non-commitment) | T73: Firm for full term | U73: Supplier reports sales and pays Vizient/MSS admin fees where products are on those agreements | V73: Primary Vendor: 80%+ of annual rental spend for Exhibit B.1 equipment | W73: ACH payment at invoice due date (thirty days); optional GHX ePay 10-day pay less 2% | X73: Mutual indemnity; no consequential damages (carve-out for supplier gross negligence); insurance $1M/$3M; supplier may not assign without consent; FOB destination; NE law | Y73: Applies to direct and SSS distributor purchases. New evolutionary products added at current pricing. | Z73: High | AA73: Text
A74: NewYork-Presbyterian | B74: The New York and Presbyterian Hospital; NewYork-Presbyterian/Queens; Hudson Valley Hospital Center | C74: New York Presbyterian | D74: NYP_Enterprise_Agreement_for_Vizient_Products_and_Services_Exp_09_30_29.pdf | E74: Pricing Exhibit | F74: MME Rental, Respiratory | G74: Vizient CE7782 | H74: US Med-Equip, LLC | I74: 2025-12-01 | J74: 2029-09-30 | K74: 47391 | L74: Contract text | N74: =IF(M74<>"",M74-Summary!$C$3,IF(K74="","",K74-Summary!$C$3)) -> 1086 | O74: Active | P74: ~46 months | Q74: None stated | R74: Either party, 90 days written notice without cause; 30-day cure for breach | S74: Custom daily/monthly rates per Exhibit A (may differ from Vizient pricing) | T74: Firm through Term | U74: Annual sales volume rebate 3% ($1M) to 5% ($5M+); void if hospital joins Vizient Impact Standardization; Vizient admin fees apply | V74: 80% of annual MME rental spend (Exhibit C), with exceptions | W74: Net 30; 1% discount if paid in 10 days by ACH/wire; 1%/month late interest; 30 days notice before credit hold | X74: Cannot suspend critical patient care products; strict software/security warranties; 7-year record retention; NY law | Y74: Hospital-level pricing agreement under Vizient CE7782, outlasting the 9/30/2027 Vizient term. BTS can be added if NYP starts purchasing. | Z74: High | AA74: Text
A75: Nobis Rehabilitation Partners | B75: Nobis Rehabilitation Partners (as Manager for Customers in Attachment B) | C75: Nobis Rehab | D75: Nobis_Rehab_Agreement_MME_BTS_Exp_11_30_26_Auto Renewal.pdf | E75: Master/Rental Agreement | F75: MME Rental, BTS Rental | G75: Vizient CE7073; Vizient CE3363 | H75: US Med-Equip, LLC | I75: 2023-12-01 | J75: 2026-11-30 (auto-renews 1-yr) | K75: 46356 | L75: Contract text | N75: =IF(M75<>"",M75-Summary!$C$3,IF(K75="","",K75-Summary!$C$3)) -> 51 | O75: Active | P75: 3 years | Q75: Auto-renews successive 1-yr periods | R75: Either party without cause on 30 days written notice; breach w/60-day cure | S75: Vizient Tier 3 (90% committed) rates on CE7073 and CE3363 (Attachment A daily rates) | T75: Not stated | U75: Not stated | V75: Primary vendor: 90%+ of annual rental spend on CE7073/CE3363 products | W75: Net 30 | X75: Customer liable for loss/damage; full new replacement cost if not returned; mutual indemnity; USME GL $1M/$3M | Y75: Covers Nobis rehab hospitals (e.g., Oklahoma City, Shreveport). Manager has no direct purchase obligation. Initial term ends 11/30/2026 then auto-renews. | Z75: High | AA75: OCR
A76: North Memorial Health | B76: North Memorial Health Care | C76: North Memorial HealthCare | D76: First Amendment to NMHC Equipment Mgt Service Agreement_06_30_27_Auto.pdf | E76: Amendment | F76: Asset Mgmt/On-site, MME Rental | G76: Direct | H76: US Med-Equip, LLC (assignee of Freedom Medical, Inc.) | I76: 2025-11-07 | J76: 2027-06-30 | K76: 46568 | L76: Contract text | N76: =IF(M76<>"",M76-Summary!$C$3,IF(K76="","",K76-Summary!$C$3)) -> 263 | O76: Active | P76: 5 years (orig. 2021-04-29 to 2026-06-30) + 1-yr extension | Q76: Not stated in amendment | R76: Per underlying agreement (not stated) | S76: Extension term (7/1/26-6/30/27) flat $94,103.60/mo: pool staffing $50,884 ($35,104 NMH, $15,780 Maple Grove) + 240 overage pumps at $180.04/mo | T76: Fixed for extension term | U76: Not stated | V76: Not stated | W76: Per underlying agreement | X76: Title to 640 Baxter Spectrum IQ pumps transfers to customer at no cost 6/30/26; 240 overage pumps transfer 6/30/27 contingent on full performance; MN law | Y76: Assigns FMI equipment management agreement to USME and extends one year. Covers North Memorial and Maple Grove hospitals. Filename says 'Auto' but no auto-renewal in amendment text. | Z76: High | AA76: OCR
A77: Ochsner Health | B77: Ochsner Clinic Foundation | C77: Ochsner | D77: Ochsner Clinic Foundation_Vizient_MME_Exp9_30_29_auto renew.pdf | E77: Master/Rental Agreement | F77: MME Rental, Respiratory, Asset Mgmt/On-site | G77: Direct (Contract # OH07262024JD) | H77: US Med-Equip, LLC | I77: 2024-10-01 | J77: 2029-09-30 | K77: 47391 | L77: Contract text | N77: =IF(M77<>"",M77-Summary!$C$3,IF(K77="","",K77-Summary!$C$3)) -> 1086 | O77: Active | P77: 60 months | Q77: Auto-renews successive 1-yr terms | R77: Either party with or without cause, 90 days written notice | S77: Primary Vendor daily/monthly rates per Attachment A; 50% rental equity toward lost equipment, 25% equity toward purchase | T77: Fixed for term (pricing effective throughout term) | U77: Not stated | V77: Primary vendor: 90%+ of annual rental spend; after 60-day cure, list pricing for remaining term | W77: Net 30; late interest up to 1.5%/month (18%/yr); credit hold/list pricing on delinquency | X77: Customer liable for loss/damage (excl. wear); mutual indemnity; no consequential damages; CGL $1M/$3M primary, no insured-v-insured exclusion; mutual consent to assign; LA statutory employer | Y77: Covers ~40 Ochsner LA/MS hospitals (Attachment B). Monthly rental-age reports and RFID scans owed. Filename references Vizient but text is a direct agreement with no Vizient contract cited. | Z77: High | AA77: Text
A78: OU Health | B78: OU Medicine, Inc. d/b/a OU Health | C78: OU Health | D78: OU Health_Rental Agreement_Exp_10_31_27_auto renew.pdf | E78: Master/Rental Agreement | F78: MME Rental, Respiratory | G78: Direct | H78: US Med-Equip, LLC | I78: 2024-11-01 | J78: 2027-10-31 (initial term; then auto-renews) | K78: 46691 | L78: Contract text | N78: =IF(M78<>"",M78-Summary!$C$3,IF(K78="","",K78-Summary!$C$3)) -> 386 | O78: Active | P78: 3 years | Q78: Auto-renews for successive 1-yr terms | R78: After Initial Term, either party without cause on 30 days written notice; breach with 60-day cure | S78: Attachment A daily/monthly MME rental rates (contract #09042024JD) | T78: Pricing effective through term (fixed) | U78: Not stated | V78: Not stated | W78: Net 30; late interest lower of 1.5%/month or legal max; credit hold, repossession and list pricing on non-payment | X78: Customer liable for loss/damage and must insure at replacement cost; full replacement cost if not returned; mutual indemnity; CGL $1M/$3M; Harris County TX venue | Y78: Standard USME MME rental agreement for OU Health with broad monitoring, infusion and respiratory price list. | Z78: High | AA78: Text
A79: Partners Cooperative | B79: Partners Cooperative, Inc. | C79: Partners Coop - Asset Management | D79: Partners Cooperative Asset Manage_Exp_8_31_27_ext 2029.pdf | E79: Rebate Agreement | F79: Asset Mgmt/On-site | G79: Partners Cooperative PC-SVC90 | H79: US Med-Equip, LLC | I79: 2024-09-01 | J79: 2027-08-31 (up to 2029-08-31 with renewals) | K79: 46630 | L79: Contract text | N79: =IF(M79<>"",M79-Summary!$C$3,IF(K79="","",K79-Summary!$C$3)) -> 325 | O79: Active | P79: 3 years | Q79: Two 1-yr renewals automatic unless 30 days non-renewal notice | R79: Either party, without cause, 90 days written notice; member end-user agreements: member 30 days, USME 90 days | S79: Per member End-User Service Agreement/SOW pricing (Attachment A/B) | T79: Not stated | U79: 2% GPO fee on total gross revenue from members, paid monthly within 30 days; also Vizient fees if contracted | V79: Non-exclusive; no commitment | W79: Member pays undisputed invoices within 30 days; late interest 1.5%/month | X79: USME liability capped at 12 months' fees for applicable SOW; consequential damages excluded | Y79: GPO fee agreement plus template Member Services Agreement/SOW for asset management. Filename 'ext 2029' matches the two 1-yr renewal options, not a signed extension. | Z79: High | AA79: Text
A80: Partners Cooperative | B80: PARTNERS Cooperative, Inc. | C80: Partners Coop MME - CE71 | D80: USME Partners Coop CE71 MME Exp 9_30_2028_ext 2030.pdf | E80: GPO Agreement | F80: MME Rental | G80: Partners Cooperative CE71 | H80: US Med-Equip, LLC | I80: 2025-01-01 | J80: 2027-09-30 per cover page (filename says 2028-09-30, ext 2030) | K80: 46660 | L80: Contract text | N80: =IF(M80<>"",M80-Summary!$C$3,IF(K80="","",K80-Summary!$C$3)) -> 355 | O80: Active | P80: 3 years per Sec. 13(a) | Q80: Auto-renews two 1-yr terms unless 30 days notice of non-renewal | R80: Either party without cause on 90 days written notice; 30 days for material breach; member End-User Agreements: member 30 days, vendor 90 days | S80: Exhibit A pricing fixed for Initial Term; A-Tier GPO most-competitive pricing obligation | T80: Fixed for Initial Term; then annually by CPI-U capped at 2%; unauthorized increase is material breach | U80: 0.5% GPO fee on total gross revenue, monthly; 1% cash rebate to 90% primary-provider members; extra 1% bonus if annual Partners volume >$7M | V80: No mandatory commitment; 1% rebate requires 90% LOC primary provider; DSO <=30 days for rebates | W80: Members: 1% 10 days via ACH, net 30 | X80: MFN-style A-Tier pricing with 10-business-day price-correction duty; 95% fill-rate commitment; delivery <=10 days; Partners audit rights; surcharges must be disclosed | Y80: Partners Co-op (Southeast IDN cooperative) MME rental agreement. Dates conflict: cover says 1/1/2025 to 9/30/2027 (3 years would end 12/31/2027); filename says 9/30/2028 with extension to 2030. | Z80: Medium | AA80: Text
A81: Partners Cooperative | B81: Partners Cooperative, Inc. | C81: Partners Coop - Refurbished | D81: USME Partners Refurb Equip Sale_EXP 3_30_2028.pdf | E81: Purchase/Sale Agreement | F81: Refurb Equipment Sales | G81: Partners PC-CE61 | H81: US Med-Equip (text also names 'MEDLINE' as VENDOR - template error) | I81: 2025-04-01 | J81: 2028-03-31 | K81: 46843 | L81: Contract text | N81: =IF(M81<>"",M81-Summary!$C$3,IF(K81="","",K81-Summary!$C$3)) -> 538 | O81: Active | P81: 36 months | Q81: Option to renew for two 1-yr terms | R81: Either party without cause, 30 days written notice; Partners may terminate immediately on failure to supply/recall | S81: Exhibit A refurb sale prices at 20% off list (e.g., Servo-i U $10,500; Mac 5500 $4,250; Alaris 8015 $1,034.80) | T81: Fixed 36 months; vendor may modify not more than once annually with documentation via written amendment | U81: 3% quarterly GPO fee on paid sales, due within 30 days of quarter end | V81: None; A-Tier GPO best pricing obligation (10-business-day response to non-compliant pricing) | W81: Net 30 to Distribution Centers; member terms per member requirement; FOB destination | X81: 1-yr warranty (90 days accessories/repairs); CGL $1M/$3M; no consequential damages; innovative tech capped at 10% over replaced tech | Y81: Refurbished MME sales (vents, monitors, infusion, bladder scanners) to Partners members. Vendor named 'MEDLINE' in opening paragraph - drafting error to correct. Filename expiry 3/30/2028 vs computed 3/31/2028. | Z81: High | AA81: Text
A82: Partners Cooperative | B82: Baptist Health (Baptist Health System, Jacksonville FL) | C82: Baptist Health | D82: BTS_LOC_Baptist_Jacksonville_exp_6_10_2028_ext 2030.pdf | E82: GPO Letter of Participation/SIP | F82: BTS Rental | G82: Partners Cooperative CE69 | H82: US Med-Equip, Inc. (text); US Med-Equip, LLC on price file | I82: 2025-02-01 | J82: Upon expiration/termination of the underlying Agreement (filename: 2028-06-10, ext 2030) | K82: 46914 | L82: Contract text | N82: =IF(M82<>"",M82-Summary!$C$3,IF(K82="","",K82-Summary!$C$3)) -> 609 | O82: Active | P82: Coterminous with Agreement | Q82: Not stated | R82: Not stated | S82: Partners Cooperative CE69 published daily pricing (Exhibit B) | T82: Not stated | U82: Not stated | V82: Minimum 90% of annual BTS spend with USME on specialty wound care products; utilization reports bi-annually | W82: DSO not to exceed Net 30; consolidated invoice by campus paid on one invoice | X82: USME must deliver/pick up within 24 hrs, supply nurse-call cables, daily census report incl. patient names, monthly spend reports | Y82: Covers Baptist Health Jacksonville members incl. Wolfson Children's and Baptist Medical Centers (Exhibit A). Expiration not in text; filename indicates 6/10/2028 extended to 2030. | Z82: Medium | AA82: Text
... A96: ScionHealth (Kindred) | B96: Kindred Healthcare Operating, LLC (ScionHealth), with HealthTrust Purchasing Group, L.P. | C96: Kindred Healthcare - ScionHealth | D96: ScionHealth_Kindred HealthcareExp_8_31_2027_auto renew.pdf | E96: Master/Rental Agreement | F96: MME Rental | G96: HealthTrust HPG-7093 | H96: US Med-Equip, LLC | I96: 2024-09-01 | J96: 2027-08-31 | K96: 46630 | L96: Contract text | N96: =IF(M96<>"",M96-Summary!$C$3,IF(K96="","",K96-Summary!$C$3)) -> 325 | O96: Active | P96: 3 years | Q96: Auto-renews 1-yr terms | R96: After initial term either party 30 days without cause; customer 60 days if USME ceases to be GPO-contracted supplier; 60-day breach cure | S96: Primary Vendor pricing per Attachment A; reverts to HealthTrust pricing if commitment missed or late payment uncured | T96: Fixed until 3rd anniversary; then once per year up to greater of 5% or Medical Care CPI-U with 30 days notice | U96: Rebate 2%/4%/6% for primary supplier in 1/2/3 verticals (MME, BTS, ASAP); DSO <=45, ACH, EMR integration, business reviews | V96: Primary vendor: >=90% of annual rental spend for Attachment B facilities; 60-day assurance period; not a breach | W96: Net 30 from receipt of invoice; 60-day cure for late payment before repossession/credit hold | X96: Customer pays repair or replacement cost less 50% of rents paid; customer insures equipment at replacement cost; mutual indemnity; no consequential damages; assignment needs mutual consent; CGL $1M/$3M | Y96: Tri-party agreement structured as amendment to HPG-7093 covering ScionHealth/Kindred facilities. Filename indicates auto-renew after 8/31/2027. | Z96: High | AA96: Text
A97: Select Medical | B97: Select Medical Corporation | C97: Select Medical | D97: SELECT Amendment_Advance Wave_Exp_9_30_2023_Auto Renew.PDF | E97: Amendment | F97: BTS Rental | G97: Direct | H97: Freedom Medical, Inc. | I97: 2022-01-01 | J97: 2023-09-30 initial; auto-renewing 1-yr terms (current term to 2027-09-30) | K97: 45199 | L97: Contract text | M97: 46660 | N97: =IF(M97<>"",M97-Summary!$C$3,IF(K97="","",K97-Summary!$C$3)) -> 355 | O97: Active | P97: Base agreement 2019-10-01; initial term extended to 2023-09-30 | Q97: Auto-renews 1-yr terms unless 90 days written non-renewal notice | R97: Hospital may terminate without liability for pervasive non-delivery of standard products (Sec 3(c)); otherwise non-renewal on 90 days notice | S97: Not stated (base Therapy Support Service Rental Agreement Exhibit A) | T97: Not stated | U97: 4% annual rebate on rental revenue for Exhibit A products, paid by check within 30 days after each calendar-year rebate period | V97: Not stated | W97: Not stated | X97: Not stated | Y97: First amendment to Freedom Medical support surface national rental agreement (Advanced Wave) with Select Medical. No assignment to USME in this document - confirm assignment. | Z97: High | AA97: Text
A98: Smith & Nephew | B98: Smith & Nephew, Inc. | C98: Smith + Nephew | D98: SN Amendment to Master Service Agrmt_2022_exp_6_1_2027.pdf | E98: Amendment | F98: MME Rental, Other | G98: Direct | H98: US Med-Equip, LLC (assignee of US Med-Equip, Inc.) | I98: 2022-06-01 (amends MSA and SOW No. 1 effective 2019-03-04) | J98: 2027-06-01 | K98: 46539 | L98: Contract text | N98: =IF(M98<>"",M98-Summary!$C$3,IF(K98="","",K98-Summary!$C$3)) -> 234 | O98: Active | P98: Amendment term 2022-06-01 to 2027-06-01; MSA continues while any SOW in effect | Q98: Not stated | R98: Either party, with or without cause, 120 days written notice (MSA or any SOW); for uncured breach (30 days) or insolvency | S98: Not stated in amendment (per underlying MSA/SOW No. 1) | T98: Not stated | U98: Not stated | V98: USME must rent exclusively S&N RENASYS NPWT pumps to S&N customers and to its other NPWT customers (with exceptions); S&N uses USME as exclusive peak rental provider where not constrained/out of coverage | W98: Not stated | X98: Mutual exclusivity obligations; underlying MSA terms govern other risk items | Y98: Vendor partnership: USME provides peak and daily rental of Smith & Nephew NPWT (RENASYS) pumps to S&N customers. Amendment signed 6/1/2022 (DocuSign 9/19/2022); USME exclusivity restricts offering competing NPWT pumps. | Z98: High | AA98: OCR
A99: St. Elizabeth Healthcare | B99: St. Elizabeth Healthcare | C99: St. Elizabeth Health | D99: St Elizabeth Health ASAP Exp 11_17_2029_ext 2031.pdf | E99: Service Agreement/SOW | F99: Asset Mgmt/On-site | G99: Partners Cooperative MSA (9/1/2024) | H99: US Med-Equip, LLC | I99: 2024-11-18 | J99: 2029-11-17 (two 1-yr auto-renewals to 2031) | K99: 47439 | L99: Contract text | N99: =IF(M99<>"",M99-Summary!$C$3,IF(K99="","",K99-Summary!$C$3)) -> 1134 | O99: Active | P99: 5 years | Q99: Auto-renews two 1-yr terms unless St. Elizabeth gives 60 days notice | R99: Per MSA Article 7: 90 days written notice (per SEH cover sheet) | S99: Fixed $934,812/yr, paid $77,901/month; allocated across 6 sites | T99: Not stated | U99: Not stated | V99: Not stated | W99: Per MSA Section 3.3 | X99: 15-min delivery for on-site rush orders, 2-hr + drive time off-site; PAR checks; QBRs; staff competency docs; no explicit penalties | Y99: On-site equipment management (ASAP) at Edgewood, Florence, Ft Thomas, Dearborn, Grant, Covington covering USME and customer-owned equipment. | Z99: High | AA99: OCR
A100: St. Jude | B100: St. Jude Children's Research Hospital | C100: St. Jude | D100: St Jude Childrens_Exp_10_31_2022_Auto Renew.pdf | E100: Master/Rental Agreement | F100: MME Rental | G100: Vizient CE7073 | H100: US Med-Equip, LLC | I100: 2019-11-01 | J100: 2026-10-31 (current auto-renewal term) | K100: 46326 | L100: Contract text | N100: =IF(M100<>"",M100-Summary!$C$3,IF(K100="","",K100-Summary!$C$3)) -> 21 | O100: Active | P100: 3 years | Q100: Auto-renews successive 1-yr terms unless cancelled 30 days before term end | R100: Either party, 30 days written notice | S100: Monthly/daily rates per Vizient CE7073 Exhibit A; 25% equity discount toward buyout up to 12 months | T100: Not stated (per Vizient CE7073) | U100: Not stated (per Vizient) | V100: Not stated | W100: Due on 1st day of each month | X100: Customer liable for loss/damage and abuse plus enforcement costs; full new-unit cost if not surrendered; USME CGL $1M/$3M; 30-day cure | Y100: Contract 093019STJ_MS. Current renewal term ends 10/31/2026; non-renewal notice deadline about 10/1/2026 has passed, so it will likely roll to 10/31/2027. | Z100: High | AA100: OCR
A101: Stanford Health Care | B101: Stanford Health Care Tri-Valley | C101: Stanford Health Care - Tri-Valley | D101: Stanford Health Care Tri Valley_Exp_07_31_2027.Pdf | E101: Master/Rental Agreement | F101: MME Rental, Respiratory | G101: Direct | H101: US Med-Equip, LLC | I101: 2024-08-01 | J101: 2027-07-31 | K101: 46599 | L101: Contract text | N101: =IF(M101<>"",M101-Summary!$C$3,IF(K101="","",K101-Summary!$C$3)) -> 294 | O101: Active | P101: 3 years | Q101: Not stated | R101: Either party may terminate without cause (notice period illegible in text) | S101: Daily/monthly rental rates per Attachment A (model-level list) | T101: Firm 2 years; thereafter max once per contract year tied to Medical Care CPI-U (text partially garbled) | U101: Not stated | V101: Not stated | W101: Net 30 from invoice; late interest lesser of 1%/month or legal max; credit hold after 30-day default notice | X101: Customer liable for loss/damage (depreciated value for lost/stolen units); no consequential damages; CGL $1M/$3M with 2-yr tail; 4-hr delivery 24/7; California law | Y101: MME peak rental agreement (Contract #SHTV082124KS) for Stanford Tri-Valley with strict invoicing standards (PO per invoice). Some clauses garbled in source text. | Z101: Medium | AA101: Text
A102: State of California - CDCR | B102: California Department of Corrections and Rehabilitation / California Correctional Health Care Services (CDCR/CCHCS) | C102: California Dept. of Corrections | D102: CDCR_MME_BTS_Exp_6_30_2029.pdf | E102: Master/Rental Agreement | F102: BTS Rental, MME Rental, Biomed/Repair Service | G102: Direct (State Agreement 25-00237; Solicitation SD25-00047) | H102: US Med-Equip, LLC | I102: 2026-07-01 (or upon approval; DGS approved 2026-06-24) | J102: 2029-06-30 | K102: 47299 | L102: Contract text | N102: =IF(M102<>"",M102-Summary!$C$3,IF(K102="","",K102-Summary!$C$3)) -> 994 | O102: Active | P102: 3 years | Q102: None stated; amendments require mutual consent and DGS approval | R102: State may terminate with 30 days written notice; contractor may request only if State substantially fails to perform; State may cancel if funding reduced | S102: Daily rental rates per Exhibit B-1 Rate Sheet; max contract amount $5,072,709.90; equivalent substitutes at same daily rate | T102: Not stated (rates fixed per Rate Sheet; amendment only for CalHR benefit rate changes) | U102: Not stated | V102: As-needed basis; no volume guarantee; DVBE subcontractor participation commitment | W102: Monthly in arrears on approved invoices with service reports; CA Prompt Payment Act (Gov. Code 927) | X102: State not liable for loss/damage to rental equipment except its negligence; 24-hr delivery response, 24/7 service; 50% of rent paid credited to buyout; contractor repairs State property damage; GC 19134 benefits | Y102: Statewide therapeutic patient care equipment rental for CDCR institutions (Exhibit A-2), with portal ordering (2 logins per institution) and repair services. Signed by Clay Rose 6/16/2026; rate sheet OCR garbled. | Z102: Medium | AA102: OCR
A103: State of Louisiana | B103: State of Louisiana (Office of State Procurement) | C103: State of Louisiana | D103: 4400029974 - Emergency Rental of Hospital Beds - SW.pdf | E103: Master/Rental Agreement | F103: BTS Rental | G103: Direct (LA contract 4400029974) | H103: US Med-Equip Inc | I103: 2024-06-28 (current renewal 2026-05-01) | J103: 2027-04-30 | K103: 46507 | L103: Contract text | N103: =IF(M103<>"",M103-Summary!$C$3,IF(K103="","",K103-Summary!$C$3)) -> 202 | O103: Active | P103: 12 months per renewal; total max 36 months | Q103: Annual renewals; total term not to exceed 36 months | R103: State: for convenience on 30 days written notice; for cause on 30 days; non-appropriation | S103: $33.99/day per hospital bed (Paramount A6), per Attachment B | T103: Not stated (fixed unit price) | U103: Not stated | V103: Non-exclusive; no guaranteed quantities; USME committed 50+ beds within 12-24 hrs, 24+ per day | W103: Not stated (unit price basis; invoices to using agency) | X103: Broad indemnity of State; CGL $1M/$2M, auto $1M, WC/EL $1M, State as additional insured; detainment/reroute charges $125 | Y103: Statewide emergency contingency contract to rent hospital beds during Governor-declared emergencies; 24/7 availability, delivery 8-24 hrs, inside delivery at no charge. | Z103: High | AA103: Text
A104: State of Louisiana | B104: State of Louisiana, Office of State Procurement | C104: State of Louisiana | D104: Renewal Notification 4400029974.pdf | E104: Extension | F104: BTS Rental | G104: Direct (State Contract 4400029974, T-Number 92821) | H104: US Med-Equip, Inc. (as written) | I104: 2026-05-01 | J104: 2027-04-30 | K104: 46507 | L104: Contract text | N104: =IF(M104<>"",M104-Summary!$C$3,IF(K104="","",K104-Summary!$C$3)) -> 202 | O104: Active | P104: Not stated (renewal of 12 months) | Q104: State exercised renewal option for 12 months at original terms | R104: Per original contract termination provisions (not stated here) | S104: Original terms, conditions and prices/discounts | T104: None (renewed at original prices) | U104: Not stated | V104: Not stated | W104: Not stated | X104: Not stated | Y104: State renewal notice for emergency hospital bed rental contract (Southwest region). USME must submit a contract usage report about 4 months before 4/30/2027 (around Jan 2027). Entity named 'US Med-Equip, Inc.' | Z104: High | AA104: Text
A105: STERILECO / VA North Texas Health Care System | B105: STERILECO LLC (prime contractor) | C105: Serileco LLC | D105: STERILECO_MME_Exp 06_07_2028.pdf | E105: Service Agreement/SOW | F105: Biomed/Repair Service, Respiratory | G105: Direct (Subcontract STERILECO-SUB-26-0077 under federal prime contract) | H105: US Med-Equip | I105: 2026-05-07 (signature); base period starts 2026-06-06 | J105: 2027-06-05 base; 2028-06-07 if option year exercised | K105: 46543 | L105: Contract text | N105: =IF(M105<>"",M105-Summary!$C$3,IF(K105="","",K105-Summary!$C$3)) -> 238 | O105: Active | P105: 1 base year + 1 option year | Q105: One option year at STERILECO's unilateral election; STERILECO may require extension at same rates | R105: STERILECO for convenience only if government terminates its prime contract; USME may terminate for convenience on 30 days written notice (performance continues during notice); default with 10-day cure | S105: Firm fixed unit price per CLIN: Hamilton MR-1 and G5 ventilator annual service contracts; total ~$95,430 | T105: No price increase on option exercise; rate changes only for wage law mandates via good-faith negotiation | U105: Not stated | V105: Non-exclusive; work only on funded Orders; funding may be incremental | W105: Net 30 from receipt of correct invoice; ACH; payments withheld without valid COI | X105: USME indemnifies STERILECO; FAR government property liability; no direct contact with end customer; minimum insurance GL $500K, employer liability $100K; NCR quality process | Y105: Subcontract for OEM-spec service of Hamilton G5/MR-1 ventilators at VA Medical Center Dallas (VANTHCS); signed by Clay Rose as CEO. Filename labels it MME but scope is biomed service. | Z105: High | AA105: Text
A106: Tampa General Hospital | B106: Tampa General Hospital | C106: Tampa General | D106: Tampa General_Exp_10_28_2022_Auto_Renew.pdf | E106: Master/Rental Agreement | F106: MME Rental, Asset Mgmt/On-site | G106: Vizient (Tier 3 pricing referenced) | H106: US Med-Equip, LLC | I106: 2019-10-29 (per filename; day/month illegible in text) | J106: 2022-10-28 initial; auto-renewing | K106: 44862 | L106: Contract text | M106: 46323 | N106: =IF(M106<>"",M106-Summary!$C$3,IF(K106="","",K106-Summary!$C$3)) -> 18 | O106: Active | P106: 3 years | Q106: Auto-renews successive 1-yr terms unless cancelled 30 days before term end | R106: Non-renewal by either party with 30 days notice; termination for breach (60-day cure) | S106: Vizient Tier 3 rates (90% LOC) per Attachment A; other Vizient price-file items at Tier 3; 25% equity discount up to 12 months | T106: Not stated | U106: Not stated | V106: Tier 3 pricing tied to 90% level of commitment | W106: Due on 1st of each month | X106: Customer responsible for loss/damage; 50% of rent paid applied to lost-equipment buyout with quarterly RFID scans; full new-unit cost if not returned; CGL $1M/$3M; Texas law, Harris County | Y106: Contract #109414. Includes mySmarts portal, RFID tracking and PM notification value-adds. Auto-renews annually, so likely still in effect. | Z106: Medium | AA106: OCR
A107: Tenet Healthcare | B107: Tenet Business Services Corporation (on behalf of Tenet affiliates/facilities) | C107: Tenet Healthcare | D107: Tenet MME Rental Exp 2_15_26_ext 2028.pdf | E107: Service Agreement/SOW | F107: MME Rental | G107: HPG-7093 | H107: US Med-Equip LLC | I107: 2025-06-01 (or later execution) | J107: 2029-05-31 | K107: 47269 | L107: Contract text | N107: =IF(M107<>"",M107-Summary!$C$3,IF(K107="","",K107-Summary!$C$3)) -> 964 | O107: Active | P107: 4 years | Q107: One 1-yr extension by mutual written agreement before expiry | R107: Either party, without cause, 90 days written notice | S107: Primary Vendor daily/monthly rates per Exhibit C (e.g., PB 840 $24.16/day) | T107: Not stated | U107: 3% quarterly rebate on all spend, paid 45 days after quarter; 25% equity credit; 50% lost-equipment credit after 3 RFID scans | V107: Primary vendor: 80% of annual MME rental spend (Tenet and USPI facilities on HealthTrust roster); 90-day cure then market rates; carve-outs for clinical incompatibility | W107: Net 45 from invoice via ACH; 45-day DSO per facility for rebate | X107: Mutual indemnity; CGL with $3M products aggregate, Tenet additional insured; USME cannot assign without consent (Tenet can); arbitration; quarterly business reviews; RFID audits | Y107: Tenet/USPI MME services agreement under HPG-7093 with initial RFID audit in 8 weeks and biannual scans. Filename 'Exp 2_15_26 ext 2028' conflicts with text (4-yr term from 6/1/2025, to 5/31/2029). | Z107: High | AA107: Text
A108: Texas Purchasing Coalition (TPC) | B108: TTPC, LLC (Texas Purchasing Coalition) | C108: TPC Rental | D108: TPC_Rental_Exp_08_31_2017_auto renew.pdf | E108: GPO Agreement | F108: MME Rental | G108: TPC Standard Purchased Services Agreement (Direct GPO) | H108: US Med-Equip, Inc. | I108: 2014-09-01 | J108: 2017-08-31 initial; auto-renewing 1-yr terms (current term through 2027-08-31 if not terminated) | K108: 42978 | L108: Contract text | M108: 46630 | N108: =IF(M108<>"",M108-Summary!$C$3,IF(K108="","",K108-Summary!$C$3)) -> 325 | O108: Active | P108: 3 years | Q108: Auto-renews successive 1-yr terms | R108: Either party 90 days before renewal term; TPC may terminate anytime on 30 days notice; fees continue on Separate Agreements post-termination | S108: Exhibit D item pricing (daily/monthly per model) | T108: Fixed for term; Supplier may only decrease | U108: 1% TPC admin fee on Participant gross revenue (Exhibit B says paid monthly; Sec 3 says quarterly within 30 days) plus 3% to TPC's GPO; 1%/mo late fee; participant rebates paid directly | V108: Participants commit 95% of medical equipment rental spend to USME; 2-wk minimum on 3100A/B oscillators; 1-month minimum for suction cleanout | W108: 2% 15, Net 45 (participants) | X108: Supplier indemnifies TPC/Participants; TPC liability capped at 3 months of fees; change of control = assignment requiring consent; TPC/Participants as additional insureds | Y108: Coalition GPO agreement for Texas members; members sign Separate Agreements. Auto-renewal keeps it alive unless terminated; confirm whether still in use. | Z108: Medium | AA108: OCR
A109: TPC | B109: TTPC, LLC (TPC) | C109: TPC Rental | D109: TPC_2nd_Amendment-_Product_Add.pdf | E109: Amendment | F109: BTS Rental, Restraints/Posey | G109: Direct | H109: US Med Equip, Inc. | I109: 2025-03-15 | J109: Not stated (per base Services Agreement dated 2014-09-01) | K109: 41883 | L109: Contract text | N109: =IF(M109<>"",M109-Summary!$C$3,IF(K109="","",K109-Summary!$C$3)) -> -4422 | O109: Active | P109: Not stated | Q109: Not stated | R109: Not stated | S109: Adds Exhibit D BTS products: Tier 1/Access vs Tier 2/80% Committed daily pricing (beds, LAL mattresses, bariatric chairs/wheelchairs, Posey items) | T109: Not stated | U109: Not stated | V109: Tier 2 pricing requires 80% commitment | W109: Not stated | X109: Not stated | Y109: Second amendment to TPC Standard Purchased Services Agreement (2014) adding BTS products and pricing; signed 3/28/2025 by Mark Phalen (TPC CFO) and Tim Heck. Base term not in this document; confirm underlying agreement is still in force. | Z109: Medium | AA109: Text
A110: TPC (Texas Purchasing Coalition) | B110: TTPC, LLC (Texas Purchasing Coalition) | C110: TPC Refurbished | D110: TPC_Refurbish Equipment_Exp_08_14_2019_auto renew.pdf | E110: GPO Agreement | F110: Refurb Equipment Sales | G110: TPC Standard Agreement | H110: US Med-Equip, Inc. | I110: 2016-08-15 | J110: 2019-08-14 initial; auto-renewed, current term through 2027-08-14 | K110: 43691 | L110: Contract text | M110: 46613 | N110: =IF(M110<>"",M110-Summary!$C$3,IF(K110="","",K110-Summary!$C$3)) -> 308 | O110: Active | P110: 3 years | Q110: Auto-renews successive 1-yr terms; 90 days notice before renewal to non-renew | R110: Either party: 90 days notice before a renewal term; TPC anytime with or without cause on 30 days notice | S110: Quote-based refurbished equipment pricing (typically 20-50% below new); quarterly group-buy discounts | T110: Not stated | U110: TPC admin fee 3% of gross revenue from Participants, paid quarterly within 30 days; growth bonus admin fee 1-3% by annual spend tiers (2016-2018); 1%/month late fee | V110: No member purchase obligation | W110: Members: 2% 15, Net 45 | X110: Change of control of voting equity counts as assignment requiring consent; fees continue on Separate Agreements post-termination; supplier indemnifies TPC/Participants; TPC liability capped at 3 months' fees | Y110: Refurbished capital equipment (pumps, monitors) GPO agreement. Change-of-control clause relevant to PE ownership; fee tail survives on member Separate Agreements. | Z110: Medium | AA110: OCR
A111: UCHealth | B111: University of Colorado Health (UCHealth) | C111: University of Colorado Health | D111: UCHealth_BTS_Final Exp 2_2027.pdf | E111: Master/Rental Agreement | F111: BTS Rental | G111: Direct | H111: US Med-Equip, LLC (on behalf of subsidiaries) | I111: 2024-02-26 | J111: 2027-02-25 | K111: 46443 | L111: Contract text | N111: =IF(M111<>"",M111-Summary!$C$3,IF(K111="","",K111-Summary!$C$3)) -> 138 | O111: Active | P111: 3 years | Q111: No automatic renewal; renewals require prior written consent of both parties | R111: Either party without cause after 1st anniversary, 120 days notice; UCHealth may terminate for failed KPI performance or FM >30 days (5 days notice) | S111: Fixed daily rates per Attachment B (beds, WAVE/T-Wave surfaces, bariatric frames/ancillaries); rental fee includes delivery, maintenance, training | T111: Fixed for term; any increase must be mutually agreed in writing | U111: Not stated | V111: USME primary supplier; UCHealth commits 90% of bed/therapeutic surface/bariatric rental; if missed, USME may bill difference to GPO access pricing (failing hospital only) | W111: Net 45 from later of invoice date or receipt; 15 business days notice before credit hold | X111: SLA penalties: 1% if avg delivery >2 hrs + drive time, 1% pickup >24 hrs, uptime 1% penalty <98-99%, EPIC interface delay 2-3%, billing error credits 2-5%; replacement within 1 day; no-hire 12 months | Y111: System-wide BTS agreement for UCHealth facilities (Exhibit D). Annual KPI scorecard and quarterly business reviews; technology upgrade option after year 1 at FMV. | Z111: High | AA111: OCR
A112: UF Health Shands | B112: Shands Jacksonville Medical Center, Inc. (UF Health Jacksonville / UF Health North) | C112: UF Shands Gainesville-Jacksonville | D112: UF Shands Jackson_Exp_4_11_2022_Auto_2023_LR.pdf | E112: Master/Rental Agreement | F112: MME Rental, Respiratory | G112: Vizient CE2534 (Access Tier 1) | H112: US Med-Equip, Inc. | I112: 2019 (OCR: '12th day of Feb(?) 2019'; filename implies ~2019-04-12) | J112: Initial term ~2022 (filename 2022-04-11); auto-renews annually, current term likely to ~2027-04 | K112: 44662 | L112: Contract text | M112: 46488 | N112: =IF(M112<>"",M112-Summary!$C$3,IF(K112="","",K112-Summary!$C$3)) -> 183 | O112: Active | P112: 3 years | Q112: Auto-renews successive 1-yr terms unless either party cancels in writing 30 days prior to desired termination date | R112: Either party by written cancellation 30 days prior (renewal terms); for breach after 30-day cure; insolvency | S112: Monthly rental per Vizient CE2534 Access Tier 1 pricing (infusion, respiratory, NICU/L&D, monitoring, central supply); proposal: IPV-1C $17.68/day, $495/mo | T112: Not stated | U112: Not stated; equity option 25% of monthly rental paid (up to 12 months) toward purchase | V112: None stated | W112: Monthly rent due 1st of each month | X112: Customer responsible for safekeeping and loss/damage; abuse repairs at customer cost; GL $1M/$3M; mutual consent to assign; equipment pickup cannot affect patient care | Y112: USME Contract # R51618PP for UF Health Jacksonville MME rental. Effective date OCR is unclear and conflicts slightly with filename's 4/11 anniversary; 'Auto_2023_LR' filename tag suggests auto-renewal was being tracked. | Z112: Medium | AA112: OCR
A113: UF Health Shands | B113: Shands Jacksonville Medical Center, Inc. and Shands Teaching Hospital and Clinics, Inc. | C113: UF Shands Gainesville-Jacksonville | D113: UF Shands Amendment_Exp_02_29_28.pdf | E113: Amendment | F113: MME Rental, BTS Rental | G113: Vizient CE7782, CE9217, CE9205 | H113: USMED-EQUIP | I113: 2025-05-19 | J113: Not stated explicitly; co-terminous with Vizient CE7782 (filename 2028-02-29) | K113: 46812 | L113: Contract text | N113: =IF(M113<>"",M113-Summary!$C$3,IF(K113="","",K113-Summary!$C$3)) -> 507 | O113: Active | P113: 3 years | Q113: Auto-renews successive 1-yr terms | R113: Either party, 30 days written notice without cause after Initial Term | S113: Per Vizient CE7782/CE9217/CE9205 pricing | T113: Not stated | U113: Not stated | V113: Not stated | W113: Not stated | X113: Not stated | Y113: Amends 2019 agreement; adds six Gainesville/Jacksonville/Ocala facilities. Expiry ambiguous: 3 yrs from 5/19/2025 vs CE7782 end 9/30/2027. | Z113: Medium | AA113: Text
A114: UF Health Shands | B114: Shands Jacksonville Medical Center, Inc. and Shands Teaching Hospital and Clinics, Inc. (UF Health) | C114: UF Health | D114: UFH_USMED_Amendment_to_extend_and_add_locations_(1).pdf | E114: Amendment | F114: MME Rental | G114: Vizient CE7782 (also CE9217, CE9205) | H114: USMED-EQUIP (as written) | I114: 2025-05-19 (signed 2025-10-17; original Agreement 2019-10-01) | J114: ~2028-05-18 per 3-yr term, but co-terminous with Vizient CE7782 (2027-09-30) | K114: 46891 | L114: Contract text | N114: =IF(M114<>"",M114-Summary!$C$3,IF(K114="","",K114-Summary!$C$3)) -> 586 | O114: Active | P114: 3 years | Q114: Auto-renews successive 1-yr terms | R114: After Initial Term, either party without cause on 30 days written notice | S114: Per original Agreement and Vizient CE7782/CE9217/CE9205 pricing | T114: Not stated | U114: Not stated | V114: Not stated | W114: Not stated | X114: Not stated | Y114: Extends UF Health agreement and adds six facilities (Shands Gainesville, Cancer, Neuromedicine Heart & Vascular, Jacksonville, UF Health North, Ocala Neighborhood). The 3-year term and CE7782 co-terminus language conflict on end date. | Z114: Medium | AA114: Text
A115: UofL Health | B115: UofL Health | C115: U of L Health | D115: UofL Health_End User Agmt_Vizient_exp 08.06.2029.pdf | E115: GPO Letter of Participation/SIP | F115: BTS Rental | G115: Vizient CE9205 | H115: US Med-Equip, LLC | I115: 2026-08-07 (signature date) | J115: 2029-08-06 | K115: 47336 | L115: Contract text | N115: =IF(M115<>"",M115-Summary!$C$3,IF(K115="","",K115-Summary!$C$3)) -> 1031 | O115: Active | P115: 3 years | Q115: None stated | R115: Either party, 30 days written notice without cause after Initial Term | S115: Vizient CE9205 pricing; Primary Supplier daily rates per Attachment A (e.g., Freedom 1000 $55.00/day) | T115: Only as permitted under CE9205 | U115: Per Vizient CE9205 (not stated locally) | V115: Primary Vendor: 90% of annual rental spend on Attachment A equipment; customer excused if USME can't supply in time | W115: Net 30 via ACH; late fees capped at lesser of 1.5%/mo or legal max | X115: 2-hr response plus drive time; 24/7 support; replace defective units at no cost; CE9205 controls in conflict; no consequential damages; CE9205 indemnity and failure-to-supply remedies preserved | Y115: Local Vizient end-user agreement for bariatric/therapeutic beds and surfaces at 5 UofL hospitals (UofL, Jewish, Mary & Elizabeth, Peace, Shelbyville). Customer-favorable failure-to-supply carve-out. | Z115: High | AA115: OCR
A116: Valley Children's Healthcare | B116: Valley Children's Hospital dba Valley Children's Homecare | C116: Valley Childrens | D116: Valley Childrens Homecare_Exp_03_31_29_auto renew.pdf | E116: Master/Rental Agreement | F116: MME Rental, Respiratory | G116: Direct | H116: US Med-Equip, LLC | I116: 2024-04-01 | J116: 2029-03-31 | K116: 47208 | L116: Contract text | N116: =IF(M116<>"",M116-Summary!$C$3,IF(K116="","",K116-Summary!$C$3)) -> 903 | O116: Active | P116: 5 years | Q116: Auto-renews successive 1-yr terms | R116: Either party without cause, 30 days written notice | S116: Primary Vendor daily/monthly rates per Attachment A (ventilators, pumps, CPAP, etc.) | T116: Not stated | U116: None stated; 25% rental equity credit and 50% lost-equipment buyout credit value-adds | V116: Primary vendor: 90%+ of annual rental spend; customer may use others if USME cannot supply | W116: Net 30; repossession with 30 days written notice on non-payment | X116: Customer liable for abuse repairs (capped at reasonable equipment value); breaching party pays attorney fees; mutual indemnity; CGL $1M/$3M; mutual assignment consent; California law | Y116: Homecare MME rental agreement (Contract #KS12122023LR) for Valley Children's Homecare. | Z116: High | AA116: Text
A117: Valley Children's Healthcare | B117: Valley Children's Hospital | C117: Valley Childrens | D117: Valley Childrens Hospital_Exp_05_16_29_auto renew.pdf | E117: Master/Rental Agreement | F117: MME Rental, Respiratory | G117: Direct | H117: US Med-Equip, LLC | I117: 2024-05-17 | J117: 2029-05-16 | K117: 47254 | L117: Contract text | N117: =IF(M117<>"",M117-Summary!$C$3,IF(K117="","",K117-Summary!$C$3)) -> 949 | O117: Active | P117: 5 years | Q117: Auto-renews 1-yr terms | R117: Either party, 30 days written notice at any time | S117: Daily/monthly rates per Attachment A (Primary Vendor pricing) | T117: Not stated | U117: None stated | V117: Primary vendor: >=90% of annual MME rental spend; customer may use others if USME cannot supply | W117: Net 30; 30 days notice before equipment return on non-payment | X117: Customer bears loss/damage and abuse; repair cost capped at reasonable equipment value; damage proof by photo; mutual fee-shifting; CGL $1M/$3M; California law | Y117: Contract # KS05142024. 30-day termination for convenience undercuts 5-year term and 90% commitment. | Z117: High | AA117: OCR
A118: Vanderbilt Health (VHPC) | B118: Vanderbilt Health Purchasing Collaborative, LLC (VHPC) | C118: Vanderbilt Health PCo | D118: USME VHPC 3_Year Extension MME_BTS_Exp_10_31_2028.pdf | E118: Extension | F118: MME Rental, BTS Rental | G118: VHPC LC16609 | H118: US Med-Equip | I118: 2022-11-01 (amendment stated effective date; signed 2025-09-09) | J118: 2028-10-31 | K118: 47057 | L118: Contract text | N118: =IF(M118<>"",M118-Summary!$C$3,IF(K118="","",K118-Summary!$C$3)) -> 752 | O118: Active | P118: Underlying Supplier Agreement dated 2022-11-01; extended ~3 years to 2028-10-31 | Q118: Not stated | R118: Not stated (per underlying Supplier Agreement) | S118: Not stated (unchanged per Supplier Agreement) | T118: Not stated | U118: Not stated | V118: Not stated | W118: Not stated | X118: Not stated; all other Supplier Agreement terms unchanged | Y118: Supplier Amendment No. Two extends VHPC contract LC16609 term to 10/31/2028; only change is term. Text refers to itself inconsistently as 'First Amendment'; effective date shown as 11/1/2022 though executed 9/2025. | Z118: High | AA118: OCR
...

Sheet Action Watchlist
A1: Customer Group | B1: Counterparty (as written) | C1: Folder | D1: File Name | E1: Doc Type | F1: Service Lines | G1: GPO / Contract # | H1: USME Entity | I1: Effective Date | J1: Expiration (as stated) | K1: Expiration Date | L1: Exp. Date Source | M1: Projected Term End (auto-renew roll-fwd) | N1: Days to Expiry | O1: Status | P1: Initial Term | Q1: Renewal | R1: Termination | S1: Pricing Basis | T1: Price Increase / Escalator | U1: Rebate / Admin Fee | V1: Commitment / Exclusivity | W1: Payment Terms | X1: Liability / Risk Terms | Y1: Key Notes | Z1: Confidence | AA1: Text Source
A2: AdventHealth | B2: Adventist Health System Sunbelt Healthcare Corporation d/b/a AdventHealth | C2: AdventHealth | D2: PP-NS-1565 US Med-Equip A1.docx.pdf | E2: Amendment | F2: BTS Rental, Other | G2: Premier PP-NS-1565 | H2: US Med-Equip, LLC | I2: 2025-10-01 | J2: Not stated (follows underlying PP-NS-1565 supplement agreement) | L2: Unknown | N2: =IF(M2<>"",M2-Summary!$C$3,IF(K2="","",K2-Summary!$C$3)) | O2: Active | P2: Not stated | Q2: Not stated | R2: Not stated | S2: Adds one item to Schedule 1: Stryker Medical Extender Kit (item 59739) at $13.11/EA | T2: Not stated | U2: Not stated | V2: Not stated | W2: Not stated | X2: Not stated | Y2: Amendment 1 to AdventHealth GPO supplement agreement under Premier PP-NS-1565 adding a Stryker extender kit; signed 10/24/2025 by Doug Pytlinski (AdventHealth) and Tim Heck (USME). Term and other terms governed by the underlying supplement. | Z2: High | AA2: Text
A3: Department of Veterans Affairs | B3: Department of Veterans Affairs, Network Contract Office 17 (Amarillo VA Medical Center) | C3: Veteran Affairs Amarillo Medical Center | D3: Amendmen for VA Agreement_06.16.2026.pdf | E3: Amendment | F3: Not stated | G3: Direct (VA contract/order 36C25726R0023 per OCR; Mod P0002) | H3: US Med-Equip, LLC | I3: 2026-06-16 (contractor signature date; effective date block references 16c) | J3: Not stated | L3: Unknown | N3: =IF(M3<>"",M3-Summary!$C$3,IF(K3="","",K3-Summary!$C$3)) | O3: Active | P3: Not stated | Q3: Not stated | R3: Noncompliance with FAR 52.222-90 may result in cancellation, termination or suspension | S3: Not stated | T3: Not stated | U3: Not stated | V3: Not stated | W3: Not stated | X3: Adds FAR 52.222-90 (no racially discriminatory DEI activities); compliance material to payment under False Claims Act; flow-down to subcontractors required | Y3: SF-30 Modification P0002 solely incorporating FAR 52.222-90 per EO 14398; no other changes. Signed by Clay Rose 6/16/2026; underlying VA contract terms not included. | Z3: Medium | AA3: OCR
A4: Mayo Clinic | B4: Mayo Foundation for Medical Education and Research (on behalf of affiliates) | C4: Mayo LaCrosse | D4: Mayo La Crosse Services Amendment Exp_07_28.pdf | E4: Amendment | F4: Asset Mgmt/On-site | G4: Direct | H4: US Med-Equip, LLC | I4: 2025-07 (day blank; amendment to agreement dated 2023-06-06) | J4: Not stated (filename: 2028-07) | L4: Unknown | N4: =IF(M4<>"",M4-Summary!$C$3,IF(K4="","",K4-Summary!$C$3)) | O4: Active | P4: Not stated | Q4: Not stated | R4: Not stated (per Existing Agreement) | S4: Monthly service fee increased from $31,674 to $40,031 | T4: Not stated | U4: Not stated | V4: Not stated | W4: Not stated | X4: Not stated | Y4: Amendment No. 1 to Non-Medical Services Agreement expanding on-site coverage (M-F 7am-11pm, Sat-Sun 7am-7pm CT) and adding 1 FTE + 1 PTE. Expiration not in text; filename indicates July 2028. | Z4: Medium | AA4: Text
A5: Partners Cooperative | B5: Partners Cooperative | C5: Partners Coop MME - CE71/RFP | D5: Partners CE71 US MED-EQUIP (2021) RENTAL Exhibits.pdf | E5: Pricing Exhibit | F5: MME Rental, Respiratory, Asset Mgmt/On-site | G5: Partners CE71 | H5: US Med-Equip, Inc. | I5: Not stated (RFP submitted 2021-11-02) | J5: Not stated | L5: Unknown | N5: =IF(M5<>"",M5-Summary!$C$3,IF(K5="","",K5-Summary!$C$3)) | O5: Unclear - verify | P5: Not stated | Q5: Not stated | R5: Not stated | S5: Dual source: Access at Vizient Tier 2 pricing (no spend requirement); Primary Provider at Vizient Tier 3 pricing (Exhibit B price matrix) | T5: Not stated | U5: Access tier 0.5% rebate quarterly; Primary Provider 1% quarterly; 1% bonus on total annual rental if aggregate spend > $7M | V5: Primary Provider: 90%+ annual rental spend; members in service area convert within 60 days; non-compliance after 60-day notice moves member to Tier 2 | W5: Net 30 (Primary Provider requirement) | X5: Service commitments: 2-hr + drive time delivery, 24-hr pickup, 100% high-risk PM compliance, 90% non-high-risk; 25% rental equity and 50% lost-equipment buyout credit | Y5: USME RFP response and exhibits for Partners MME rental contract CE71; not an executed agreement. Bi-annual business reviews and utilization reports required for Primary Provider tier. Rebate '1/2%' partly garbled in text. | Z5: Medium | AA5: Text
A6: The Resource Group (Ascension) | B6: Ascension Health Resource and Supply Management Group, LLC (The Resource Group); TriMedx Holdings for Medical University Hospital Authority | C6: GPO/The Resource Group | D6: USMED-TriMed_MME_resource_Group.pdf | E6: Amendment | F6: MME Rental | G6: The Resource Group USMED-0170211 | H6: US Med-Equip LLC | I6: 2023-07-15 (master agreement 2023-02-15) | J6: Not stated | L6: Unknown | N6: =IF(M6<>"",M6-Summary!$C$3,IF(K6="","",K6-Summary!$C$3)) | O6: Unclear - verify | P6: Not stated | Q6: Not stated | R6: Not stated | S6: Products per Appendix A-2 | T6: Not stated | U6: Not stated | V6: Not stated | W6: Not stated | X6: Not stated | Y6: Amendment 001 gives TriMedx access to purchase Appendix A-2 products on behalf of Medical University Hospital Authority (MUSC) under the Resource Group master agreement. | Z6: Medium | AA6: OCR
A7: TPC | B7: TTPC, LLC (TPC) | C7: TPC Rental | D7: TPC_2nd_Amendment-_Product_Add.pdf | E7: Amendment | F7: BTS Rental, Restraints/Posey | G7: Direct | H7: US Med Equip, Inc. | I7: 2025-03-15 | J7: Not stated (per base Services Agreement dated 2014-09-01) | K7: 41883 | L7: Contract text | N7: =IF(M7<>"",M7-Summary!$C$3,IF(K7="","",K7-Summary!$C$3)) -> -4422 | O7: Active | P7: Not stated | Q7: Not stated | R7: Not stated | S7: Adds Exhibit D BTS products: Tier 1/Access vs Tier 2/80% Committed daily pricing (beds, LAL mattresses, bariatric chairs/wheelchairs, Posey items) | T7: Not stated | U7: Not stated | V7: Tier 2 pricing requires 80% commitment | W7: Not stated | X7: Not stated | Y7: Second amendment to TPC Standard Purchased Services Agreement (2014) adding BTS products and pricing; signed 3/28/2025 by Mark Phalen (TPC CFO) and Tim Heck. Base term not in this document; confirm underlying agreement is still in force. | Z7: Medium | AA7: Text
A8: Encompass Health | B8: Encompass Health Rehabilitation Hospital of Northwest Tucson, L.P. | C8: Encompass Tucson | D8: Encompass Tucson_MME_BTS_Exp_3_31_2024_LR.pdf | E8: Master/Rental Agreement | F8: MME Rental, BTS Rental, Respiratory, Restraints/Posey | G8: Direct | H8: Freedom Medical, Inc. | I8: 2019-06-14 | J8: 2024-03-31 (now rolling 30-day renewals) | K8: 45382 | L8: Contract text | N8: =IF(M8<>"",M8-Summary!$C$3,IF(K8="","",K8-Summary!$C$3)) -> -923 | O8: Active | P8: Through 2024-03-31 (~4.8 years) | Q8: Auto-renews 30-day periods unless 30 days notice | R8: Either party on 30 days written notice after initial term; customer may terminate immediately for quality issues, rep breach, or hospital sale/closure | S8: Fixed daily/monthly rates per Exhibit A; beds at Tier 5 pricing schedule | T8: Not stated | U8: Not stated | V8: Not stated | W8: Net 30; invoices due by 10th of following month; invoices received 1+ year after service deemed paid | X8: Customer bears loss/damage at replacement cost; mutual negligence indemnity; no assignment without consent (FMI-to-USME assignment risk); insurance CGL $1M/$2M, auto $1M, umbrella $5M | Y8: Legacy Freedom Medical contract for single Tucson rehab hospital; initial term ended 3/31/2024 and it has been running month-to-month. Filename '_LR' consistent; agreement names FMI, not USME. | Z8: Medium | AA8: Text
A9: VGM Group | B9: VGM Group, Inc. | C9: VGM Group | D9: VGM_MME_BioMed_Exp_4_30_2024_ext 2027.pdf | E9: GPO Agreement | F9: MME Rental, Biomed/Repair Service | G9: VGM Group GPO Product Supply Agreement (Direct GPO) | H9: US Med-Equip, LLC | I9: 2021-05-04 (signed ~2021-04-10) | J9: 2024-04-30 initial; auto-renewed to 2027-04-30 | K9: 45412 | L9: Contract text | N9: =IF(M9<>"",M9-Summary!$C$3,IF(K9="","",K9-Summary!$C$3)) -> -893 | O9: Active | P9: 3 years | Q9: Auto-renews for 3-yr terms unless 120 days notice before renewal | R9: VGM may cancel without cause on 120 days notice; mutual by agreement; $7,500 minimum fee shortfall allows cancel on 30 days notice | S9: Attachment A: VGM Access tier (no commitment) and Preferred Partnership 95% LOC daily/monthly rates; 10% off published biomed PM rates | T9: Up to supplier with 60 days notice to VGM; no increase in first 12 months | U9: 3% admin fee on monthly Net Sales; $7,500 one-time first-year fee credited against fees; 10% penalty and up to 18% interest on late fees | V9: Preferred tier requires member 95% MME rental commitment, DSO <=30 days, bi-annual reviews and leakage reports; otherwise moves to Access pricing | W9: Supplier standard terms (members); admin fees within 30 days of month end | X9: Mutual indemnity incl. data breach; audit right (supplier pays if underpaid >10%); asset sale requires buyout of PV of remaining fee stream unless successor bound | Y9: Post-acute/HME-oriented GPO. Filename 'ext 2027' consistent with automatic 3-yr renewal through 2027-04-30. | Z9: Medium | AA9: OCR
A10: Ardent Health | B10: AHS Management Company, Inc. (Ardent Health Services) | C10: Ardent | D10: Ardent_HPG_MME_SIP_Exp 9_30_2024.pdf | E10: GPO Letter of Participation/SIP | F10: MME Rental | G10: HPG-7093 | H10: US Med-Equip, LLC | I10: 2022-06-30 (signed; HPG-7093 effective 2021-08-01) | J10: Not stated (tied to HPG-7093; filename indicates 2024-09-30) | K10: 45565 | L10: Contract text | N10: =IF(M10<>"",M10-Summary!$C$3,IF(K10="","",K10-Summary!$C$3)) -> -740 | O10: Likely Active - verify | P10: Not stated | Q10: Not stated | R10: Group may exit SIP on 30 days written notice; HealthTrust may terminate on 30 days; USME may terminate for missed commitment after 60-day cure | S10: Committed Price per HPG-7093 Exhibit A (SIP tier) | T10: Not stated | U10: Not stated | V10: Group commits to 80% of requirements for products; failure lets USME revert to standard HPG agreement pricing | W10: Not stated | X10: Not stated | Y10: HPG Standardization Incentive Program acknowledgement covering Ardent facilities (Lovelace NM, UT Health East Texas, St. Francis Topeka, Seton Harker Heights, Hackensack UMC Mountainside). Expiration only from filename (9/30/2024); status depends on HPG-7093 extension. [Review note: tied to HPG-7093, which was extended to 7/31/2029; confirm SIP/LOP continues under the extension.] | Z10: Medium | AA10: Text
A11: Community Health Systems (CHS) | B11: CHSPSC, LLC (Community Health Systems) | C11: CHS | D11: CHS_MME_HPG_SIP_Exp_9_30_2024.pdf | E11: GPO Letter of Participation/SIP | F11: MME Rental | G11: HPG-7093 | H11: US Med-Equip, LLC | I11: 2021-08-01 (HPG agreement); SIP signed 2022-01-17 | J11: Not stated (filename: 2024-09-30) | K11: 45565 | L11: Contract text | N11: =IF(M11<>"",M11-Summary!$C$3,IF(K11="","",K11-Summary!$C$3)) -> -740 | O11: Likely Active - verify | P11: Not stated (co-terminous with HPG-7093) | Q11: Not stated | R11: Group may terminate SIP on 30 days notice; HealthTrust may terminate on 30 days notice; vendor may terminate after 60-day cure if commitment missed | S11: SIP Committed Price per Exhibit A of HPG-7093 | T11: Not stated | U11: Not stated | V11: Group commits to buy at least 80% of requirements for Products from USME; vendor sole remedy for shortfall is SIP termination and reversion to agreement pricing | W11: Not stated | X11: Not stated (governed by HPG-7093) | Y11: Large CHS facility schedule (~70+ hospitals across TN, FL, MS, OK, AZ, IN, PA etc.). Expiration (2024-09-30) only in filename; SIP has no own term and follows HPG-7093, which other files show running to 2026 - verify status. [Review note: tied to HPG-7093, which was extended to 7/31/2029; confirm SIP/LOP continues under the extension.] | Z11: Medium | AA11: Text
A12: HealthTrust (HPG) | B12: Community Hospital Corporation | C12: Community Hospital Corporation (CHC) | D12: CHC_HPG_MME_SIP_Exp_9_30_2024.pdf | E12: GPO Letter of Participation/SIP | F12: MME Rental | G12: HPG-7093 | H12: US Med-Equip, LLC | I12: 2022-05-03 (signed; HPG-7093 effective 2021-08-01) | J12: Not stated (tied to HPG-7093) | K12: 45565 | L12: File name | N12: =IF(M12<>"",M12-Summary!$C$3,IF(K12="","",K12-Summary!$C$3)) -> -740 | O12: Likely Active - verify | P12: Not stated | Q12: Not stated | R12: Group may exit SIP on 30 days notice; HealthTrust 30 days; vendor only for non-compliance after 60-day cure | S12: SIP Committed Price per HPG-7093 Exhibit A | T12: Not stated | U12: Not stated | V12: 80% of requirements for Products (SIP commitment); vendor's sole remedy is termination of SIP and reverting to standard HPG prices | W12: Not stated | X12: Not stated | Y12: CHC SIP covering a long roster of rural/community hospitals across many states (GPOID H018265). Filename shows expiration 9/30/2024 but the form states no end date; HPG-7093 since extended to 7/31/2029. [Review note: tied to HPG-7093, which was extended to 7/31/2029; confirm SIP/LOP continues under the extension.] | Z12: Medium | AA12: Text
A13: Partners Cooperative | B13: PARTNERS Cooperative, Inc. | C13: Partners Coop MME - CE71/RFP | D13: Partners CE71 US MED-EQUIP (2021) RENTAL Terms-Conditions Effective 01-01-22.pdf | E13: GPO Agreement | F13: MME Rental | G13: Partners Cooperative; Vizient CE7073 | H13: US Med-Equip | I13: 2022-01-01 | J13: 2024-12-31 initial; 2026-12-31 if both extension options exercised | K13: 45657 | L13: Contract text | N13: =IF(M13<>"",M13-Summary!$C$3,IF(K13="","",K13-Summary!$C$3)) -> -648 | O13: Unclear - verify | P13: 3 years | Q13: Two 1-yr extensions at PARTNERS' option | R13: Either party without cause, 30 days written notice | S13: Vizient Tier 2 for Partners Members; Vizient Tier 3 for Members choosing USME as Primary (90% LOC); monthly rate auto-applied at 30/31 days | T13: No increase for 3 years from 2022-01-01 | U13: Quarterly rebate to PARTNERS 0.5% of sales (1% for Primary/90% LOC members); +1% annual bonus if aggregate spend >$7M; Vizient marketing/ISP fees also payable | V13: No guaranteed volume; supersedes prior agreements; open to all current/future members | W13: Net 30 to Members | X13: 2-hour delivery guarantee plus drive time; availability guarantee or substitute (else member may rent elsewhere); no charge for add-ons/upgrades; free PM; GL $1M/$3M; assignment needs consent | Y13: RFP terms signed 11/16/2021. Filename references CE71; text cites Vizient CE7073. Status depends on whether extension options were exercised. | Z13: Medium | AA13: OCR
A14: Partners Cooperative | B14: Partners Cooperative, Inc. | C14: Partners Coop MME - CE72/RFP | D14: Partners CE72 US MED-EQUIP (2021) RENTAL 90% Terms-Conditions Effective 01-01-22.pdf | E14: GPO Agreement | F14: MME Rental | G14: Partners CE72 (Vizient CE7073) | H14: US Med-Equip LLC | I14: 2022-01-01 | J14: 2024-12-31 initial; 2026-12-31 if both 1-yr options exercised | K14: 45657 | L14: Contract text | N14: =IF(M14<>"",M14-Summary!$C$3,IF(K14="","",K14-Summary!$C$3)) -> -648 | O14: Unclear - verify | P14: 3 years | Q14: Two 1-yr extensions at Partners' option | R14: Either party without cause on 30 days written notice | S14: Proposal pricing on full Rental Equipment category; Vizient Tier 2 for members, Tier 3 for 90% primary members; auto-convert to monthly rate at 30/31 days | T14: No price increase for 3 years from 2022-01-01 | U14: 0.5% quarterly rebate to Partners on member sales (1% for 90% primary members); +1% annual bonus if aggregate spend >$7M; Vizient fees also payable | V14: No guaranteed volumes; 90% LOC for primary-provider tier; supersedes prior agreements | W14: Net 30 | X14: 2-hr delivery + drive time guarantee; availability guarantee w/ substitutes; free PM; mutual indemnity; GL $1M/$3M; quarterly sales reporting | Y14: Partners RFP terms accepted 11/16/2021. Status depends on option exercise; St. Elizabeth SOW references a newer Partners MSA dated 9/1/2024, which may supersede. | Z14: Medium | AA14: OCR
A15: Kaiser Permanente | B15: Kaiser Vacaville Hospital Foundation | C15: Kaiser Vacaville | D15: Kaiser Vacaville Hospital_Posey_Exp_03_4_25_auto_renew.pdf | E15: Master/Rental Agreement | F15: Restraints/Posey | G15: Direct | H15: US Med-Equip, LLC | I15: 2024-09-05 | J15: 2025-03-04 initial; auto-renewing 6-month terms (current term to 2027-03-04) | K15: 45720 | L15: Contract text | N15: =IF(M15<>"",M15-Summary!$C$3,IF(K15="","",K15-Summary!$C$3)) -> -585 | O15: Active | P15: 6 months | Q15: Auto-renews successive 6-month terms unless cancelled 30 days before term end | R15: Non-renewal by either party 30 days before term end; no convenience termination; early equipment return requires paying remainder of rental term | S15: Posey Enclosure Bed billed $45/unit monthly; 1 unit | T15: Not stated | U15: Not stated | V15: Not stated | W15: Due 30 days from monthly invoice; collection costs | X15: Customer pays full new replacement cost for lost/damaged equipment; customer-only indemnity of USME; Texas law, Harris County venue | Y15: Single Posey enclosure bed rental stored on-site. Customer signature block blank in text; agreement date lacks year in body (USME signed 9/5/2024). | Z15: Medium | AA15: Text
A16: Children's Minnesota | B16: Children's Health Care d/b/a Children's Minnesota | C16: Children's Minnesota | D16: Children's Minnesota_Exp_04_2025_LR.pdf | E16: Master/Rental Agreement | F16: MME Rental, BTS Rental, Respiratory | G16: Direct | H16: Freedom Medical, Inc. | I16: 2022-04-15 | J16: 2025-04-14 (initial term); up to 2027-04-14 if both renewals ran | K16: 45761 | L16: Contract text | N16: =IF(M16<>"",M16-Summary!$C$3,IF(K16="","",K16-Summary!$C$3)) -> -544 | O16: Unclear - verify | P16: 3 years | Q16: Two consecutive 12-month renewals unless either party gives 60 days notice of non-renewal | R16: Customer may terminate without cause after first year on 90 days notice; either party for cause with 30-day cure | S16: Daily/monthly rates per Exhibit A Rental Pricing Schedule (MME, neonatal, specialty beds/surfaces) | T16: Pricing firm for 36 months; no escalator stated | U16: Not stated | V16: Right of first option for additional rentals of currently rented equipment types; customer free to rent elsewhere for other items or if FMI cannot supply | W16: Net 30 from receipt; 1.5%/month on invoices 60+ days past due; no offset; disputes within 90 days; FMI may suspend for non-payment | X16: Customer responsible for loss/damage, billed replacement cost; FMI liability limited to repair/replacement except negligence; mutual indemnity; Minnesota law/venue | Y16: Legacy Freedom Medical agreement; 2-hour plus drive time delivery, 24-hour pickup, quarterly/annual business reviews. Initial term ended 4/2025 (matches filename); evergreen renewal language may have carried it to 4/14/2026 or 4/14/2027 absent non-renewal notice. | Z16: High | AA16: Text
A17: Englewood Post Acute | B17: Cherry Hills Healthcare, Inc. dba Englewood Post Acute and Rehabilitation | C17: Englewood | D17: Englewood Post Acute_Exp_04_18_2025_auto_2027.pdf | E17: Master/Rental Agreement | F17: BTS Rental | G17: Direct | H17: Freedom Medical, Inc. | I17: 2022-04-19 | J17: 2025-04-18 initial; renewals to 2027-04-18 | K17: 45765 | L17: Contract text | N17: =IF(M17<>"",M17-Summary!$C$3,IF(K17="","",K17-Summary!$C$3)) -> -540 | O17: Active | P17: 3 years | Q17: Two consecutive 12-month renewals unless either party gives 60 days notice of non-renewal | R17: Either party without cause, 30 days written notice | S17: Daily rental rates per Exhibit A (Freedom Comfort/Advanced Wave mattresses, $8.25-$55.00/day) | T17: Firm for 36 months; thereafter not stated | U17: None | V17: Customer to use FMI as primary medical equipment rental provider (no % stated) | W17: Net 30 from invoice; 1.5%/month on invoices 60+ days past due; no offset; billing disputes within 90 days | X17: Customer liable for loss/damage from receipt to return at current market value; FMI liability limited to repair/replace/refund, no consequential damages; mutual indemnity; arbitration | Y17: Legacy Freedom Medical therapeutic surface rental agreement for a post-acute facility. Assumed in second renewal period through 4/18/2027 absent non-renewal notice. | Z17: High | AA17: Text
A18: iMedical / Bon Secours Mercy Health | B18: iMedical (managing rentals for Bon Secours Mercy Health VA and OH locations) | C18: iMedical | D18: iMedical_BTS_Exp_4_30_2025_ext 2027.pdf | E18: Master/Rental Agreement | F18: BTS Rental | G18: Direct | H18: Freedom Medical, Inc. | I18: 2021-09-01 | J18: 2025-04-30 initial; two 12-month renewals run to 2027-04-30 | K18: 45777 | L18: Contract text | N18: =IF(M18<>"",M18-Summary!$C$3,IF(K18="","",K18-Summary!$C$3)) -> -528 | O18: Active | P18: Through 2025-04-30 (or earlier end of iMedical-BSM agreement) | Q18: Renews for two consecutive 12-month periods unless either party gives 60 days non-renewal notice | R18: For cause only (30-day cure); early cancellation without cause triggers default invoicing (difference to standard pricing) | S18: Rental rates per Exhibit B Rental Pricing Schedule (exhibit blank in scan) | T18: Firm through 2025-04-30 (term of iMedical's BSM agreement); renewal pricing not stated | U18: Not stated | V18: FMI exclusive rental supplier of therapeutic support surfaces and bariatric bed frames for BSM VA/OH locations; breach triggers repricing to standard rates | W18: Net 30; 1.5%/month on invoices 60+ days past due; may suspend on 5 days notice; no offset | X18: Customer liable for loss/damage from receipt to return at replacement cost; FMI liability limited to repair/replace/refund, no consequential damages; mutual indemnity; PA law | Y18: Sub-rental arrangement via iMedical for Bon Secours Mercy Health hospitals; includes QBRs, annual utilization reports, in-servicing. Filename 'ext 2027' consistent with two 12-month renewals; Exhibits A/B blank in scan. | Z18: Medium | AA18: OCR
... A41: University Health (Bexar County) | B41: University Health (San Antonio, TX) | C41: UniversityHealth | D41: University Health_SA_MME_Exp_09_30_2026.pdf | E41: Extension | F41: MME Rental | G41: Premier AD-NS-1283 (to 2025-11-30) / AD-NS-2139 (2025-12-01 to 2028-11-30) | H41: US Med-Equip, LLC | I41: 2025-10-01 (Mod #2 signed 2025-12-23) | J41: 2026-09-30 | K41: 46295 | L41: Contract text | N41: =IF(M41<>"",M41-Summary!$C$3,IF(K41="","",K41-Summary!$C$3)) -> -10 | O41: Unclear - verify | P41: Base contract 10/1/2023-9/30/2025 (orig. term not stated) | Q41: Two 1-yr renewal options remaining | R41: Not stated | S41: Per Premier GPO contracts AD-NS-1283 / AD-NS-2139 | T41: Firm and fixed through term including renewal years | U41: Not stated | V41: No guaranteed minimum; estimate-based; total contract value $341,926.99 | W41: Not stated | X41: Not stated | Y41: Modification #2 to Contract 22309227-IG (peak use rental) exercising 'third' 1-yr renewal; blanket POs for logistics, ACU, NICU, OR, respiratory. Term ended 9/30/2026; confirm whether next renewal executed. | Z41: Medium | AA41: OCR
A42: CHOMP (Montage Health) | B42: Community Hospital of the Monterey Peninsula | C42: Community Hospital of the Monterey Peninsula (CHOMP) | D42: CHOMP_BTS_Exp_1_31_2026.docx | E42: Master/Rental Agreement | F42: BTS Rental, MME Rental | G42: Direct (Vizient Tier 4 pricing referenced) | H42: US Med-Equip, LLC | I42: 2022-10-11 | J42: 2025-10-11 initial; auto-renewed to 2026-10-11 | K42: 45941 | L42: Contract text | M42: 46306 | N42: =IF(M42<>"",M42-Summary!$C$3,IF(K42="","",K42-Summary!$C$3)) -> 1 | O42: Active | P42: 3 years | Q42: Auto-renews successive 1-yr terms | R42: Either party without cause, 30 days written notice | S42: Vizient Tier 4 daily rates per Attachment A (bariatric beds, low beds, Posey/Freedom Safe beds, transfer devices); consignment, no charge until used | T42: Not stated | U42: None stated; value-adds include 25% rental equity credit toward buyout and 50% lost-equipment buyout credit | V42: Primary vendor: 90%+ of annual rental spend for Attachment B facilities | W42: Net 30; USME may repossess on non-payment; customer pays collection/attorney fees | X42: Customer liable for loss/damage and abuse repairs; full new-unit cost if not returned in good condition; mutual indemnity; USME CGL $1M/$3M; Texas law, Harris County venue | Y42: Consigned peak-use BTS/bariatric equipment at CHOMP. Filename says Exp 1/31/2026 but text gives 3-yr term from 10/11/2022 with auto-renewal; primary vendor clause text says MME although equipment is BTS. CHOMP BTS amendment exp 9/30/2027 also on file. | Z42: Medium | AA42: Text
A43: Natividad Medical Center (County of Monterey) | B43: County of Monterey on behalf of Natividad Medical Center | C43: Natividad Medical Ctr | D43: Natividad Medical Center_Exp_10_17_2026_Auto Renewal.pdf | E43: Master/Rental Agreement | F43: MME Rental, BTS Rental | G43: Direct | H43: US Med-Equip, LLC | I43: 2023-10-18 | J43: 2026-10-17 initial; auto-renews | K43: 46312 | L43: Contract text | N43: =IF(M43<>"",M43-Summary!$C$3,IF(K43="","",K43-Summary!$C$3)) -> 7 | O43: Active | P43: 3 years | Q43: Auto-renews successive 1-yr terms | R43: After Initial Term, either party without cause on 30 days written notice | S43: Monthly rates per Attachment A Primary Vendor pricing | T43: Fixed until 2nd anniversary; then max once per contract year by greater of 5% or Medical Care CPI-U, 30 days notice | U43: Not stated | V43: Primary vendor 80%+ of annual rental spend (MME and BTS); commitment void unless USME fills 100% of requests | W43: Net 30 from receipt by Monterey County Auditor-Controller; credit hold/market rates on nonpayment | X43: Customer liable for loss/damage and unreported damage; broad USME indemnity of County; CGL $1M/$3M, auto $500K, EL $1M; County additional insured; CA law, Monterey venue | Y43: Initial term ends 10/17/2026 and rolls to 1-yr renewal; price increase right available now. Fill-rate carve-out weakens the 80% commitment. | Z43: High | AA43: OCR
A44: Cook Children's | B44: Cook Children's Medical Center | C44: Cook Children's | D44: Cook Children MSA BTS Repair_Exp_10_19_23_Auto_2026.pdf | E44: Master/Rental Agreement | F44: BTS Rental, Biomed/Repair Service | G44: Direct | H44: US Med-Equip, LLC | I44: 2023-10-19 | J44: 2026-10-19 (or later expiration of any open SOW) | K44: 46314 | L44: Contract text | N44: =IF(M44<>"",M44-Summary!$C$3,IF(K44="","",K44-Summary!$C$3)) -> 9 | O44: Active | P44: 3 years (or until all SOWs end, if later) | Q44: No auto-renewal stated; MSA survives until all SOWs expire | R44: No convenience termination; breach with 60-day cure, insolvency, force majeure >30 days (10 days notice), mutual agreement; USME may terminate on customer change of control | S44: Per SOW Program Budget (no SOW attached) | T44: Not stated (Program Budget changes require mutual written consent) | U44: Not stated | V44: Expressly non-exclusive | W44: Net 30 from invoice receipt (undisputed); late interest lesser of 1.5%/mo or TX max, compounded; collection costs | X44: USME liability capped at 12 months of fees for applicable SOW; no consequential damages; USME indemnifies for equipment damage in its custody; 12-mo non-solicit; USME CGL $1M/$3M | Y44: Framework MSA for BTS rental and repair services; commercial terms live in SOWs not included in file. Filename 'Exp_10_19_23' is effective date; text gives 3-year term to 10/19/2026, expiring in 9 days absent active SOW. | Z44: High | AA44: OCR
A45: Tampa General Hospital | B45: Tampa General Hospital | C45: Tampa General | D45: Tampa General_Exp_10_28_2022_Auto_Renew.pdf | E45: Master/Rental Agreement | F45: MME Rental, Asset Mgmt/On-site | G45: Vizient (Tier 3 pricing referenced) | H45: US Med-Equip, LLC | I45: 2019-10-29 (per filename; day/month illegible in text) | J45: 2022-10-28 initial; auto-renewing | K45: 44862 | L45: Contract text | M45: 46323 | N45: =IF(M45<>"",M45-Summary!$C$3,IF(K45="","",K45-Summary!$C$3)) -> 18 | O45: Active | P45: 3 years | Q45: Auto-renews successive 1-yr terms unless cancelled 30 days before term end | R45: Non-renewal by either party with 30 days notice; termination for breach (60-day cure) | S45: Vizient Tier 3 rates (90% LOC) per Attachment A; other Vizient price-file items at Tier 3; 25% equity discount up to 12 months | T45: Not stated | U45: Not stated | V45: Tier 3 pricing tied to 90% level of commitment | W45: Due on 1st of each month | X45: Customer responsible for loss/damage; 50% of rent paid applied to lost-equipment buyout with quarterly RFID scans; full new-unit cost if not returned; CGL $1M/$3M; Texas law, Harris County | Y45: Contract #109414. Includes mySmarts portal, RFID tracking and PM notification value-adds. Auto-renews annually, so likely still in effect. | Z45: Medium | AA45: OCR
A46: Veterans Affairs (VA) | B46: Department of Veterans Affairs, NCO 17 (Amarillo VA Medical Center) | C46: Veteran Affairs Amarillo Medical Center | D46: VA Amarillo Medical Center Exp_10_30_2030.pdf | E46: Service Agreement/SOW | F46: BTS Rental | G46: Direct (VA contract 36C25726P0023) | H46: US Med-Equip, LLC | I46: 2025-10-31 | J46: 2026-10-30 base; 2030-10-30 if all 4 option years exercised | K46: 46325 | L46: Contract text | N46: =IF(M46<>"",M46-Summary!$C$3,IF(K46="","",K46-Summary!$C$3)) -> 20 | O46: Active | P46: 1-year base + four 1-yr options | Q46: Government option years (FAR 52.217-9) plus up to 6-month extension (52.217-8) | R46: Government termination for convenience (FAR 52.212-4(l)); customer-only | S46: Daily rates fixed all years: LAL mattress $17.10, IME Elite low bed $27.55, bariatric low bed $55.00, bariatric LAL mattress $24.38 (400 days each) | T46: Fixed for base and option years | U46: Not stated | V46: None; base award $49,612 (total $248,060 incl. options) | W46: Prompt Payment Act; invoices via Tungsten e-invoicing monthly | X46: Deliver within 4 hrs; replace non-working equipment within 4 hrs; tech on site within 4 hrs; pickup within 24 hrs; govt insurance minimums per FAR 52.228-5 | Y46: Bed/surface rental for Amarillo VA. Base year ends 2026-10-30, three weeks out - confirm VA exercises option year 1. | Z46: High | AA46: Text
A47: St. Jude | B47: St. Jude Children's Research Hospital | C47: St. Jude | D47: St Jude Childrens_Exp_10_31_2022_Auto Renew.pdf | E47: Master/Rental Agreement | F47: MME Rental | G47: Vizient CE7073 | H47: US Med-Equip, LLC | I47: 2019-11-01 | J47: 2026-10-31 (current auto-renewal term) | K47: 46326 | L47: Contract text | N47: =IF(M47<>"",M47-Summary!$C$3,IF(K47="","",K47-Summary!$C$3)) -> 21 | O47: Active | P47: 3 years | Q47: Auto-renews successive 1-yr terms unless cancelled 30 days before term end | R47: Either party, 30 days written notice | S47: Monthly/daily rates per Vizient CE7073 Exhibit A; 25% equity discount toward buyout up to 12 months | T47: Not stated (per Vizient CE7073) | U47: Not stated (per Vizient) | V47: Not stated | W47: Due on 1st day of each month | X47: Customer liable for loss/damage and abuse plus enforcement costs; full new-unit cost if not surrendered; USME CGL $1M/$3M; 30-day cure | Y47: Contract 093019STJ_MS. Current renewal term ends 10/31/2026; non-renewal notice deadline about 10/1/2026 has passed, so it will likely roll to 10/31/2027. | Z47: High | AA47: OCR
A48: Encompass Health | B48: Encompass Health Corporation | C48: Encompass Health | D48: Encompass_Exp_11_12_2023_auto_renewal.pdf | E48: Master/Rental Agreement | F48: MME Rental, Respiratory | G48: Vizient CE7073 | H48: US Med-Equip, LLC | I48: 2020-11-12 | J48: 2023-11-12 initial; auto-renews 1-yr (current term to ~2026-11-12) | K48: 45242 | L48: Contract text | M48: 46338 | N48: =IF(M48<>"",M48-Summary!$C$3,IF(K48="","",K48-Summary!$C$3)) -> 33 | O48: Active | P48: 3 years | Q48: Auto-renews 1-yr terms unless cancelled 30 days before term end | R48: Either party, 60 days written notice without cause | S48: Monthly rates per Attachment A at Vizient Tier 3 Preferred Partnership (90% LOC) pricing | T48: Fixed for term (reductions only) | U48: Vizient admin fees apply; 25% equity discount on rental dollars (up to 12 months) toward purchase | V48: Dual-source MME vendor designation; credit standing required, DSO <= 60 days | W48: Due 1st of each month; repossession right on non-payment | X48: Customer bears loss/damage and abuse repairs; USME indemnifies for customer use of equipment; CGL $1M/$3M; assignment requires consent; Delaware law | Y48: Contract # EH 09152020JD. Vizient terms apply where more favorable to customer. Next renewal ~2026-11-12; cancellation window closes ~mid-Oct 2026. | Z48: Medium | AA48: OCR
A49: Nobis Rehabilitation Partners | B49: Nobis Rehabilitation Partners (as Manager for Customers in Attachment B) | C49: Nobis Rehab | D49: Nobis_Rehab_Agreement_MME_BTS_Exp_11_30_26_Auto Renewal.pdf | E49: Master/Rental Agreement | F49: MME Rental, BTS Rental | G49: Vizient CE7073; Vizient CE3363 | H49: US Med-Equip, LLC | I49: 2023-12-01 | J49: 2026-11-30 (auto-renews 1-yr) | K49: 46356 | L49: Contract text | N49: =IF(M49<>"",M49-Summary!$C$3,IF(K49="","",K49-Summary!$C$3)) -> 51 | O49: Active | P49: 3 years | Q49: Auto-renews successive 1-yr periods | R49: Either party without cause on 30 days written notice; breach w/60-day cure | S49: Vizient Tier 3 (90% committed) rates on CE7073 and CE3363 (Attachment A daily rates) | T49: Not stated | U49: Not stated | V49: Primary vendor: 90%+ of annual rental spend on CE7073/CE3363 products | W49: Net 30 | X49: Customer liable for loss/damage; full new replacement cost if not returned; mutual indemnity; USME GL $1M/$3M | Y49: Covers Nobis rehab hospitals (e.g., Oklahoma City, Shreveport). Manager has no direct purchase obligation. Initial term ends 11/30/2026 then auto-renews. | Z49: High | AA49: OCR
A50: CuraHealth | B50: Curahealth, LLC | C50: CuraHealth | D50: CuraHealth_MME_Exp12_3_2023_auto_renew.pdf | E50: Master/Rental Agreement | F50: MME Rental, Respiratory | G50: Vizient (Preferred Partnership 90% LOC Tier 3 pricing; no contract # stated) | H50: US Med-Equip, LLC | I50: 2020-12-04 | J50: 2023-12-03 initial; auto-renewed, current term likely through 2026-12-03 | K50: 45263 | L50: Contract text | M50: 46359 | N50: =IF(M50<>"",M50-Summary!$C$3,IF(K50="","",K50-Summary!$C$3)) -> 54 | O50: Active | P50: 3 years | Q50: Auto-renews successive 1-yr terms unless either party cancels in writing 30 days before term end | R50: No termination for convenience; for uncured breach (60-day cure) or insolvency; non-renewal with 30 days notice | S50: Monthly rental rates per Attachment A at Vizient Preferred Partnership 90% LOC Tier 3 pricing; Contract # CH 10122020JD | T50: Not stated | U50: Not stated; equity option: 25% of monthly rental paid (up to 12 months) credited toward purchase | V50: Customer names USME primary first-call vendor for MME rental in exchange for Vizient Preferred Partnership pricing | W50: Monthly rent due on the 1st of each month; customer pays collection/attorney fees on default | X50: Customer responsible for safekeeping, loss/damage and abuse repairs; full replacement cost if not returned in good condition; GL $1M/$3M; mutual indemnity; customer may not assign | Y50: Monthly MME/respiratory rental (ventilators, pumps, monitors, CPMs) to Curahealth. Auto-renewal keeps it in force absent a non-renewal notice; next renewal date ~12/3/2026, cancel notice by ~11/3/2026. | Z50: Medium | AA50: OCR
A51: CHRISTUS Health | B51: CHRISTUS Health | C51: Christus Health | D51: CHRISTUS Refurb Purchase Agreement exp_12_31_2021_auto renew.pdf | E51: Purchase/Sale Agreement | F51: Refurb Equipment Sales, Biomed/Repair Service | G51: Direct | H51: US Med-Equip, Inc. | I51: 2017-01-01; Amendment 2018-07-24 | J51: 2021-12-31 initial; auto-renews 1-yr terms (current term to 2026-12-31 if not terminated) | K51: 44561 | L51: Contract text | M51: 46387 | N51: =IF(M51<>"",M51-Summary!$C$3,IF(K51="","",K51-Summary!$C$3)) -> 82 | O51: Active | P51: 5 years | Q51: Auto-renews successive 1-yr terms | R51: Either party without cause on 30 days written notice; breach w/15-day cure; Facility immediate for cause | S51: Fixed purchase prices per Exhibit A/Attachment 1 (refurb/new Philips, Physio, Zoll defibs; flat repair after warranty); $125/hr bench rate non-warranty | T51: Supplier provides then-current published list price each Jan 1; discounts per table | U51: Not stated | V51: None stated | W51: Monthly invoicing to CHRISTUS AP; terms not legible in excerpt | X51: Broad supplier indemnity; insurance GL $1M/$2M, auto $1M, E&O $1M, cyber $10M, umbrella $1M; no assignment w/o consent; 5-yr/12-mo bench warranties | Y51: Refurbished defibrillator sales and repair agreement; 2018 amendment added products, pricing and participating facilities. Evergreen renewal per text. | Z51: Medium | AA51: OCR
A52: Montage Health (CHOMP) | B52: Community Hospital of the Monterey Peninsula | C52: Community Hospital of the Monterey Peninsula (CHOMP) | D52: CHOMP_BTS_Exp_1_31_26.pdf | E52: Master/Rental Agreement | F52: BTS Rental, MME Rental | G52: Vizient (Tier 4 pricing referenced) | H52: US Med-Equip, LLC | I52: 2023-02-01 | J52: 2026-01-31 initial; auto-renewed, current term through 2027-01-31 | K52: 46053 | L52: Contract text | M52: 46418 | N52: =IF(M52<>"",M52-Summary!$C$3,IF(K52="","",K52-Summary!$C$3)) -> 113 | O52: Active | P52: 3 years | Q52: Auto-renews successive 1-yr terms | R52: Either party without cause, 90 days written notice | S52: Monthly rental fee per Attachment A; Primary Vendor pricing; Vizient Tier 4 daily rates (e.g., Freedom 1000 $67.50/day) | T52: Not stated | U52: Not stated; value adds include 25% rental equity credit (up to 12 months) and 50% lost-equipment buyout credit | V52: Primary Vendor: 90%+ of annual rental spend for Covered Facilities (Attachment B); consignment equipment on site at no charge until used | W52: Net 30; USME may repossess on non-payment | X52: Customer liable for loss/damage and abuse repairs; full new-unit cost if not surrendered in good condition; mutual indemnity; USME GL $1M/$3M; California law | Y52: Consignment model for peak need with customer usage reporting. Contract # UCIMC10112022TH appears carried over from another template. Filename BTS; text covers MME primary vendor and BTS surfaces. | Z52: Medium | AA52: OCR
A53: Infirmary Health | B53: Infirmary Health Hospitals, Inc. d/b/a Infirmary LTAC Hospital | C53: Infirmary LTAC Hospital | D53: Infirmary Health_Vizient_Tier 1_Exp_2_11_2011_Auto renew.pdf | E53: Master/Rental Agreement | F53: MME Rental, Respiratory | G53: Not stated in text (filename says Vizient Tier 1) | H53: US Med-Equip, Inc. | I53: 2018-02-12 | J53: 2021-02-11 initial term; auto-renewing | K53: 44238 | L53: Contract text | M53: 46429 | N53: =IF(M53<>"",M53-Summary!$C$3,IF(K53="","",K53-Summary!$C$3)) -> 124 | O53: Active | P53: 3 years | Q53: Auto-renews successive 1-yr terms unless cancelled 30 days before term end | R53: Non-renewal by either party 30 days before term end; Company may terminate for customer breach (30-day cure) | S53: Primary Vendor pricing per Attachment A (e.g. PB 980 vent $71.14/day, $1,992/mo); 25% equity discount up to 12 months | T53: Not stated | U53: Not stated | V53: Primary vendor: 90%+ of annual MME rental spend | W53: Due on 1st of each month | X53: Customer responsible for loss/damage and abuse repairs; full new-unit cost if not returned; USME CGL $1M/$3M; Alabama law, Mobile County venue | Y53: Contract 02072018, ventilator-focused pricing. Filename 'Exp_2_11_2011' is a typo for 2021. Auto-renews annually, so likely still in effect unless cancelled. | Z53: Medium | AA53: OCR
A54: UCHealth | B54: University of Colorado Health (UCHealth) | C54: University of Colorado Health | D54: UCHealth_BTS_Final Exp 2_2027.pdf | E54: Master/Rental Agreement | F54: BTS Rental | G54: Direct | H54: US Med-Equip, LLC (on behalf of subsidiaries) | I54: 2024-02-26 | J54: 2027-02-25 | K54: 46443 | L54: Contract text | N54: =IF(M54<>"",M54-Summary!$C$3,IF(K54="","",K54-Summary!$C$3)) -> 138 | O54: Active | P54: 3 years | Q54: No automatic renewal; renewals require prior written consent of both parties | R54: Either party without cause after 1st anniversary, 120 days notice; UCHealth may terminate for failed KPI performance or FM >30 days (5 days notice) | S54: Fixed daily rates per Attachment B (beds, WAVE/T-Wave surfaces, bariatric frames/ancillaries); rental fee includes delivery, maintenance, training | T54: Fixed for term; any increase must be mutually agreed in writing | U54: Not stated | V54: USME primary supplier; UCHealth commits 90% of bed/therapeutic surface/bariatric rental; if missed, USME may bill difference to GPO access pricing (failing hospital only) | W54: Net 45 from later of invoice date or receipt; 15 business days notice before credit hold | X54: SLA penalties: 1% if avg delivery >2 hrs + drive time, 1% pickup >24 hrs, uptime 1% penalty <98-99%, EPIC interface delay 2-3%, billing error credits 2-5%; replacement within 1 day; no-hire 12 months | Y54: System-wide BTS agreement for UCHealth facilities (Exhibit D). Annual KPI scorecard and quarterly business reviews; technology upgrade option after year 1 at FMV. | Z54: High | AA54: OCR
A55: Amber Well Health | B55: Amber Well Health Hiawatha | C55: Amber Well | D55: Amber Well Health Hiawatha_Rental_Agreement_Exp_02_28_26.pdf | E55: Master/Rental Agreement | F55: BTS Rental, MME Rental | G55: Direct | H55: US Med-Equip, LLC | I55: 2025-03-01 | J55: 2027-02-28 (current auto-renewal term; initial term ended 2026-02-28) | K55: 46446 | L55: Contract text | N55: =IF(M55<>"",M55-Summary!$C$3,IF(K55="","",K55-Summary!$C$3)) -> 141 | O55: Active | P55: 1 year | Q55: Auto-renews successive 1-yr terms | R55: Either party, 30 days written notice without cause after Initial Term; 60-day cure for breach | S55: Daily/monthly rates per Attachment A; Primary Vendor pricing (BTS + MME cribs) | T55: Fixed until 2nd anniversary (2027-03-01); then max once/yr, greater of 5% or prior-yr Medical Care CPI-U, 30 days notice (email OK) | U55: Not stated | V55: Primary Vendor: 90%+ of annual rental spend; 60-day cure, else list pricing for remainder of term | W55: Net 30; late interest lesser of 1.5%/mo or legal max; credit-hold and list pricing on non-payment | X55: Customer liable for loss/damage and must insure equipment at replacement cost; mutual indemnity; no consequential damages; USME CGL $1M/$3M; full new-unit cost if not surrendered | Y55: Single Kansas critical-access hospital (Hiawatha, KS), contract KS02072025HCH. Mostly BTS (Freedom Wave, Nuvay surfaces) plus cribs. Filename expiry 2/28/26 is end of initial term; auto-renewed. | Z55: High | AA55: OCR
A56: Lehigh Valley Health Network (LVHN) | B56: Lehigh Valley Health Network, Inc. (for its wholly owned non-profit subsidiaries) | C56: Lehigh Valley Health Network (LVHN) | D56: LVHN Equipment and Service Agreement_Exp_3_4_2026_incl amend.pdf | E56: Master/Rental Agreement | F56: MME Rental, BTS Rental, Biomed/Repair Service, Asset Mgmt/On-site | G56: Direct | H56: US Med-Equip, LLC | I56: 2024-03-01 | J56: 2026-02-28 initial; auto-renewed to 2027-02-28 | K56: 46081 | L56: Contract text | M56: 46446 | N56: =IF(M56<>"",M56-Summary!$C$3,IF(K56="","",K56-Summary!$C$3)) -> 141 | O56: Active | P56: 2 years | Q56: Auto-renews 1-yr terms unless 60 days notice | R56: After initial term, either party without cause on 60 days written notice | S56: MME daily/monthly Primary Vendor rates per Attachment A; SOW #1 on-site BMET services $12,395/month (3-yr SOW to 2027-02-28) | T56: Not stated | U56: Not stated | V56: Primary vendor: 90%+ of annual rental spend for Attachment A equipment; 60-day cure, else market rates | W56: Net 30 from invoice; late interest 1.5%/month | X56: 95% monthly fill rate guarantee (USME pays cost difference); customer liable for loss/damage from negligence; mutual indemnity; no consequential damages; CGL $1M/$2M, products $8M, cyber $10M | Y56: Includes Amendment No. 1 (beds at HPG-77980 pricing) and SOW #1 for on-site biomed technician services. Filename exp 3/4/2026 vs text initial term ending ~2/28/2026, now auto-renewed. | Z56: High | AA56: Text
A57: Lehigh Valley Health Network (LVHN) | B57: Lehigh Valley Health Network Inc. (for its wholly owned subsidiaries) | C57: Lehigh Valley Health Network (LVHN) | D57: LVHN Equipment and Service agreement_Exp_2_28_2026.pdf | E57: Master/Rental Agreement | F57: MME Rental, Biomed/Repair Service, Asset Mgmt/On-site | G57: Direct | H57: US Med-Equip, LLC | I57: 2024-03-01 | J57: 2026-02-28 initial; auto-renewed through 2027-02-28 absent notice | K57: 46081 | L57: Contract text | M57: 46446 | N57: =IF(M57<>"",M57-Summary!$C$3,IF(K57="","",K57-Summary!$C$3)) -> 141 | O57: Active | P57: 2 years | Q57: Auto-renews successive 1-yr terms unless 60 days notice before renewal | R57: Either party, 60 days written notice without cause after Initial Term; 60-day cure for breach | S57: Monthly rental fees per Attachment A; Primary Vendor pricing; on-site BMET service fees per SOW Annex 3 | T57: Not stated | U57: Rental equity discount: 25% of monthly rental credit toward buyout (up to 12 months) | V57: Primary Vendor: 90%+ of annual rental spend; 60-day cure, else market rates | W57: Net 30; late interest lesser of 1.5%/month or legal max; 15-day late notice before remedies | X57: 95% monthly fill rate guarantee, USME pays cost difference for substitute products; customer liable for loss/damage only if negligent; insurance: products $8M, E&O $5M, cyber $10M; mutual indemnity | Y57: Combined MME rental and on-site BMET/biomed SOW (RFID tracking, PM/repair of hospital-owned equipment, M-F 8-5). Initial term ended 2/28/2026; auto-renewal likely in effect. | Z57: Medium | AA57: Text
A58: Lehigh Valley Health Network (LVHN) | B58: Lehigh Valley Health Network, Inc. | C58: Lehigh Valley Health Network (LVHN) | D58: LVHN Amendment_Exp_2_28_2026.pdf | E58: Amendment | F58: MME Rental, BTS Rental | G58: HPG-77980 (bed pricing basis) | H58: US Med-Equip, LLC | I58: 2024-03-05 | J58: Not stated (base agreement auto-renews; current term to 2027-02-28) | K58: 46446 | L58: Contract text | N58: =IF(M58<>"",M58-Summary!$C$3,IF(K58="","",K58-Summary!$C$3)) -> 141 | O58: Active | P58: Base: 2 years from 2024-03-01 | Q58: Base auto-renews 1-yr terms | R58: Per base agreement | S58: Adds hospital/specialty bed rentals (bariatric, wound care) for LVH-Macungie and LVH-Gilbertsville at HealthTrust HPG-77980 published pricing | T58: Not stated | U58: Not stated | V58: Not stated | W58: Not stated | X58: Not stated | Y58: Amendment No. 1 clarifies customer as LVHN and its affiliates and adds as-needed bed rentals at two affiliates. Filename exp 2/28/2026 reflects base initial term, which auto-renews. | Z58: High | AA58: Text
A59: Veterans Affairs | B59: Department of Veterans Affairs, Rocky Mountain Regional VA Medical Center (Eastern Colorado VA HCS, NCO 19) | C59: Veteran Affairs - Rocky Mountain Med Ctr | D59: Rocky Mountain Medical Center BTS Exp_3_1_2031.pdf | E59: Purchase/Sale Agreement | F59: BTS Rental | G59: Direct (VA contract 36C25926P0277) | H59: US Med-Equip, LLC | I59: 2026-03-02 | J59: 2027-03-01 (base year); 2031-03-01 if all four option years exercised | K59: 46447 | L59: Contract text | N59: =IF(M59<>"",M59-Summary!$C$3,IF(K59="","",K59-Summary!$C$3)) -> 142 | O59: Active | P59: 1-year base period | Q59: Four 1-yr government options (FAR 52.217-9), total not to exceed 5 years; 52.217-8 up to 6-month extension | R59: Government may terminate for convenience at any time (FAR 52.212-4(l)); for cause with cure notice | S59: Firm daily rates, NTE quantities: VersaTech 600 ULB w/Wave $48.36/day; $107.25/day item; Freedom 1000 w/Advanced Wave XMS $98.88/day | T59: Fixed; same rates in all option years | U59: None | V59: No minimum; orders as needed by designated ordering personnel up to NTE amounts | W59: Net 30; electronic invoicing via Tungsten; Prompt Payment Act interest | X59: FAR commercial terms: no consequential damages; patent indemnity; risk of loss with contractor until acceptance; security prohibitions clause 52.240-91 | Y59: Specialty/bariatric bed and mattress rental for Aurora, CO VA medical center; base year award $50,721, $137,541 total including options. Option years must be exercised by VA each year. | Z59: High | AA59: Text
A60: Wave Healthcare | B60: Wave Healthcare | C60: Wave Healthcare | D60: Wave Healthcare rental Agreement_Exp_03_17_2027_Auto Renew.pdf | E60: Master/Rental Agreement | F60: MME Rental, Respiratory | G60: Direct (Contract # WH03182024JD) | H60: US Med-Equip, LLC | I60: 2024-03-18 | J60: 2027-03-17 | K60: 46463 | L60: Contract text | N60: =IF(M60<>"",M60-Summary!$C$3,IF(K60="","",K60-Summary!$C$3)) -> 158 | O60: Active | P60: 3 years | Q60: Auto-renews successive 1-yr terms | R60: Either party without cause on 30 days notice, only after Initial Term | S60: Monthly rates per Attachment A: Trilogy 100 and Trilogy 200 ventilators $185.00/month | T60: Not stated | U60: Not stated | V60: Primary vendor: 90%+ of annual rental spend | W60: Net 30; collection/attorney costs | X60: Customer liable for repair/replacement of lost/damaged equipment and full new cost if not returned in good condition; mutual indemnity; CGL $1M/$3M; Texas law | Y60: Small ventilator rental agreement with a Texas customer. | Z60: High | AA60: Text
A61: Penn State Health | B61: Penn State Health | C61: Penn State | D61: Penn State_Omnibed_Amendement_exp 03.28.2027.pdf | E61: Amendment | F61: Asset Mgmt/On-site | G61: Direct | H61: US Med-Equip, LLC | I61: 2026-09-29 | J61: 2027-03-28 (not to exceed 180 days) | K61: 46474 | L61: Contract text | N61: =IF(M61<>"",M61-Summary!$C$3,IF(K61="","",K61-Summary!$C$3)) -> 169 | O61: Active | P61: 180 days max | Q61: Extendable if mutually agreeable | R61: Per MSA | S61: Not stated; adds Pay Per Clean: Giraffe Warmers $40, Giraffe Omnibeds $55 | T61: Not stated | U61: Not stated | V61: Not stated | W61: Not stated | X61: Not stated | Y61: Amendment No. 1 to SOW 101424PSH under 2/24/2025 MSA; adds cleaning of Giraffe warmers/Omnibeds at Hampden Medical Center to on-site equipment services scope. Signature block garbled. | Z61: Medium | AA61: Text
A62: UF Health Shands | B62: Shands Jacksonville Medical Center, Inc. (UF Health Jacksonville / UF Health North) | C62: UF Shands Gainesville-Jacksonville | D62: UF Shands Jackson_Exp_4_11_2022_Auto_2023_LR.pdf | E62: Master/Rental Agreement | F62: MME Rental, Respiratory | G62: Vizient CE2534 (Access Tier 1) | H62: US Med-Equip, Inc. | I62: 2019 (OCR: '12th day of Feb(?) 2019'; filename implies ~2019-04-12) | J62: Initial term ~2022 (filename 2022-04-11); auto-renews annually, current term likely to ~2027-04 | K62: 44662 | L62: Contract text | M62: 46488 | N62: =IF(M62<>"",M62-Summary!$C$3,IF(K62="","",K62-Summary!$C$3)) -> 183 | O62: Active | P62: 3 years | Q62: Auto-renews successive 1-yr terms unless either party cancels in writing 30 days prior to desired termination date | R62: Either party by written cancellation 30 days prior (renewal terms); for breach after 30-day cure; insolvency | S62: Monthly rental per Vizient CE2534 Access Tier 1 pricing (infusion, respiratory, NICU/L&D, monitoring, central supply); proposal: IPV-1C $17.68/day, $495/mo | T62: Not stated | U62: Not stated; equity option 25% of monthly rental paid (up to 12 months) toward purchase | V62: None stated | W62: Monthly rent due 1st of each month | X62: Customer responsible for safekeeping and loss/damage; abuse repairs at customer cost; GL $1M/$3M; mutual consent to assign; equipment pickup cannot affect patient care | Y62: USME Contract # R51618PP for UF Health Jacksonville MME rental. Effective date OCR is unclear and conflicts slightly with filename's 4/11 anniversary; 'Auto_2023_LR' filename tag suggests auto-renewal was being tracked. | Z62: Medium | AA62: OCR
A63: State of Louisiana | B63: State of Louisiana (Office of State Procurement) | C63: State of Louisiana | D63: 4400029974 - Emergency Rental of Hospital Beds - SW.pdf | E63: Master/Rental Agreement | F63: BTS Rental | G63: Direct (LA contract 4400029974) | H63: US Med-Equip Inc | I63: 2024-06-28 (current renewal 2026-05-01) | J63: 2027-04-30 | K63: 46507 | L63: Contract text | N63: =IF(M63<>"",M63-Summary!$C$3,IF(K63="","",K63-Summary!$C$3)) -> 202 | O63: Active | P63: 12 months per renewal; total max 36 months | Q63: Annual renewals; total term not to exceed 36 months | R63: State: for convenience on 30 days written notice; for cause on 30 days; non-appropriation | S63: $33.99/day per hospital bed (Paramount A6), per Attachment B | T63: Not stated (fixed unit price) | U63: Not stated | V63: Non-exclusive; no guaranteed quantities; USME committed 50+ beds within 12-24 hrs, 24+ per day | W63: Not stated (unit price basis; invoices to using agency) | X63: Broad indemnity of State; CGL $1M/$2M, auto $1M, WC/EL $1M, State as additional insured; detainment/reroute charges $125 | Y63: Statewide emergency contingency contract to rent hospital beds during Governor-declared emergencies; 24/7 availability, delivery 8-24 hrs, inside delivery at no charge. | Z63: High | AA63: Text
A64: State of Louisiana | B64: State of Louisiana, Office of State Procurement | C64: State of Louisiana | D64: Renewal Notification 4400029974.pdf | E64: Extension | F64: BTS Rental | G64: Direct (State Contract 4400029974, T-Number 92821) | H64: US Med-Equip, Inc. (as written) | I64: 2026-05-01 | J64: 2027-04-30 | K64: 46507 | L64: Contract text | N64: =IF(M64<>"",M64-Summary!$C$3,IF(K64="","",K64-Summary!$C$3)) -> 202 | O64: Active | P64: Not stated (renewal of 12 months) | Q64: State exercised renewal option for 12 months at original terms | R64: Per original contract termination provisions (not stated here) | S64: Original terms, conditions and prices/discounts | T64: None (renewed at original prices) | U64: Not stated | V64: Not stated | W64: Not stated | X64: Not stated | Y64: State renewal notice for emergency hospital bed rental contract (Southwest region). USME must submit a contract usage report about 4 months before 4/30/2027 (around Jan 2027). Entity named 'US Med-Equip, Inc.' | Z64: High | AA64: Text
A65: LHC Group | B65: LHC Group, Inc. | C65: LHC | D65: LHC _EXP_5_14_2020_Auto_2024.pdf | E65: Master/Rental Agreement | F65: MME Rental | G65: Direct | H65: US Med-Equip, Inc. | I65: 2019-05-15 | J65: 2027-05-14 (current auto-renewal term, if never cancelled) | K65: 46521 | L65: Contract text | N65: =IF(M65<>"",M65-Summary!$C$3,IF(K65="","",K65-Summary!$C$3)) -> 216 | O65: Active | P65: 1 year | Q65: Auto-renews successive 1-yr terms unless either party cancels 30 days before term end | R65: Customer only: any time on 60 days written notice; breach with 60-day cure | S65: Daily/monthly rates per Attachment A (Sole Source Vendor pricing); 25% equity discount toward buyout up to 12 months | T65: Not stated | U65: Not stated | V65: Sole source: 90%+ of annual MME rental spend | W65: Due 30 days from receipt of invoice | X65: Customer liable for loss/damage from negligence and abuse plus USME enforcement costs; full new-unit cost if not surrendered; USME CGL $1M/$3M; lost-equipment 50% buyout credit | Y65: Contract LHC040819TH. Filename 'Auto_2024' implies renewals tracked only through 2024; text auto-renews indefinitely, so confirm whether still billing. | Z65: Medium | AA65: OCR
A66: ClearSky Health | B66: ClearSky Health | C66: ClearSky Health | D66: ClearSky Health MME BTS Exp_5_31_26_LR.pdf | E66: Master/Rental Agreement | F66: MME Rental | G66: Direct | H66: US Med-Equip, LLC | I66: 2023-06-01 | J66: 2027-05-31 (current auto-renewal term; initial term ended 2026-05-31) | K66: 46538 | L66: Contract text | N66: =IF(M66<>"",M66-Summary!$C$3,IF(K66="","",K66-Summary!$C$3)) -> 233 | O66: Active | P66: 3 years | Q66: Auto-renews successive 1-yr terms | R66: Either party, 30 days written notice without cause (any time) | S66: Monthly rental rates per Attachment A; Primary Vendor pricing | T66: Not stated | U66: Not stated | V66: Primary Vendor: 90%+ of annual MME rental spend for Attachment B facilities | W66: Net 30 | X66: Customer liable for loss/damage and abuse repairs plus USME enforcement/collection costs; full new-unit cost if not surrendered; USME CGL $1M/$3M; customer may not assign without consent | Y66: Contract 06082023LR with New Mexico rehab operator. Only MME monthly pricing visible in OCR (no BTS pricing found despite 'MME BTS' filename). Attachment B facility list not captured. | Z66: Medium | AA66: OCR
A67: Smith & Nephew | B67: Smith & Nephew, Inc. | C67: Smith + Nephew | D67: SN Amendment to Master Service Agrmt_2022_exp_6_1_2027.pdf | E67: Amendment | F67: MME Rental, Other | G67: Direct | H67: US Med-Equip, LLC (assignee of US Med-Equip, Inc.) | I67: 2022-06-01 (amends MSA and SOW No. 1 effective 2019-03-04) | J67: 2027-06-01 | K67: 46539 | L67: Contract text | N67: =IF(M67<>"",M67-Summary!$C$3,IF(K67="","",K67-Summary!$C$3)) -> 234 | O67: Active | P67: Amendment term 2022-06-01 to 2027-06-01; MSA continues while any SOW in effect | Q67: Not stated | R67: Either party, with or without cause, 120 days written notice (MSA or any SOW); for uncured breach (30 days) or insolvency | S67: Not stated in amendment (per underlying MSA/SOW No. 1) | T67: Not stated | U67: Not stated | V67: USME must rent exclusively S&N RENASYS NPWT pumps to S&N customers and to its other NPWT customers (with exceptions); S&N uses USME as exclusive peak rental provider where not constrained/out of coverage | W67: Not stated | X67: Mutual exclusivity obligations; underlying MSA terms govern other risk items | Y67: Vendor partnership: USME provides peak and daily rental of Smith & Nephew NPWT (RENASYS) pumps to S&N customers. Amendment signed 6/1/2022 (DocuSign 9/19/2022); USME exclusivity restricts offering competing NPWT pumps. | Z67: High | AA67: OCR
A68: STERILECO / VA North Texas Health Care System | B68: STERILECO LLC (prime contractor) | C68: Serileco LLC | D68: STERILECO_MME_Exp 06_07_2028.pdf | E68: Service Agreement/SOW | F68: Biomed/Repair Service, Respiratory | G68: Direct (Subcontract STERILECO-SUB-26-0077 under federal prime contract) | H68: US Med-Equip | I68: 2026-05-07 (signature); base period starts 2026-06-06 | J68: 2027-06-05 base; 2028-06-07 if option year exercised | K68: 46543 | L68: Contract text | N68: =IF(M68<>"",M68-Summary!$C$3,IF(K68="","",K68-Summary!$C$3)) -> 238 | O68: Active | P68: 1 base year + 1 option year | Q68: One option year at STERILECO's unilateral election; STERILECO may require extension at same rates | R68: STERILECO for convenience only if government terminates its prime contract; USME may terminate for convenience on 30 days written notice (performance continues during notice); default with 10-day cure | S68: Firm fixed unit price per CLIN: Hamilton MR-1 and G5 ventilator annual service contracts; total ~$95,430 | T68: No price increase on option exercise; rate changes only for wage law mandates via good-faith negotiation | U68: Not stated | V68: Non-exclusive; work only on funded Orders; funding may be incremental | W68: Net 30 from receipt of correct invoice; ACH; payments withheld without valid COI | X68: USME indemnifies STERILECO; FAR government property liability; no direct contact with end customer; minimum insurance GL $500K, employer liability $100K; NCR quality process | Y68: Subcontract for OEM-spec service of Hamilton G5/MR-1 ventilators at VA Medical Center Dallas (VANTHCS); signed by Clay Rose as CEO. Filename labels it MME but scope is biomed service. | Z68: High | AA68: Text
A69: Banner Health | B69: Banner Health | C69: Banner Health | D69: Banner_MME_Exp_6_30_2025_Auto_2026_LR.pdf | E69: Master/Rental Agreement | F69: MME Rental, Respiratory | G69: Direct | H69: US Med-Equip, LLC | I69: 2022-07-01 | J69: 2027-06-30 (initial term ended 2025-06-30; auto-renews annually) | K69: 46568 | L69: Contract text | N69: =IF(M69<>"",M69-Summary!$C$3,IF(K69="","",K69-Summary!$C$3)) -> 263 | O69: Active | P69: 3 years | Q69: Auto-renews successive 1-yr terms | R69: Either party, without cause, 30 days written notice | S69: Second-call vendor pricing per Attachment A (daily/monthly rates, e.g., Servo-i $62.98/day) | T69: Not stated | U69: None; 25% rental equity credit toward buyout (up to 12 months); 50% lost-equipment buyout credit with 3 RFID scans | V69: Second-call vendor status only (called when primary MME supplier cannot fill) | W69: Monthly rent due 1st of month; repossession right for non-payment | X69: Customer liable for loss/damage/abuse; full new-equipment replacement cost if not returned in good condition; customer pays collection/attorney fees; CGL $1M/$3M; Texas law, Harris County venue | Y69: Contract #BH06212022JD. USME is second-call, not primary, for Banner covered facilities (Attachment B). Text auto-renewal consistent with filename 'Auto'. | Z69: High | AA69: Text
A70: HCA Healthcare / HealthTrust (HPG) | B70: HealthTrust Purchasing Group, L.P. (HealthTrust and HCA) | C70: GPO/HealthTrust | D70: HPG MME S2_7093_Amendment_extension_exp 6_30_2027.pdf | E70: Extension | F70: MME Rental | G70: HPG agreement no. 143302 (filed under HPG-7093) | H70: US Med-Equip, LLC | I70: 2026-07-01 | J70: 2027-06-30 | K70: 46568 | L70: Contract text | N70: =IF(M70<>"",M70-Summary!$C$3,IF(K70="","",K70-Summary!$C$3)) -> 263 | O70: Active | P70: Original agreement dated 2020-08-01 | Q70: Extension to 2027-06-30 | R70: Not stated (per underlying agreement) | S70: Not stated (unchanged per underlying agreement) | T70: Not stated | U70: Not stated | V70: Not stated | W70: Not stated | X70: Not stated | Y70: One-page amendment extending the Aug 1, 2020 HCA/HealthTrust MME pricing agreement (No. 143302) to 6/30/2027; signed by Doug Murray (CRO) June 2026. Text references both 'Pricing Agreement' and 'Purchasing Agreement'. | Z70: High | AA70: Text
